verilog/verilog_seminar/20bits-carry-selector-adder/d_ff2.v
module d_ff2 (q,clk,reset,out);

input [20:0]q;
input clk;
input reset;
output reg [20:0]out;

always@ (posedge clk)
begin
    if(~reset)
    begin
        out <= 21'b0;
    end
    else 
    begin
        out <= q;
    end

end

endmodule

verilog/20bits-carry-selector-adder/d_ff.v
module d_ff (q,clk,reset,out);

input [4:0] q;
input clk;
input reset;
output reg [4:0] out;

always@ (posedge clk)
begin
if(~reset)
    begin
        out<= 5'b00000;
    end
else
    begin
        out <= q;
    end
end

endmodule

verilog/verilog_seminar/20bits-carry-selector-adder/Mux.v
module Mux_2to1 (A,B,Sel,Out,Carry);

input [4:0] A,B; // A,B는 계산되어서 들어오는 값임. 원래 입력되는 값 X
input Sel;
output reg Carry;
output reg [3:0] Out; // MSB는 carry_out임 헷갈리지 마셈.

always @ * begin
    case(Sel)
    1'b0 : begin
            Out[3:0] <= A[3:0];  // 계산한 값은 d_ff에 넣어주고
            Carry <= A[4];       // 케리는 옆에 adder로 넘겨주기
           end
    1'b1 : begin 
            Out[3:0] <= B[3:0];
            Carry <= B[4];
           end
    endcase
end

endmodule

verilog/verilog_seminar/20bits-carry-selector-adder/CSA.v
`include "Mux.v"
`include "d_ff.v"
`include "d_ff2.v"

module CSA (A,B,Out,clk,reset);

input clk,reset;
input [19:0] A,B;
input wire C_in;
reg [4:0] d_ff000,d_ff001,
          d_ff100,d_ff101,
          d_ff200,d_ff201,
          d_ff300,d_ff301,
          d_ff400,d_ff401;
output wire [20:0] Out;
output wire [4:0]Carry;
wire [4:0]Mux_in00, Mux_in01, Mux_in10, Mux_in11,
          Mux_in20, Mux_in21, Mux_in30, Mux_in31,
          Mux_in40, Mux_in41;
wire [19:0]Sum;



Mux_2to1 mux0 (Mux_in00, Mux_in01, 1'b0,     Sum[3:0],   Carry[0]);
Mux_2to1 mux1 (Mux_in10, Mux_in11, Carry[0], Sum[7:4],   Carry[1]);
Mux_2to1 mux2 (Mux_in20, Mux_in21, Carry[1], Sum[11:8],  Carry[2]);
Mux_2to1 mux3 (Mux_in30, Mux_in31, Carry[2], Sum[15:12], Carry[3]);
Mux_2to1 mux4 (Mux_in40, Mux_in41, Carry[3], Sum[19:16], Carry[4]);

d_ff d00 (d_ff000,clk,reset,Mux_in00);
d_ff d01 (d_ff001,clk,reset,Mux_in01);
d_ff d10 (d_ff100,clk,reset,Mux_in10);
d_ff d11 (d_ff101,clk,reset,Mux_in11);
d_ff d20 (d_ff200,clk,reset,Mux_in20);
d_ff d21 (d_ff201,clk,reset,Mux_in21);
d_ff d30 (d_ff300,clk,reset,Mux_in30);
d_ff d31 (d_ff301,clk,reset,Mux_in31);
d_ff d40 (d_ff400,clk,reset,Mux_in40);
d_ff d41 (d_ff401,clk,reset,Mux_in41);

d_ff2 d200 ({Carry[4],Sum},clk,reset,Out);


always @ * begin
    d_ff000[4:0] <= A[3:0] + B[3:0] + 1'b0;
    d_ff001[4:0] <= A[3:0] + B[3:0] + 1'b1;

    d_ff100[4:0] <= A[7:4] + B[7:4] + 1'b0;
    d_ff101[4:0] <= A[7:4] + B[7:4] + 1'b1;

    d_ff200[4:0] <= A[11:8] + B[11:8] + 1'b0;
    d_ff201[4:0] <= A[11:8] + B[11:8] + 1'b1;

    d_ff300[4:0] <= A[15:12] + B[15:12] + 1'b0;
    d_ff301[4:0] <= A[15:12] + B[15:12] + 1'b1;

    d_ff400[4:0] <= A[19:16] + B[19:16] + 1'b0;
    d_ff401[4:0] <= A[19:16] + B[19:16] + 1'b1;
end

endmodule

verilog/verilog_seminar/20bits-carry-selector-adder/stimulus_carry_select_adder_20b.v
`include "CSA.v"  // 앞에서 만든 CSA를 불로 옴.
`timescale 100ps/1ps // #1 = 100ps를 쉰다. 오차 시간 = 1ps
module stimulus_carry_select_adder_20b; // 모듈 이름

wire [20:0] sum; // 합계
reg [19:0] a, b; // 입력되는 숫자
reg clk;   // 클락
reg reset; // 리셋 기능을 위한 변수

reg [19:0] mat_a_input [0:99]; // 100행 20열 짜리 레지스털
reg [19:0] mat_b_input [0:99];
reg [20:0] mat_sum_output [0:99];

initial
begin
	clk <= 1;
	reset <= 0;
	#10
	reset <= 1;
end

always #5 clk <= ~clk;


CSA csa0 (.Out(sum), .A(a), .B(b), .clk(clk), .reset(reset));


integer i;
initial
begin
    $dumpfile("stimulus_carry_select_adder_20b.vcd");
    $dumpvars(0,stimulus_carry_select_adder_20b);
	$readmemh("a_input_20b.txt", mat_a_input);
	$readmemh("b_input_20b.txt", mat_b_input);
	i = 0;
	#(10);

	for(i = 0; i < 100; i++)
	begin
		a = mat_a_input[i];
		b = mat_b_input[i];
		#(10);
	end
	$finish;
end

integer k;
integer err;
reg [22:0] mat_sum;

initial
begin
    $dumpfile("stimulus_carry_select_adder_20b.vcd");
    $dumpvars(0,stimulus_carry_select_adder_20b);
	$readmemh("sum_output_20b.txt", mat_sum_output);
	err = 0;
	k = 0;
	#(20);

	for(k = 0; k < 100; k = k + 1)
	begin
		mat_sum <= mat_sum_output[k];
		if((sum != mat_sum))
			err = err + 1;
		#(10);
	end
$finish;

end


endmodule

verilog/20bits-carry-selector-adder/stimulus_carry_select_adder_20b.vcd
$date
	Mon Aug 19 19:57:01 2019
$end
$version
	Icarus Verilog
$end
$timescale
	1ps
$end
$scope module stimulus_carry_select_adder_20b $end
$var wire 21 ! sum [20:0] $end
$var reg 20 " a [19:0] $end
$var reg 20 # b [19:0] $end
$var reg 1 $ clk $end
$var reg 23 % mat_sum [22:0] $end
$var reg 1 & reset $end
$var integer 32 ' err [31:0] $end
$var integer 32 ( i [31:0] $end
$var integer 32 ) k [31:0] $end
$scope module csa0 $end
$var wire 20 * A [19:0] $end
$var wire 20 + B [19:0] $end
$var wire 1 , C_in $end
$var wire 1 $ clk $end
$var wire 1 & reset $end
$var wire 20 - Sum [19:0] $end
$var wire 21 . Out [20:0] $end
$var wire 5 / Mux_in41 [4:0] $end
$var wire 5 0 Mux_in40 [4:0] $end
$var wire 5 1 Mux_in31 [4:0] $end
$var wire 5 2 Mux_in30 [4:0] $end
$var wire 5 3 Mux_in21 [4:0] $end
$var wire 5 4 Mux_in20 [4:0] $end
$var wire 5 5 Mux_in11 [4:0] $end
$var wire 5 6 Mux_in10 [4:0] $end
$var wire 5 7 Mux_in01 [4:0] $end
$var wire 5 8 Mux_in00 [4:0] $end
$var wire 5 9 Carry [4:0] $end
$var reg 5 : d_ff000 [4:0] $end
$var reg 5 ; d_ff001 [4:0] $end
$var reg 5 < d_ff100 [4:0] $end
$var reg 5 = d_ff101 [4:0] $end
$var reg 5 > d_ff200 [4:0] $end
$var reg 5 ? d_ff201 [4:0] $end
$var reg 5 @ d_ff300 [4:0] $end
$var reg 5 A d_ff301 [4:0] $end
$var reg 5 B d_ff400 [4:0] $end
$var reg 5 C d_ff401 [4:0] $end
$scope module d00 $end
$var wire 1 $ clk $end
$var wire 5 D q [4:0] $end
$var wire 1 & reset $end
$var reg 5 E out [4:0] $end
$upscope $end
$scope module d01 $end
$var wire 1 $ clk $end
$var wire 5 F q [4:0] $end
$var wire 1 & reset $end
$var reg 5 G out [4:0] $end
$upscope $end
$scope module d10 $end
$var wire 1 $ clk $end
$var wire 5 H q [4:0] $end
$var wire 1 & reset $end
$var reg 5 I out [4:0] $end
$upscope $end
$scope module d11 $end
$var wire 1 $ clk $end
$var wire 5 J q [4:0] $end
$var wire 1 & reset $end
$var reg 5 K out [4:0] $end
$upscope $end
$scope module d20 $end
$var wire 1 $ clk $end
$var wire 5 L q [4:0] $end
$var wire 1 & reset $end
$var reg 5 M out [4:0] $end
$upscope $end
$scope module d200 $end
$var wire 1 $ clk $end
$var wire 21 N q [20:0] $end
$var wire 1 & reset $end
$var reg 21 O out [20:0] $end
$upscope $end
$scope module d21 $end
$var wire 1 $ clk $end
$var wire 5 P q [4:0] $end
$var wire 1 & reset $end
$var reg 5 Q out [4:0] $end
$upscope $end
$scope module d30 $end
$var wire 1 $ clk $end
$var wire 5 R q [4:0] $end
$var wire 1 & reset $end
$var reg 5 S out [4:0] $end
$upscope $end
$scope module d31 $end
$var wire 1 $ clk $end
$var wire 5 T q [4:0] $end
$var wire 1 & reset $end
$var reg 5 U out [4:0] $end
$upscope $end
$scope module d40 $end
$var wire 1 $ clk $end
$var wire 5 V q [4:0] $end
$var wire 1 & reset $end
$var reg 5 W out [4:0] $end
$upscope $end
$scope module d41 $end
$var wire 1 $ clk $end
$var wire 5 X q [4:0] $end
$var wire 1 & reset $end
$var reg 5 Y out [4:0] $end
$upscope $end
$scope module mux0 $end
$var wire 5 Z A [4:0] $end
$var wire 5 [ B [4:0] $end
$var wire 1 \ Sel $end
$var reg 1 ] Carry $end
$var reg 4 ^ Out [3:0] $end
$upscope $end
$scope module mux1 $end
$var wire 5 _ A [4:0] $end
$var wire 5 ` B [4:0] $end
$var wire 1 a Sel $end
$var reg 1 b Carry $end
$var reg 4 c Out [3:0] $end
$upscope $end
$scope module mux2 $end
$var wire 5 d A [4:0] $end
$var wire 5 e B [4:0] $end
$var wire 1 f Sel $end
$var reg 1 g Carry $end
$var reg 4 h Out [3:0] $end
$upscope $end
$scope module mux3 $end
$var wire 5 i A [4:0] $end
$var wire 5 j B [4:0] $end
$var wire 1 k Sel $end
$var reg 1 l Carry $end
$var reg 4 m Out [3:0] $end
$upscope $end
$scope module mux4 $end
$var wire 5 n A [4:0] $end
$var wire 5 o B [4:0] $end
$var wire 1 p Sel $end
$var reg 1 q Carry $end
$var reg 4 r Out [3:0] $end
$upscope $end
$upscope $end
$upscope $end
$scope module stimulus_carry_select_adder_20b $end
$scope module csa0 $end
$scope module d00 $end
$upscope $end
$scope module d01 $end
$upscope $end
$scope module d10 $end
$upscope $end
$scope module d11 $end
$upscope $end
$scope module d20 $end
$upscope $end
$scope module d200 $end
$upscope $end
$scope module d21 $end
$upscope $end
$scope module d30 $end
$upscope $end
$scope module d31 $end
$upscope $end
$scope module d40 $end
$upscope $end
$scope module d41 $end
$upscope $end
$scope module mux0 $end
$upscope $end
$scope module mux1 $end
$upscope $end
$scope module mux2 $end
$upscope $end
$scope module mux3 $end
$upscope $end
$scope module mux4 $end
$upscope $end
$upscope $end
$upscope $end
$enddefinitions $end
#0
$dumpvars
b0 r
0q
0p
b0 o
b0 n
b0 m
0l
0k
b0 j
b0 i
b0 h
0g
0f
b0 e
b0 d
b0 c
0b
0a
b0 `
b0 _
b0 ^
0]
0\
b0 [
b0 Z
b0 Y
bx X
b0 W
bx V
b0 U
bx T
b0 S
bx R
b0 Q
bx P
b0 O
b0 N
b0 M
bx L
b0 K
bx J
b0 I
bx H
b0 G
bx F
b0 E
bx D
bx C
bx B
bx A
bx @
bx ?
bx >
bx =
bx <
bx ;
bx :
b0 9
b0 8
b0 7
b0 6
b0 5
b0 4
b0 3
b0 2
b0 1
b0 0
b0 /
b0 .
b0 -
z,
bx +
bx *
b0 )
b0 (
b0 '
0&
bx %
1$
bx #
bx "
b0 !
$end
#500
0$
#1000
1k
1a
b1111 r
b1010 m
1g
b1 h
b110 c
b101 9
1]
b11111010000101100111 N
b11111010000101100111 -
b111 ^
b10000 /
b10000 Y
b10000 o
b1111 0
b1111 W
b1111 n
b1010 1
b1010 U
b1010 j
b1001 2
b1001 S
b1001 i
b10010 3
b10010 Q
b10010 e
b10001 4
b10001 M
b10001 d
b110 5
b110 K
b110 `
b101 6
b101 I
b101 _
b11000 7
b11000 G
b11000 [
b10111 8
b10111 E
b10111 Z
b10000 C
b10000 X
b1111 B
b1111 V
b1010 A
b1010 T
b1001 @
b1001 R
b10010 ?
b10010 P
b10001 >
b10001 L
b110 =
b110 J
b101 <
b101 H
b11000 ;
b11000 F
b10111 :
b10111 D
1$
1&
b101001100001001100 #
b101001100001001100 +
b11010000100100011011 "
b11010000100100011011 *
#1500
0$
#2000
1p
b10 ^
b1000 c
b11 h
1l
b11 m
b11101 9
1q
b110110011001110000010 N
b10110011001110000010 -
b1011 r
b10010 8
b10010 E
b10010 Z
b10011 7
b10011 G
b10011 [
b111 6
b111 I
b111 _
b1000 5
b1000 K
b1000 `
b10011 4
b10011 M
b10011 d
b10100 3
b10100 Q
b10100 e
b10010 2
b10010 S
b10010 i
b10011 1
b10011 U
b10011 j
b11010 0
b11010 W
b11010 n
b11011 /
b11011 Y
b11011 o
b11111010000101100111 !
b11111010000101100111 .
b11111010000101100111 O
b11011 C
b11011 X
b11010 B
b11010 V
b10011 A
b10011 T
b10010 @
b10010 R
b10100 ?
b10100 P
b10011 >
b10011 L
b1000 =
b1000 J
b111 <
b111 H
b10011 ;
b10011 F
b10010 :
b10010 D
1$
b11111010000101100111 %
b11001011010101100011 #
b11001011010101100011 +
b11100111111000011111 "
b11100111111000011111 *
b1 (
#2500
0$
#3000
0a
0q
b111 r
b0 m
b10 h
b1101 c
b1100 9
0]
b1110000001011011111 N
b1110000001011011111 -
b1111 ^
b110110011001110000010 !
b110110011001110000010 .
b110110011001110000010 O
b111 /
b111 Y
b111 o
b110 0
b110 W
b110 n
b10000 1
b10000 U
b10000 j
b1111 2
b1111 S
b1111 i
b10011 3
b10011 Q
b10011 e
b10010 4
b10010 M
b10010 d
b1110 5
b1110 K
b1110 `
b1101 6
b1101 I
b1101 _
b10000 7
b10000 G
b10000 [
b1111 8
b1111 E
b1111 Z
b111 C
b111 X
b110 B
b110 V
b10000 A
b10000 T
b1111 @
b1111 R
b10011 ?
b10011 P
b10010 >
b10010 L
b1110 =
b1110 J
b1101 <
b1101 H
b10000 ;
b10000 F
b1111 :
b1111 D
1$
b110110011001110000010 %
b1001111101010111100 #
b1001111101010111100 +
b100000100000100011 "
b100000100000100011 *
b10 (
b1 )
#3500
0$
#4000
1f
1b
b0 c
b10 h
b101110001001000001111 N
b1110001001000001111 -
b1 m
b11110 9
1q
b10000 6
b10000 I
b10000 _
b10001 5
b10001 K
b10001 `
b10001 4
b10001 M
b10001 d
b10010 3
b10010 Q
b10010 e
b10000 2
b10000 S
b10000 i
b10001 1
b10001 U
b10001 j
b10110 0
b10110 W
b10110 n
b10111 /
b10111 Y
b10111 o
b1110000001011011111 !
b1110000001011011111 .
b1110000001011011111 O
b10111 C
b10111 X
b10110 B
b10110 V
b10001 A
b10001 T
b10000 @
b10000 R
b10010 ?
b10010 P
b10001 >
b10001 L
b10001 =
b10001 J
b10000 <
b10000 H
1$
b1110000001011011111 %
b10000111010011011111 #
b10000111010011011111 +
b11101001110100110000 "
b11101001110100110000 *
b11 (
b10 )
#4500
0$
#5000
0p
0f
1a
0q
b1100 r
0l
b1100 m
b100 h
0b
b1010 c
b101 9
1]
b11001100010010100011 N
b11001100010010100011 -
b11 ^
b101110001001000001111 !
b101110001001000001111 .
b101110001001000001111 O
b1101 /
b1101 Y
b1101 o
b1100 0
b1100 W
b1100 n
b1100 1
b1100 U
b1100 j
b1011 2
b1011 S
b1011 i
b10101 3
b10101 Q
b10101 e
b10100 4
b10100 M
b10100 d
b1010 5
b1010 K
b1010 `
b1001 6
b1001 I
b1001 _
b10100 7
b10100 G
b10100 [
b10011 8
b10011 E
b10011 Z
b1101 C
b1101 X
b1100 B
b1100 V
b1100 A
b1100 T
b1011 @
b1011 R
b10101 ?
b10101 P
b10100 >
b10100 L
b1010 =
b1010 J
b1001 <
b1001 H
b10100 ;
b10100 F
b10011 :
b10011 D
1$
b101110001001000001111 %
b101010011001111111 #
b101010011001111111 +
b10100001111000100100 "
b10100001111000100100 *
b100 (
b11 )
#5500
0$
#6000
0a
1f
1p
0]
b1101 ^
1b
b11 c
b1 h
b1110 9
1l
b11 m
b10110011000100111101 N
b10110011000100111101 -
b1011 r
b1101 8
b1101 E
b1101 Z
b1110 7
b1110 G
b1110 [
b10011 6
b10011 I
b10011 _
b10100 5
b10100 K
b10100 `
b10000 4
b10000 M
b10000 d
b10001 3
b10001 Q
b10001 e
b10010 2
b10010 S
b10010 i
b10011 1
b10011 U
b10011 j
b1010 0
b1010 W
b1010 n
b1011 /
b1011 Y
b1011 o
b11001100010010100011 !
b11001100010010100011 .
b11001100010010100011 O
b1011 C
b1011 X
b1010 B
b1010 V
b10011 A
b10011 T
b10010 @
b10010 R
b10001 ?
b10001 P
b10000 >
b10000 L
b10100 =
b10100 J
b10011 <
b10011 H
b1110 ;
b1110 F
b1101 :
b1101 D
1$
b11001100010010100011 %
b10011010000110110111 #
b10011010000110110111 +
b11000111110000110 "
b11000111110000110 *
b101 (
b100 )
#6500
0$
#7000
0p
0k
0f
b1000 r
0l
b1010 m
0g
b1001 h
b0 9
0b
b1101 c
b10001010100111011011 N
b10001010100111011011 -
b1011 ^
b10110011000100111101 !
b10110011000100111101 .
b10110011000100111101 O
b1001 /
b1001 Y
b1001 o
b1000 0
b1000 W
b1000 n
b1011 1
b1011 U
b1011 j
b1010 2
b1010 S
b1010 i
b1010 3
b1010 Q
b1010 e
b1001 4
b1001 M
b1001 d
b1110 5
b1110 K
b1110 `
b1101 6
b1101 I
b1101 _
b1100 7
b1100 G
b1100 [
b1011 8
b1011 E
b1011 Z
b1001 C
b1001 X
b1000 B
b1000 V
b1011 A
b1011 T
b1010 @
b1010 R
b1010 ?
b1010 P
b1001 >
b1001 L
b1110 =
b1110 J
b1101 <
b1101 H
b1100 ;
b1100 F
b1011 :
b1011 D
1$
b10110011000100111101 %
b1000011010100100001 #
b1000011010100100001 +
b1000111010010111010 "
b1000111010010111010 *
b110 (
b101 )
#7500
0$
#8000
1a
1p
1]
b1 ^
b10 c
b111 h
1l
b11 m
b11001 9
1q
b100110011011100100001 N
b110011011100100001 -
b11 r
b10001 8
b10001 E
b10001 Z
b10010 7
b10010 G
b10010 [
b1 6
b1 I
b1 _
b10 5
b10 K
b10 `
b111 4
b111 M
b111 d
b1000 3
b1000 Q
b1000 e
b10011 2
b10011 S
b10011 i
b10100 1
b10100 U
b10100 j
b10010 0
b10010 W
b10010 n
b10011 /
b10011 Y
b10011 o
b10001010100111011011 !
b10001010100111011011 .
b10001010100111011011 O
b10011 C
b10011 X
b10010 B
b10010 V
b10100 A
b10100 T
b10011 @
b10011 R
b1000 ?
b1000 P
b111 >
b111 L
b10 =
b10 J
b1 <
b1 H
b10010 ;
b10010 F
b10001 :
b10001 D
1$
b10001010100111011011 %
b10100111011100011011 #
b10100111011100011011 +
b10001100000000000110 "
b10001100000000000110 *
b111 (
b110 )
#8500
0$
#9000
0p
0f
0a
b1010 r
0l
b101 m
b1000 h
0b
b1111 c
b10000 9
0]
b110100101100011110111 N
b10100101100011110111 -
b111 ^
b100110011011100100001 !
b100110011011100100001 .
b100110011011100100001 O
b11011 /
b11011 Y
b11011 o
b11010 0
b11010 W
b11010 n
b110 1
b110 U
b110 j
b101 2
b101 S
b101 i
b1001 3
b1001 Q
b1001 e
b1000 4
b1000 M
b1000 d
b10000 5
b10000 K
b10000 `
b1111 6
b1111 I
b1111 _
b1000 7
b1000 G
b1000 [
b111 8
b111 E
b111 Z
b11011 C
b11011 X
b11010 B
b11010 V
b110 A
b110 T
b101 @
b101 R
b1001 ?
b1001 P
b1000 >
b1000 L
b10000 =
b10000 J
b1111 <
b1111 H
b1000 ;
b1000 F
b111 :
b111 D
1$
b100110011011100100001 %
b10110000011100000101 #
b10110000011100000101 +
b11110101000111110010 "
b11110101000111110010 *
b1000 (
b111 )
#9500
0$
#10000
b1011 r
1a
1p
1]
b1011 ^
b1001 c
b11001 9
1l
b110110110100010011011 N
b10110110100010011011 -
b110 m
b11011 8
b11011 E
b11011 Z
b11100 7
b11100 G
b11100 [
b1000 6
b1000 I
b1000 _
b1001 5
b1001 K
b1001 `
b10110 2
b10110 S
b10110 i
b10111 1
b10111 U
b10111 j
b110100101100011110111 !
b110100101100011110111 .
b110100101100011110111 O
b10111 A
b10111 T
b10110 @
b10110 R
b1001 =
b1001 J
b1000 <
b1000 H
b11100 ;
b11100 F
b11011 :
b11011 D
1$
b110100101100011110111 %
b10111111100001101101 #
b10111111100001101101 +
b11110111000000101110 "
b11110111000000101110 *
b1001 (
b1000 )
#10500
0$
#11000
0p
1f
0q
b1001 r
0l
b1011 m
b1011 h
b11 9
1b
b0 c
b10011011101100000000 N
b10011011101100000000 -
b0 ^
b110110110100010011011 !
b110110110100010011011 .
b110110110100010011011 O
b1010 /
b1010 Y
b1010 o
b1001 0
b1001 W
b1001 n
b1100 1
b1100 U
b1100 j
b1011 2
b1011 S
b1011 i
b1011 3
b1011 Q
b1011 e
b1010 4
b1010 M
b1010 d
b10000 5
b10000 K
b10000 `
b1111 6
b1111 I
b1111 _
b10001 7
b10001 G
b10001 [
b10000 8
b10000 E
b10000 Z
b1010 C
b1010 X
b1001 B
b1001 V
b1100 A
b1100 T
b1011 @
b1011 R
b1011 ?
b1011 P
b1010 >
b1010 L
b10000 =
b10000 J
b1111 <
b1111 H
b10001 ;
b10001 F
b10000 :
b10000 D
1$
b110110110100010011011 %
b1110011010101101011 #
b1110011010101101011 +
b101000010110010101 "
b101000010110010101 *
b1010 (
b1001 )
#11500
0$
#12000
0f
b1 ^
0b
b1110 c
b1110 h
b1101 m
b10001 9
1q
b100001101111011100001 N
b1101111011100001 -
b0 r
b10001 8
b10001 E
b10001 Z
b10010 7
b10010 G
b10010 [
b1101 6
b1101 I
b1101 _
b1110 5
b1110 K
b1110 `
b1110 4
b1110 M
b1110 d
b1111 3
b1111 Q
b1111 e
b1101 2
b1101 S
b1101 i
b1110 1
b1110 U
b1110 j
b10000 0
b10000 W
b10000 n
b10001 /
b10001 Y
b10001 o
b10011011101100000000 !
b10011011101100000000 .
b10011011101100000000 O
b10001 C
b10001 X
b10000 B
b10000 V
b1110 A
b1110 T
b1101 @
b1101 R
b1111 ?
b1111 P
b1110 >
b1110 L
b1110 =
b1110 J
b1101 <
b1101 H
b10010 ;
b10010 F
b10001 :
b10001 D
1$
b10011011101100000000 %
b10101011101010101 #
b10101011101010101 +
b11111000011110001100 "
b11111000011110001100 *
b1011 (
b1010 )
#12500
0$
#13000
1f
b10 r
b1111 m
b1010 h
b10011 9
1b
b100101111101001110001 N
b101111101001110001 -
b111 c
b100001101111011100001 !
b100001101111011100001 .
b100001101111011100001 O
b10011 /
b10011 Y
b10011 o
b10010 0
b10010 W
b10010 n
b10000 1
b10000 U
b10000 j
b1111 2
b1111 S
b1111 i
b1010 3
b1010 Q
b1010 e
b1001 4
b1001 M
b1001 d
b10111 5
b10111 K
b10111 `
b10110 6
b10110 I
b10110 _
b10011 C
b10011 X
b10010 B
b10010 V
b10000 A
b10000 T
b1111 @
b1111 R
b1010 ?
b1010 P
b1001 >
b1001 L
b10111 =
b10111 J
b10110 <
b10110 H
1$
b100001101111011100001 %
b111010100111100011 #
b111010100111100011 +
b11110101000010001110 "
b11110101000010001110 *
b1100 (
b1011 )
#13500
0$
#14000
0f
1k
1p
b0 ^
0b
b10 c
1g
b1 h
b11101 9
1l
b110 m
b101100110000100100000 N
b1100110000100100000 -
b110 r
b10000 8
b10000 E
b10000 Z
b10001 7
b10001 G
b10001 [
b1 6
b1 I
b1 _
b10 5
b10 K
b10 `
b10001 4
b10001 M
b10001 d
b10010 3
b10010 Q
b10010 e
b10101 2
b10101 S
b10101 i
b10110 1
b10110 U
b10110 j
b10101 0
b10101 W
b10101 n
b10110 /
b10110 Y
b10110 o
b100101111101001110001 !
b100101111101001110001 .
b100101111101001110001 O
b10110 C
b10110 X
b10101 B
b10101 V
b10110 A
b10110 T
b10101 @
b10101 R
b10010 ?
b10010 P
b10001 >
b10001 L
b10 =
b10 J
b1 <
b1 H
b10001 ;
b10001 F
b10000 :
b10000 D
1$
b100101111101001110001 %
b11101001110100000111 #
b11101001110100000111 +
b1111100010000011001 "
b1111100010000011001 *
b1101 (
b1100 )
#14500
0$
#15000
b1 c
0k
1f
0a
0q
b1111 r
b11 m
0g
b1110 h
1b
b1010 9
0]
b11110011111000010101 N
b11110011111000010101 -
b101 ^
b101100110000100100000 !
b101100110000100100000 .
b101100110000100100000 O
b1111 /
b1111 Y
b1111 o
b1110 0
b1110 W
b1110 n
b10100 1
b10100 U
b10100 j
b10011 2
b10011 S
b10011 i
b1110 3
b1110 Q
b1110 e
b1101 4
b1101 M
b1101 d
b10010 5
b10010 K
b10010 `
b10001 6
b10001 I
b10001 _
b110 7
b110 G
b110 [
b101 8
b101 E
b101 Z
b1111 C
b1111 X
b1110 B
b1110 V
b10100 A
b10100 T
b10011 @
b10011 R
b1110 ?
b1110 P
b1101 >
b1101 L
b10010 =
b10010 J
b10001 <
b10001 H
b110 ;
b110 F
b101 :
b101 D
1$
b101100110000100100000 %
b100111000000100011 #
b100111000000100011 +
b11001100110111110010 "
b11001100110111110010 *
b1110 (
b1101 )
#15500
0$
#16000
1a
0f
0p
1]
0b
b1011 c
b1011 h
0l
b111 m
b1 9
0q
b11110111101110110101 N
b11110111101110110101 -
b1111 r
b10101 8
b10101 E
b10101 Z
b10110 7
b10110 G
b10110 [
b1010 6
b1010 I
b1010 _
b1011 5
b1011 K
b1011 `
b1011 4
b1011 M
b1011 d
b1100 3
b1100 Q
b1100 e
b111 2
b111 S
b111 i
b1000 1
b1000 U
b1000 j
b1111 0
b1111 W
b1111 n
b10000 /
b10000 Y
b10000 o
b11110011111000010101 !
b11110011111000010101 .
b11110011111000010101 O
b10000 C
b10000 X
b1111 B
b1111 V
b1000 A
b1000 T
b111 @
b111 R
b1100 ?
b1100 P
b1011 >
b1011 L
b1011 =
b1011 J
b1010 <
b1010 H
b10110 ;
b10110 F
b10101 :
b10101 D
1$
b11110011111000010101 %
b11010011011010001011 #
b11010011011010001011 +
b100100010100101010 "
b100100010100101010 *
b1111 (
b1110 )
#16500
0$
#17000
1p
1k
b1111 r
1l
b101 m
b1101 9
1g
b1100 h
b1001 c
b11110101110010010100 N
b11110101110010010100 -
b100 ^
b11110111101110110101 !
b11110111101110110101 .
b11110111101110110101 O
b1111 /
b1111 Y
b1111 o
b1110 0
b1110 W
b1110 n
b10101 1
b10101 U
b10101 j
b10100 2
b10100 S
b10100 i
b11101 3
b11101 Q
b11101 e
b11100 4
b11100 M
b11100 d
b1001 5
b1001 K
b1001 `
b1000 6
b1000 I
b1000 _
b10101 7
b10101 G
b10101 [
b10100 8
b10100 E
b10100 Z
b1111 C
b1111 X
b1110 B
b1110 V
b10101 A
b10101 T
b10100 @
b10100 R
b11101 ?
b11101 P
b11100 >
b11100 L
b1001 =
b1001 J
b1000 <
b1000 H
b10101 ;
b10101 F
b10100 :
b10100 D
1$
b11110111101110110101 %
b10001001110100001100 #
b10001001110100001100 +
b1101011111110001000 "
b1101011111110001000 *
b10000 (
b1111 )
#17500
0$
#18000
1f
0k
1b
b0 c
0g
b111 h
b1001 m
b11011 9
1q
b111101001011100000100 N
b11101001011100000100 -
b1110 r
b1111 6
b1111 I
b1111 _
b10000 5
b10000 K
b10000 `
b110 4
b110 M
b110 d
b111 3
b111 Q
b111 e
b11001 2
b11001 S
b11001 i
b11010 1
b11010 U
b11010 j
b11101 0
b11101 W
b11101 n
b11110 /
b11110 Y
b11110 o
b11110101110010010100 !
b11110101110010010100 .
b11110101110010010100 O
b11110 C
b11110 X
b11101 B
b11101 V
b11010 A
b11010 T
b11001 @
b11001 R
b111 ?
b111 P
b110 >
b110 L
b10000 =
b10000 J
b1111 <
b1111 H
1$
b11110101110010010100 %
b11111111000000101010 #
b11111111000000101010 +
b11101010011011011010 "
b11101010011011011010 *
b10001 (
b10000 )
#18500
0$
#19000
b1101 r
0p
0a
0q
0l
b1110 m
b1101 h
b1 c
b10 9
0]
b11011110110100010101 N
b11011110110100010101 -
b101 ^
b111101001011100000100 !
b111101001011100000100 .
b111101001011100000100 O
b1110 /
b1110 Y
b1110 o
b1101 0
b1101 W
b1101 n
b1111 1
b1111 U
b1111 j
b1110 2
b1110 S
b1110 i
b1101 3
b1101 Q
b1101 e
b1100 4
b1100 M
b1100 d
b10010 5
b10010 K
b10010 `
b10001 6
b10001 I
b10001 _
b110 7
b110 G
b110 [
b101 8
b101 E
b101 Z
b1110 C
b1110 X
b1101 B
b1101 V
b1111 A
b1111 T
b1110 @
b1110 R
b1101 ?
b1101 P
b1100 >
b1100 L
b10010 =
b10010 J
b10001 <
b10001 H
b110 ;
b110 F
b101 :
b101 D
1$
b111101001011100000100 %
b10100000000110100 #
b10100000000110100 +
b11001010110011100001 "
b11001010110011100001 *
b10010 (
b10001 )
#19500
0$
#20000
0f
0k
b1001 ^
0b
b100 c
0g
b1111 h
b110 m
b10000 9
1q
b101100110111101001001 N
b1100110111101001001 -
b110 r
b1001 8
b1001 E
b1001 Z
b1010 7
b1010 G
b1010 [
b100 6
b100 I
b100 _
b101 5
b101 K
b101 `
b1111 4
b1111 M
b1111 d
b10000 3
b10000 Q
b10000 e
b110 2
b110 S
b110 i
b111 1
b111 U
b111 j
b10110 0
b10110 W
b10110 n
b10111 /
b10111 Y
b10111 o
b11011110110100010101 !
b11011110110100010101 .
b11011110110100010101 O
b10111 C
b10111 X
b10110 B
b10110 V
b111 A
b111 T
b110 @
b110 R
b10000 ?
b10000 P
b1111 >
b1111 L
b101 =
b101 J
b100 <
b100 H
b1010 ;
b1010 F
b1001 :
b1001 D
1$
b11011110110100010101 %
b1110001010100110101 #
b1110001010100110101 +
b11110101101000010100 "
b11110101101000010100 *
b10011 (
b10010 )
#20500
0$
