verilog/digital_system_experiment/digitalsystem4/full_adder.v
module full_adder(A,B,cin,sum,cout);

input A,B;
input cin;
output sum,cout;

wire t1,t2,t3;

xor(t1,A,B);
and(t2,A,B);
xor(sum,t1,cin);
and(t3,t1,cin);
or(cout,t3,t2);

endmodule

verilog/digital_system_experiment/digitalsystem4/4bit_adder.v
`include "full_adder.v"

module adder_4bit(A,B,sum,cin,cout);

input [3:0]A,B;
input cin;
output [3:0]sum;
output cout;
wire [2:0]c;

full_adder fa0 (A[0],B[0],cin,sum[0],c[0]);
full_adder fa1 (A[1],B[1],c[0],sum[1],c[1]);
full_adder fa2 (A[2],B[2],c[1],sum[2],c[2]);
full_adder fa3 (A[3],B[3],c[2],sum[3],cout);

endmodule

verilog/digitalsystem4/4bit_multi.v
`include "4bit_adder.v"

module multi_4bit(A,B,C,cin);

input [3:0]A,B;
input cin;
output [7:0]C;

wire [3:0]A0;
wire [3:0]A1;
wire [3:0]A2;
wire [3:0]A3;
wire [2:0]carry;

wire [3:0]s0;
wire [3:0]s1;
wire [3:0]s2;
// A0 * B
and(A0[0],A[0],B[0]);
and(A0[1],A[0],B[1]);
and(A0[2],A[0],B[2]);
and(A0[3],A[0],B[3]);
// A1 * B
and(A1[0],A[1],B[0]);
and(A1[1],A[1],B[1]);
and(A1[2],A[1],B[2]);
and(A1[3],A[1],B[3]);
// A2 * B
and(A2[0],A[2],B[0]);
and(A2[1],A[2],B[1]);
and(A2[2],A[2],B[2]);
and(A2[3],A[2],B[3]);
// A3 * B
and(A3[0],A[3],B[0]);
and(A3[1],A[3],B[1]);
and(A3[2],A[3],B[2]);
and(A3[3],A[3],B[3]);

//module adder_4bit(A,B,sum,cin,cout);
adder_4bit add01 ({1'b0    ,A0[3],A0[2],A0[1]},A1,s0,cin,carry[0]);
adder_4bit add02 ({carry[0],s0[3],s0[2],s0[1]},A2,s1,cin,carry[1]);
adder_4bit add03 ({carry[1],s1[3],s1[2],s1[1]},A3,s2,cin,carry[2]);

assign C[0] = A0[0];
assign C[1] = s0[0];
assign C[2] = s1[0];
assign C[7:3] = {carry[2],s2[3],s2[2],s2[1],s2[0]};

endmodule

verilog/digitalsystem4/4bit_multi_tb.v
`include "4bit_multi.v"
`timescale 100ps/1ps

module multi_4bit_tb;

reg [3:0] A,B;
reg cin;
wire [7:0] C;
integer i,j;

multi_4bit multi0(A,B,C,cin);

initial begin
    $dumpfile("4bit_multi_tb.vcd");
    $dumpvars(0,multi_4bit_tb); // 여기에는 모듈 이름 써야됨. 파일 제목 x
    cin <= 1'b0;
    for(i=4'b0000; i<= 4'b1111; i++) begin
        B <= i;
        for(j=4'b0000; j<= 4'b1111; j++) begin
            A <= j; #10;
        end
    end
    $finish;
end

endmodule

verilog/digitalsystem4/4bit_multi_tb.vcd
$date
	Sat Sep 28 19:08:38 2019
$end
$version
	Icarus Verilog
$end
$timescale
	1ps
$end
$scope module multi_4bit_tb $end
$var wire 8 ! C [7:0] $end
$var reg 4 " A [3:0] $end
$var reg 4 # B [3:0] $end
$var reg 1 $ cin $end
$var integer 32 % i [31:0] $end
$var integer 32 & j [31:0] $end
$scope module multi0 $end
$var wire 4 ' A [3:0] $end
$var wire 4 ( B [3:0] $end
$var wire 1 $ cin $end
$var wire 4 ) s2 [3:0] $end
$var wire 4 * s1 [3:0] $end
$var wire 4 + s0 [3:0] $end
$var wire 3 , carry [2:0] $end
$var wire 8 - C [7:0] $end
$var wire 4 . A3 [3:0] $end
$var wire 4 / A2 [3:0] $end
$var wire 4 0 A1 [3:0] $end
$var wire 4 1 A0 [3:0] $end
$scope module add01 $end
$var wire 4 2 A [3:0] $end
$var wire 4 3 B [3:0] $end
$var wire 1 $ cin $end
$var wire 4 4 sum [3:0] $end
$var wire 1 5 cout $end
$var wire 3 6 c [2:0] $end
$scope module fa0 $end
$var wire 1 7 A $end
$var wire 1 8 B $end
$var wire 1 $ cin $end
$var wire 1 9 cout $end
$var wire 1 : sum $end
$var wire 1 ; t1 $end
$var wire 1 < t2 $end
$var wire 1 = t3 $end
$upscope $end
$scope module fa1 $end
$var wire 1 > A $end
$var wire 1 ? B $end
$var wire 1 @ cin $end
$var wire 1 A cout $end
$var wire 1 B sum $end
$var wire 1 C t1 $end
$var wire 1 D t2 $end
$var wire 1 E t3 $end
$upscope $end
$scope module fa2 $end
$var wire 1 F A $end
$var wire 1 G B $end
$var wire 1 H cin $end
$var wire 1 I cout $end
$var wire 1 J sum $end
$var wire 1 K t1 $end
$var wire 1 L t2 $end
$var wire 1 M t3 $end
$upscope $end
$scope module fa3 $end
$var wire 1 N A $end
$var wire 1 O B $end
$var wire 1 P cin $end
$var wire 1 5 cout $end
$var wire 1 Q sum $end
$var wire 1 R t1 $end
$var wire 1 S t2 $end
$var wire 1 T t3 $end
$upscope $end
$upscope $end
$scope module add02 $end
$var wire 4 U A [3:0] $end
$var wire 4 V B [3:0] $end
$var wire 1 $ cin $end
$var wire 4 W sum [3:0] $end
$var wire 1 X cout $end
$var wire 3 Y c [2:0] $end
$scope module fa0 $end
$var wire 1 Z A $end
$var wire 1 [ B $end
$var wire 1 $ cin $end
$var wire 1 \ cout $end
$var wire 1 ] sum $end
$var wire 1 ^ t1 $end
$var wire 1 _ t2 $end
$var wire 1 ` t3 $end
$upscope $end
$scope module fa1 $end
$var wire 1 a A $end
$var wire 1 b B $end
$var wire 1 c cin $end
$var wire 1 d cout $end
$var wire 1 e sum $end
$var wire 1 f t1 $end
$var wire 1 g t2 $end
$var wire 1 h t3 $end
$upscope $end
$scope module fa2 $end
$var wire 1 i A $end
$var wire 1 j B $end
$var wire 1 k cin $end
$var wire 1 l cout $end
$var wire 1 m sum $end
$var wire 1 n t1 $end
$var wire 1 o t2 $end
$var wire 1 p t3 $end
$upscope $end
$scope module fa3 $end
$var wire 1 q A $end
$var wire 1 r B $end
$var wire 1 s cin $end
$var wire 1 X cout $end
$var wire 1 t sum $end
$var wire 1 u t1 $end
$var wire 1 v t2 $end
$var wire 1 w t3 $end
$upscope $end
$upscope $end
$scope module add03 $end
$var wire 4 x A [3:0] $end
$var wire 4 y B [3:0] $end
$var wire 1 $ cin $end
$var wire 4 z sum [3:0] $end
$var wire 1 { cout $end
$var wire 3 | c [2:0] $end
$scope module fa0 $end
$var wire 1 } A $end
$var wire 1 ~ B $end
$var wire 1 $ cin $end
$var wire 1 !" cout $end
$var wire 1 "" sum $end
$var wire 1 #" t1 $end
$var wire 1 $" t2 $end
$var wire 1 %" t3 $end
$upscope $end
$scope module fa1 $end
$var wire 1 &" A $end
$var wire 1 '" B $end
$var wire 1 (" cin $end
$var wire 1 )" cout $end
$var wire 1 *" sum $end
$var wire 1 +" t1 $end
$var wire 1 ," t2 $end
$var wire 1 -" t3 $end
$upscope $end
$scope module fa2 $end
$var wire 1 ." A $end
$var wire 1 /" B $end
$var wire 1 0" cin $end
$var wire 1 1" cout $end
$var wire 1 2" sum $end
$var wire 1 3" t1 $end
$var wire 1 4" t2 $end
$var wire 1 5" t3 $end
$upscope $end
$scope module fa3 $end
$var wire 1 6" A $end
$var wire 1 7" B $end
$var wire 1 8" cin $end
$var wire 1 { cout $end
$var wire 1 9" sum $end
$var wire 1 :" t1 $end
$var wire 1 ;" t2 $end
$var wire 1 <" t3 $end
$upscope $end
$upscope $end
$upscope $end
$upscope $end
$enddefinitions $end
#0
$dumpvars
0<"
0;"
0:"
09"
08"
07"
06"
05"
04"
03"
02"
01"
00"
0/"
0."
0-"
0,"
0+"
0*"
0)"
0("
0'"
0&"
0%"
0$"
0#"
0""
0!"
0~
0}
b0 |
0{
b0 z
b0 y
b0 x
0w
0v
0u
0t
0s
0r
0q
0p
0o
0n
0m
0l
0k
0j
0i
0h
0g
0f
0e
0d
0c
0b
0a
0`
0_
0^
0]
0\
0[
0Z
b0 Y
0X
b0 W
b0 V
b0 U
0T
0S
0R
0Q
0P
0O
0N
0M
0L
0K
0J
0I
0H
0G
0F
0E
0D
0C
0B
0A
0@
0?
0>
0=
0<
0;
0:
09
08
07
b0 6
05
b0 4
b0 3
b0 2
b0 1
b0 0
b0 /
b0 .
b0 -
b0 ,
b0 +
b0 *
b0 )
b0 (
b0 '
b0 &
b0 %
0$
b0 #
b0 "
b0 !
$end
#1000
b1 "
b1 '
b1 &
#2000
b10 "
b10 '
b10 &
#3000
b11 "
b11 '
b11 &
#4000
b100 "
b100 '
b100 &
#5000
b101 "
b101 '
b101 &
#6000
b110 "
b110 '
b110 &
#7000
b111 "
b111 '
b111 &
#8000
b1000 "
b1000 '
b1000 &
#9000
b1001 "
b1001 '
b1001 &
#10000
b1010 "
b1010 '
b1010 &
#11000
b1011 "
b1011 '
b1011 &
#12000
b1100 "
b1100 '
b1100 &
#13000
b1101 "
b1101 '
b1101 &
#14000
b1110 "
b1110 '
b1110 &
#15000
b1111 "
b1111 '
b1111 &
#16000
b0 "
b0 '
b1 #
b1 (
b1 %
b0 &
#17000
b1 !
b1 -
b1 1
b1 "
b1 '
b1 &
#18000
b1 +
b1 4
1:
1;
b10 !
b10 -
18
b0 1
b1 0
b1 3
b10 "
b10 '
b10 &
#19000
b11 !
b11 -
b1 1
b11 "
b11 '
b11 &
#20000
b0 +
b0 4
0:
b1 *
b1 W
1]
0;
1^
b100 !
b100 -
08
1[
b0 1
b0 0
b0 3
b1 /
b1 V
b100 "
b100 '
b100 &
#21000
b101 !
b101 -
b1 1
b101 "
b101 '
b101 &
#22000
b1 +
b1 4
1:
1;
b110 !
b110 -
18
b0 1
b1 0
b1 3
b110 "
b110 '
b110 &
#23000
b111 !
b111 -
b1 1
b111 "
b111 '
b111 &
#24000
b0 +
b0 4
0:
b0 *
b0 W
0]
b1 )
b1 z
1""
0;
0^
1#"
b1000 !
b1000 -
08
0[
1~
b0 1
b0 0
b0 3
b0 /
b0 V
b1 .
b1 y
b1000 "
b1000 '
b1000 &
#25000
b1001 !
b1001 -
b1 1
b1001 "
b1001 '
b1001 &
#26000
b1 +
b1 4
1:
1;
b1010 !
b1010 -
18
b0 1
b1 0
b1 3
b1010 "
b1010 '
b1010 &
#27000
b1011 !
b1011 -
b1 1
b1011 "
b1011 '
b1011 &
#28000
b0 +
b0 4
0:
b1 *
b1 W
1]
0;
1^
b1100 !
b1100 -
08
1[
b0 1
b0 0
b0 3
b1 /
b1 V
b1100 "
b1100 '
b1100 &
#29000
b1101 !
b1101 -
b1 1
b1101 "
b1101 '
b1101 &
#30000
b1 +
b1 4
1:
1;
b1110 !
b1110 -
18
b0 1
b1 0
b1 3
b1110 "
b1110 '
b1110 &
#31000
b1111 !
b1111 -
b1 1
b1111 "
b1111 '
b1111 &
#32000
b0 +
b0 4
0:
b0 *
b0 W
0]
b0 )
b0 z
0""
0;
0^
0#"
b0 !
b0 -
08
0[
0~
b0 1
b0 0
b0 3
b0 /
b0 V
b0 .
b0 y
b0 "
b0 '
b10 #
b10 (
b10 %
b0 &
#33000
b10 !
b10 -
b1 +
b1 4
1:
1;
17
b1 2
b10 1
b1 "
b1 '
b1 &
#34000
b1 *
b1 W
1]
1^
b100 !
b100 -
1Z
0:
b1 U
0;
b10 +
b10 4
1B
07
1C
b0 2
1?
b0 1
b10 0
b10 3
b10 "
b10 '
b10 &
#35000
b110 !
b110 -
b11 +
b11 4
1:
1;
17
b1 2
b10 1
b11 "
b11 '
b11 &
#36000
0]
b1 )
b1 z
1""
0^
1#"
b1000 !
b1000 -
0Z
1}
0:
b0 U
b1 x
0;
b0 +
b0 4
0B
b10 *
b10 W
1e
07
0C
1f
b0 2
0?
1b
b0 1
b0 0
b0 3
b10 /
b10 V
b100 "
b100 '
b100 &
#37000
b1010 !
b1010 -
b1 +
b1 4
1:
1;
17
b1 2
b10 1
b101 "
b101 '
b101 &
#38000
b11 *
b11 W
1]
1^
b1100 !
b1100 -
1Z
0:
b1 U
0;
b10 +
b10 4
1B
07
1C
b0 2
1?
b0 1
b10 0
b10 3
b110 "
b110 '
b110 &
#39000
b1110 !
b1110 -
b11 +
b11 4
1:
1;
17
b1 2
b10 1
b111 "
b111 '
b111 &
#40000
0]
0""
0^
0#"
0Z
0}
0:
b0 U
b0 x
b10000 !
b10000 -
0;
b0 +
b0 4
0B
b0 *
b0 W
0e
b10 )
b10 z
1*"
07
0C
0f
1+"
b0 2
0?
0b
1'"
b0 1
b0 0
b0 3
b0 /
b0 V
b10 .
b10 y
b1000 "
b1000 '
b1000 &
#41000
b10010 !
b10010 -
b1 +
b1 4
1:
1;
17
b1 2
b10 1
b1001 "
b1001 '
b1001 &
#42000
b1 *
b1 W
1]
1^
b10100 !
b10100 -
1Z
0:
b1 U
0;
b10 +
b10 4
1B
07
1C
b0 2
1?
b0 1
b10 0
b10 3
b1010 "
b1010 '
b1010 &
#43000
b10110 !
b10110 -
b11 +
b11 4
1:
1;
17
b1 2
b10 1
b1011 "
b1011 '
b1011 &
#44000
0]
b11 )
b11 z
1""
0^
1#"
b11000 !
b11000 -
0Z
1}
0:
b0 U
b1 x
0;
b0 +
b0 4
0B
b10 *
b10 W
1e
07
0C
1f
b0 2
0?
1b
b0 1
b0 0
b0 3
b10 /
b10 V
b1100 "
b1100 '
b1100 &
#45000
b11010 !
b11010 -
b1 +
b1 4
1:
1;
17
b1 2
b10 1
b1101 "
b1101 '
b1101 &
#46000
b11 *
b11 W
1]
1^
b11100 !
b11100 -
1Z
0:
b1 U
0;
b10 +
b10 4
1B
07
1C
b0 2
1?
b0 1
b10 0
b10 3
b1110 "
b1110 '
b1110 &
#47000
b11110 !
b11110 -
b11 +
b11 4
1:
1;
17
b1 2
b10 1
b1111 "
b1111 '
b1111 &
#48000
0]
0""
0^
0#"
0Z
0}
0:
b0 U
b0 x
b0 !
b0 -
0;
b0 +
b0 4
0B
b0 *
b0 W
0e
b0 )
b0 z
0*"
07
0C
0f
0+"
b0 2
0?
0b
0'"
b0 1
b0 0
b0 3
b0 /
b0 V
b0 .
b0 y
b0 "
b0 '
b11 #
b11 (
b11 %
b0 &
#49000
b1 +
b1 4
1:
1;
17
b11 !
b11 -
b1 2
b11 1
b1 "
b1 '
b1 &
#50000
b0 )
b0 z
0""
0#"
0}
b0 x
0e
0f
0a
0J
0H
b1 *
b1 W
1]
0A
1^
0E
1Z
0@
b1 U
1:
b0 6
09
b11 +
b11 4
1B
07
1;
0<
1C
b110 !
b110 -
b0 2
18
1?
b0 1
b11 0
b11 3
b10 "
b10 '
b10 &
#51000
b1 )
b1 z
1""
1#"
1}
b1 x
1e
1f
1a
b10 *
b10 W
0]
0^
1J
0Z
1H
b10 U
1A
0B
1E
1@
b100 +
b100 4
0:
b11 6
19
0;
1<
17
b1001 !
b1001 -
b1 2
b11 1
b11 "
b11 '
b11 &
#52000
0h
0*"
0c
0a
0+"
0\
b1 )
b1 z
1""
0&"
0_
0J
1#"
0Z
0H
1}
0m
0@
b0 U
0A
b1 x
0k
0:
b0 6
09
b0 +
b0 4
0B
0E
1]
b11 *
b11 W
1e
b0 Y
0d
07
0;
0<
0C
1^
1f
0g
b1100 !
b1100 -
b0 2
08
0?
1[
1b
b0 1
b0 0
b0 3
b11 /
b11 V
b100 "
b100 '
b100 &
#53000
b1 +
b1 4
1:
1;
17
b1111 !
b1111 -
b1 2
b11 1
b101 "
b101 '
b101 &
#54000
1*"
1+"
1&"
b10 )
b10 z
0""
0#"
1m
1f
0g
0}
1k
0a
b10 x
1d
0e
1h
0J
1c
0H
b100 *
b100 W
0]
b11 Y
1\
0A
0^
1_
0E
1Z
0@
b1 U
1:
b0 6
09
b11 +
b11 4
1B
07
1;
0<
1C
b10010 !
b10010 -
b0 2
18
1?
b0 1
b11 0
b11 3
b110 "
b110 '
b110 &
#55000
0h
0f
1g
0c
1a
b101 *
b101 W
1]
b10 Y
0\
1^
0_
1J
0Z
1H
b10 U
1A
0B
1E
1@
b100 +
b100 4
0:
b11 6
19
0;
1<
17
b10101 !
b10101 -
b1 2
b11 1
b111 "
b111 '
b111 &
#56000
0-"
0a
0("
0!"
0&"
0J
0$"
0Z
0H
0}
0m
02"
0@
b0 U
0A
b0 x
0k
00"
0:
b0 6
09
b0 +
b0 4
0B
0E
0]
b0 *
b0 W
0e
b0 Y
0d
1""
b11 )
b11 z
1*"
b0 |
0)"
07
0;
0<
0C
0^
0f
0g
1#"
1+"
0,"
b11000 !
b11000 -
b0 2
08
0?
0[
0b
1~
1'"
b0 1
b0 0
b0 3
b0 /
b0 V
b11 .
b11 y
b1000 "
b1000 '
b1000 &
#57000
b1 +
b1 4
1:
1;
17
b11011 !
b11011 -
b1 2
b11 1
b1001 "
b1001 '
b1001 &
#58000
02"
00"
0)"
1*"
0-"
0("
b11 )
b11 z
1""
b0 |
0!"
1#"
0$"
0}
b0 x
0e
0f
0a
0J
0H
b1 *
b1 W
1]
0A
1^
0E
1Z
0@
b1 U
1:
b0 6
09
b11 +
b11 4
1B
07
1;
0<
1C
b11110 !
b11110 -
b0 2
18
1?
b0 1
b11 0
b11 3
b1010 "
b1010 '
b1010 &
#59000
12"
10"
1)"
0*"
1-"
1("
b100 )
b100 z
0""
b11 |
1!"
0#"
1$"
1}
b1 x
1e
1f
1a
b10 *
b10 W
0]
0^
1J
0Z
1H
b10 U
1A
0B
1E
1@
b100 +
b100 4
0:
b11 6
19
0;
1<
17
b100001 !
b100001 -
b1 2
b11 1
b1011 "
b1011 '
b1011 &
#60000
0h
1-"
0c
0a
1("
1+"
0,"
0\
b100 )
b100 z
0""
b11 |
1!"
0&"
0_
0J
0#"
1$"
0Z
0H
1}
0m
0@
b0 U
0A
b1 x
0k
0:
b0 6
09
b0 +
b0 4
0B
0E
1]
b11 *
b11 W
1e
b0 Y
0d
07
0;
0<
0C
1^
1f
0g
b100100 !
b100100 -
b0 2
08
0?
1[
1b
b0 1
b0 0
b0 3
b11 /
b11 V
b1100 "
b1100 '
b1100 &
#61000
b1 +
b1 4
1:
1;
17
b100111 !
b100111 -
b1 2
b11 1
b1101 "
b1101 '
b1101 &
#62000
0-"
0+"
1,"
0("
1&"
b101 )
b101 z
1""
b10 |
0!"
1#"
0$"
1m
1f
0g
0}
1k
0a
b10 x
1d
0e
1h
0J
1c
0H
b100 *
b100 W
0]
b11 Y
1\
0A
0^
1_
0E
1Z
0@
b1 U
1:
b0 6
09
b11 +
b11 4
1B
07
1;
0<
1C
b101010 !
b101010 -
b0 2
18
1?
b0 1
b11 0
b11 3
b1110 "
b1110 '
b1110 &
#63000
0h
0f
1g
0c
1a
b101 *
b101 W
1]
b10 Y
0\
1^
0_
1J
0Z
1H
b10 U
1A
0B
1E
1@
b100 +
b100 4
0:
b11 6
19
0;
1<
17
b101101 !
b101101 -
b1 2
b11 1
b1111 "
b1111 '
b1111 &
#64000
0a
0&"
0J
0Z
0H
0}
0m
02"
0@
b0 U
0A
b0 x
0k
00"
0:
b0 6
09
b0 +
b0 4
0B
0E
0]
b0 *
b0 W
0e
b0 Y
0d
0""
b0 )
b0 z
0*"
b0 |
0)"
07
0;
0<
0C
0^
0f
0g
0#"
0+"
0,"
b0 !
b0 -
b0 2
08
0?
0[
0b
0~
0'"
b0 1
b0 0
b0 3
b0 /
b0 V
b0 .
b0 y
b0 "
b0 '
b100 #
b100 (
b100 %
b0 &
#65000
b100 !
b100 -
b1 *
b1 W
1]
1^
1Z
b1 U
b10 +
b10 4
1B
1C
1>
b10 2
b100 1
b1 "
b1 '
b1 &
#66000
b1 )
b1 z
1""
1#"
b1000 !
b1000 -
1}
0]
b1 x
0^
b10 *
b10 W
1e
0Z
1f
1a
0B
b10 U
0C
b100 +
b100 4
1J
0>
1K
b0 2
1G
b0 1
b100 0
b100 3
b10 "
b10 '
b10 &
#67000
b1100 !
b1100 -
b11 *
b11 W
1]
1^
1Z
b11 U
b110 +
b110 4
1B
1C
1>
b10 2
b100 1
b11 "
b11 '
b11 &
#68000
0""
0#"
0}
0]
b10000 !
b10000 -
0^
0e
b10 )
b10 z
1*"
0Z
0f
1+"
0a
1&"
0B
b0 U
b10 x
0C
b0 +
b0 4
0J
b100 *
b100 W
1m
0>
0K
1n
b0 2
0G
1j
b0 1
b0 0
b0 3
b100 /
b100 V
b100 "
b100 '
b100 &
#69000
b10100 !
b10100 -
b101 *
b101 W
1]
1^
1Z
b1 U
b10 +
b10 4
1B
1C
1>
b10 2
b100 1
b101 "
b101 '
b101 &
#70000
b11 )
b11 z
1""
1#"
b11000 !
b11000 -
1}
0]
b11 x
0^
b110 *
b110 W
1e
0Z
1f
1a
0B
b10 U
0C
b100 +
b100 4
1J
0>
1K
b0 2
1G
b0 1
b100 0
b100 3
b110 "
b110 '
b110 &
#71000
b11100 !
b11100 -
b111 *
b111 W
1]
1^
1Z
b11 U
b110 +
b110 4
1B
1C
1>
b10 2
b100 1
b111 "
b111 '
b111 &
#72000
0""
0#"
0}
0]
0^
0e
0*"
0Z
0f
0+"
0a
0&"
0B
b0 U
b0 x
b100000 !
b100000 -
0C
b0 +
b0 4
0J
b0 *
b0 W
0m
b100 )
b100 z
12"
0>
0K
0n
13"
b0 2
0G
0j
1/"
b0 1
b0 0
b0 3
b0 /
b0 V
b100 .
b100 y
b1000 "
b1000 '
b1000 &
#73000
b100100 !
b100100 -
b1 *
b1 W
1]
1^
1Z
b1 U
b10 +
b10 4
1B
1C
1>
b10 2
b100 1
b1001 "
b1001 '
b1001 &
#74000
b101 )
b101 z
1""
1#"
b101000 !
b101000 -
1}
0]
b1 x
0^
b10 *
b10 W
1e
0Z
1f
1a
0B
b10 U
0C
b100 +
b100 4
1J
0>
1K
b0 2
1G
b0 1
b100 0
b100 3
b1010 "
b1010 '
b1010 &
#75000
b101100 !
b101100 -
b11 *
b11 W
1]
1^
1Z
b11 U
b110 +
b110 4
1B
1C
1>
b10 2
b100 1
b1011 "
b1011 '
b1011 &
#76000
0""
0#"
0}
0]
b110000 !
b110000 -
0^
0e
b110 )
b110 z
1*"
0Z
0f
1+"
0a
1&"
0B
b0 U
b10 x
0C
b0 +
b0 4
0J
b100 *
b100 W
1m
0>
0K
1n
b0 2
0G
1j
b0 1
b0 0
b0 3
b100 /
b100 V
b1100 "
b1100 '
b1100 &
#77000
b110100 !
b110100 -
b101 *
b101 W
1]
1^
1Z
b1 U
b10 +
b10 4
1B
1C
1>
b10 2
b100 1
b1101 "
b1101 '
b1101 &
#78000
b111 )
b111 z
1""
1#"
b111000 !
b111000 -
1}
0]
b11 x
0^
b110 *
b110 W
1e
0Z
1f
1a
0B
b10 U
0C
b100 +
b100 4
1J
0>
1K
b0 2
1G
b0 1
b100 0
b100 3
b1110 "
b1110 '
b1110 &
#79000
b111100 !
b111100 -
b111 *
b111 W
1]
1^
1Z
b11 U
b110 +
b110 4
1B
1C
1>
b10 2
b100 1
b1111 "
b1111 '
b1111 &
#80000
0""
0#"
0}
0]
0^
0e
0*"
0Z
0f
0+"
0a
0&"
0B
b0 U
b0 x
b0 !
b0 -
0C
b0 +
b0 4
0J
b0 *
b0 W
0m
b0 )
b0 z
02"
0>
0K
0n
03"
b0 2
0G
0j
0/"
b0 1
b0 0
b0 3
b0 /
b0 V
b0 .
b0 y
b0 "
b0 '
b101 #
b101 (
b101 %
b0 &
#81000
b1 *
b1 W
1]
1^
1Z
b1 U
b10 +
b10 4
1B
1C
1>
b101 !
b101 -
b10 2
b101 1
b1 "
b1 '
b1 &
#82000
b1 )
b1 z
1""
1#"
1}
0]
b1 x
0^
b10 *
b10 W
1e
0Z
1f
1a
0B
b10 U
0C
1:
b101 +
b101 4
1J
0>
1;
1K
b1010 !
b1010 -
b0 2
18
1G
b0 1
b101 0
b101 3
b10 "
b10 '
b10 &
#83000
b11 *
b11 W
1]
1^
1Z
b11 U
b111 +
b111 4
1B
1C
1>
b1111 !
b1111 -
b10 2
b101 1
b11 "
b11 '
b11 &
#84000
02"
03"
0."
0t
0s
0""
0l
0#"
0p
0}
0k
b10 )
b10 z
1*"
0Z
0f
0d
1+"
0a
0e
0h
1&"
0B
b0 U
0c
b10 x
0C
0:
b0 +
b0 4
0J
1]
b0 Y
0\
b101 *
b101 W
1m
0>
0;
0K
1^
0_
1n
b10100 !
b10100 -
b0 2
08
0G
1[
1j
b0 1
b0 0
b0 3
b101 /
b101 V
b100 "
b100 '
b100 &
#85000
b11 )
b11 z
1""
1#"
1}
b11 x
1e
1c
b110 *
b110 W
0]
b1 Y
1\
0^
1_
1Z
b1 U
b10 +
b10 4
1B
1C
1>
b11001 !
b11001 -
b10 2
b101 1
b101 "
b101 '
b101 &
#86000
02"
03"
0."
1*"
1+"
0t
1&"
0s
b11 )
b11 z
1""
0l
1#"
1m
0p
0c
1}
0k
1]
0\
b11 x
b0 Y
0d
1^
0_
b111 *
b111 W
1e
0h
0Z
1f
1a
0B
b10 U
0C
1:
b101 +
b101 4
1J
0>
1;
1K
b11110 !
b11110 -
b0 2
18
1G
b0 1
b101 0
b101 3
b110 "
b110 '
b110 &
#87000
12"
13"
1."
0*"
0+"
1t
0&"
1s
b100 )
b100 z
0""
1l
0#"
0m
1p
0}
1k
b100 x
1d
0e
1h
1c
b1000 *
b1000 W
0]
b111 Y
1\
0^
1_
1Z
b11 U
b111 +
b111 4
1B
1C
1>
b100011 !
b100011 -
b10 2
b101 1
b111 "
b111 '
b111 &
#88000
0("
0!"
0$"
0."
0}
0k
0*"
0Z
0f
0d
0+"
0t
0a
0e
0h
0&"
0s
09"
0B
b0 U
0c
b0 x
0l
08"
0C
0:
b0 +
b0 4
0J
0]
b0 Y
0\
b0 *
b0 W
0m
0p
1""
b101 )
b101 z
12"
b0 |
01"
0>
0;
0K
0^
0_
0n
1#"
13"
04"
b101000 !
b101000 -
b0 2
08
0G
0[
0j
1~
1/"
b0 1
b0 0
b0 3
b0 /
b0 V
b101 .
b101 y
b1000 "
b1000 '
b1000 &
#89000
b1 *
b1 W
1]
1^
1Z
b1 U
b10 +
b10 4
1B
1C
1>
b101101 !
b101101 -
b10 2
b101 1
b1001 "
b1001 '
b1001 &
#90000
1*"
1("
b110 )
b110 z
0""
b1 |
1!"
0#"
1$"
1}
0]
b1 x
0^
b10 *
b10 W
1e
0Z
1f
1a
0B
b10 U
0C
1:
b101 +
b101 4
1J
0>
1;
1K
b110010 !
b110010 -
b0 2
18
1G
b0 1
b101 0
b101 3
b1010 "
b1010 '
b1010 &
#91000
b11 *
b11 W
1]
1^
1Z
b11 U
b111 +
b111 4
1B
1C
1>
b110111 !
b110111 -
b10 2
b101 1
b1011 "
b1011 '
b1011 &
#92000
13"
04"
0."
09"
08"
0t
01"
0("
0s
12"
05"
1""
0!"
0l
00"
1#"
0$"
0p
b0 |
0)"
0}
0k
b111 )
b111 z
1*"
0-"
0Z
0f
0d
1+"
0a
0e
0h
1&"
0B
b0 U
0c
b10 x
0C
0:
b0 +
b0 4
0J
1]
b0 Y
0\
b101 *
b101 W
1m
0>
0;
0K
1^
0_
1n
b111100 !
b111100 -
b0 2
08
0G
1[
1j
b0 1
b0 0
b0 3
b101 /
b101 V
b1100 "
b1100 '
b1100 &
#93000
19"
18"
11"
02"
15"
10"
1)"
0*"
1-"
1("
b1000 )
b1000 z
0""
b111 |
1!"
0#"
1$"
1}
b11 x
1e
1c
b110 *
b110 W
0]
b1 Y
1\
0^
1_
1Z
b1 U
b10 +
b10 4
1B
1C
1>
b1000001 !
b1000001 -
b10 2
b101 1
b1101 "
b1101 '
b1101 &
#94000
15"
13"
04"
10"
0."
1)"
1-"
1+"
0t
1("
1&"
0s
b1000 )
b1000 z
0""
b111 |
1!"
0l
0#"
1$"
1m
0p
0c
1}
0k
1]
0\
b11 x
b0 Y
0d
1^
0_
b111 *
b111 W
1e
0h
0Z
1f
1a
0B
b10 U
0C
1:
b101 +
b101 4
1J
0>
1;
1K
b1000110 !
b1000110 -
b0 2
18
1G
b0 1
b101 0
b101 3
b1110 "
b1110 '
b1110 &
#95000
05"
03"
14"
00"
1."
0)"
0-"
0+"
1t
0("
0&"
1s
b1001 )
b1001 z
1""
b100 |
0!"
1l
1#"
0$"
0m
1p
0}
1k
b100 x
1d
0e
1h
1c
b1000 *
b1000 W
0]
b111 Y
1\
0^
1_
1Z
b11 U
b111 +
b111 4
1B
1C
1>
b1001011 !
b1001011 -
b10 2
b101 1
b1111 "
b1111 '
b1111 &
#96000
0."
0*"
0}
0k
0Z
0f
0+"
0t
0d
0a
0&"
0s
09"
0e
0h
0B
b0 U
b0 x
0l
08"
0c
0C
0J
0m
0p
02"
b0 |
01"
b0 +
b0 4
0:
b0 *
b0 W
0]
b0 Y
0\
b0 )
b0 z
0""
0>
0K
0n
03"
04"
0;
0^
0_
0#"
b0 2
0G
0j
0/"
b0 !
b0 -
08
0[
0~
b0 1
b0 0
b0 3
b0 /
b0 V
b0 .
b0 y
b0 "
b0 '
b110 #
b110 (
b110 %
b0 &
#97000
b1 *
b1 W
1]
1^
1Z
b110 !
b110 -
b1 U
1:
b11 +
b11 4
1B
1;
1C
17
1>
b11 2
b110 1
b1 "
b1 '
b1 &
#98000
0*"
0+"
0&"
0m
0n
b1 )
b1 z
1""
0i
1#"
1}
0Q
b1 x
1]
0P
b11 *
b11 W
1e
1^
0I
1f
b1100 !
b1100 -
1Z
0M
1a
0:
0H
b11 U
0;
1B
b0 6
0A
b110 +
b110 4
1J
07
0>
1C
0D
1K
b0 2
1?
1G
b0 1
b110 0
b110 3
b10 "
b10 '
b10 &
#99000
1*"
1+"
1&"
b10 )
b10 z
0""
0#"
1m
0}
1n
b10 x
1i
0e
0f
1Q
b100 *
b100 W
0]
0a
1P
0^
1I
0Z
0J
1M
b10010 !
b10010 -
b100 U
1H
1:
b1001 +
b1001 4
0B
b110 6
1A
1;
0C
1D
17
1>
b11 2
b110 1
b11 "
b11 '
b11 &
