verilog/digital_system_experiment/digitalsystem4/full_adder.v
module full_adder(A,B,cin,sum,cout);

input A,B;
input cin;
output sum,cout;

wire t1,t2,t3;

xor(t1,A,B);
and(t2,A,B);
xor(sum,t1,cin);
and(t3,t1,cin);
or(cout,t3,t2);

endmodule

verilog/digital_system_experiment/digitalsystem4/4bit_adder.v
`include "full_adder.v"

module adder_4bit(A,B,sum,cin,cout);

input [3:0]A,B;
input cin;
output [3:0]sum;
output cout;
wire [2:0]c;

full_adder fa0 (A[0],B[0],cin,sum[0],c[0]);
full_adder fa1 (A[1],B[1],c[0],sum[1],c[1]);
full_adder fa2 (A[2],B[2],c[1],sum[2],c[2]);
full_adder fa3 (A[3],B[3],c[2],sum[3],cout);

endmodule

verilog/digital_system_experiment/digitalsystem4/4bit_adder_tb.v
`include "4bit_adder.v"
`timescale 100ps/1ps

module adder_4bit_tb;

reg [3:0]A,B;
reg cin;
wire [3:0]sum;
wire cout;
integer i,j,k;

adder_4bit fa4 (A,B,sum,cin,cout);

initial begin
    $dumpfile("4bit_adder_tb.vcd");
    $dumpvars(0,adder_4bit_tb); // 여기에는 모듈 이름 써야됨. 파일 제목 x
    for(i = 0; i < 1; i++)
	begin
        cin <= i;
		for(j=0; j <16; j++)
        begin
            B <= j;
            for(k=0; k<16; k++)
            begin
                A <= k; #10;
            end
        end
        $finish;
	end
end
endmodule

verilog/digitalsystem4/4bit_adder_tb.vcd
$date
	Sat Sep 28 13:40:49 2019
$end
$version
	Icarus Verilog
$end
$timescale
	1ps
$end
$scope module adder_4bit_tb $end
$var wire 4 ! sum [3:0] $end
$var wire 1 " cout $end
$var reg 4 # A [3:0] $end
$var reg 4 $ B [3:0] $end
$var reg 1 % cin $end
$var integer 32 & i [31:0] $end
$var integer 32 ' j [31:0] $end
$var integer 32 ( k [31:0] $end
$scope module fa4 $end
$var wire 4 ) A [3:0] $end
$var wire 4 * B [3:0] $end
$var wire 1 % cin $end
$var wire 4 + sum [3:0] $end
$var wire 1 " cout $end
$var wire 3 , c [2:0] $end
$scope module fa0 $end
$var wire 1 - A $end
$var wire 1 . B $end
$var wire 1 % cin $end
$var wire 1 / cout $end
$var wire 1 0 sum $end
$var wire 1 1 t1 $end
$var wire 1 2 t2 $end
$var wire 1 3 t3 $end
$upscope $end
$scope module fa1 $end
$var wire 1 4 A $end
$var wire 1 5 B $end
$var wire 1 6 cin $end
$var wire 1 7 cout $end
$var wire 1 8 sum $end
$var wire 1 9 t1 $end
$var wire 1 : t2 $end
$var wire 1 ; t3 $end
$upscope $end
$scope module fa2 $end
$var wire 1 < A $end
$var wire 1 = B $end
$var wire 1 > cin $end
$var wire 1 ? cout $end
$var wire 1 @ sum $end
$var wire 1 A t1 $end
$var wire 1 B t2 $end
$var wire 1 C t3 $end
$upscope $end
$scope module fa3 $end
$var wire 1 D A $end
$var wire 1 E B $end
$var wire 1 F cin $end
$var wire 1 " cout $end
$var wire 1 G sum $end
$var wire 1 H t1 $end
$var wire 1 I t2 $end
$var wire 1 J t3 $end
$upscope $end
$upscope $end
$upscope $end
$enddefinitions $end
#0
$dumpvars
0J
0I
0H
0G
0F
0E
0D
0C
0B
0A
0@
0?
0>
0=
0<
0;
0:
09
08
07
06
05
04
03
02
01
00
0/
0.
0-
b0 ,
b0 +
b0 *
b0 )
b0 (
b0 '
b0 &
0%
b0 $
b0 #
0"
b0 !
$end
#1000
b1 !
b1 +
10
11
1-
b1 #
b1 )
b1 (
#2000
00
b10 !
b10 +
18
01
19
0-
14
b10 #
b10 )
b10 (
#3000
b11 !
b11 +
10
11
1-
b11 #
b11 )
b11 (
#4000
00
08
b100 !
b100 +
1@
01
09
1A
0-
04
1<
b100 #
b100 )
b100 (
#5000
b101 !
b101 +
10
11
1-
b101 #
b101 )
b101 (
#6000
00
b110 !
b110 +
18
01
19
0-
14
b110 #
b110 )
b110 (
#7000
b111 !
b111 +
10
11
1-
b111 #
b111 )
b111 (
#8000
00
08
0@
b1000 !
b1000 +
1G
01
09
0A
1H
0-
04
0<
1D
b1000 #
b1000 )
b1000 (
#9000
b1001 !
b1001 +
10
11
1-
b1001 #
b1001 )
b1001 (
#10000
00
b1010 !
b1010 +
18
01
19
0-
14
b1010 #
b1010 )
b1010 (
#11000
b1011 !
b1011 +
10
11
1-
b1011 #
b1011 )
b1011 (
#12000
00
08
b1100 !
b1100 +
1@
01
09
1A
0-
04
1<
b1100 #
b1100 )
b1100 (
#13000
b1101 !
b1101 +
10
11
1-
b1101 #
b1101 )
b1101 (
#14000
00
b1110 !
b1110 +
18
01
19
0-
14
b1110 #
b1110 )
b1110 (
#15000
b1111 !
b1111 +
10
11
1-
b1111 #
b1111 )
b1111 (
#16000
08
0@
b1 !
b1 +
0G
09
0A
0H
0-
04
0<
0D
1.
b0 #
b0 )
b1 $
b1 *
b1 '
b0 (
#17000
18
16
b10 !
b10 +
00
b1 ,
1/
01
12
1-
b1 #
b1 )
b1 (
#18000
0@
0>
06
07
10
b0 ,
0/
b11 !
b11 +
18
0;
11
02
19
0-
14
b10 #
b10 )
b10 (
#19000
1@
1>
17
08
1;
16
b100 !
b100 +
00
b11 ,
1/
01
12
1-
b11 #
b11 )
b11 (
#20000
0G
0>
0F
06
07
0?
10
b0 ,
0/
08
0;
b101 !
b101 +
1@
0C
11
02
09
1A
0-
04
1<
b100 #
b100 )
b100 (
#21000
18
16
b110 !
b110 +
00
b1 ,
1/
01
12
1-
b101 #
b101 )
b101 (
#22000
0G
0F
0?
1@
0C
0>
06
07
10
b0 ,
0/
b111 !
b111 +
18
0;
11
02
19
0-
14
b110 #
b110 )
b110 (
#23000
1G
1F
1?
0@
1C
1>
17
08
1;
16
b1000 !
b1000 +
00
b111 ,
1/
01
12
1-
b111 #
b111 )
b111 (
#24000
0>
0F
06
07
0?
0"
10
b0 ,
0/
08
0;
0@
0C
b1001 !
b1001 +
1G
0J
11
02
09
0A
1H
0-
04
0<
1D
b1000 #
b1000 )
b1000 (
#25000
18
16
b1010 !
b1010 +
00
b1 ,
1/
01
12
1-
b1001 #
b1001 )
b1001 (
#26000
0@
0>
06
07
10
b0 ,
0/
b1011 !
b1011 +
18
0;
11
02
19
0-
14
b1010 #
b1010 )
b1010 (
#27000
1@
1>
17
08
1;
16
b1100 !
b1100 +
00
b11 ,
1/
01
12
1-
b1011 #
b1011 )
b1011 (
#28000
0"
1G
0J
0>
0F
06
07
0?
10
b0 ,
0/
08
0;
b1101 !
b1101 +
1@
0C
11
02
09
1A
0-
04
1<
b1100 #
b1100 )
b1100 (
#29000
18
16
b1110 !
b1110 +
00
b1 ,
1/
01
12
1-
b1101 #
b1101 )
b1101 (
#30000
0"
1G
0J
0F
0?
1@
0C
0>
06
07
10
b0 ,
0/
b1111 !
b1111 +
18
0;
11
02
19
0-
14
b1110 #
b1110 )
b1110 (
#31000
1"
0G
1J
1F
1?
0@
1C
1>
17
08
1;
16
b0 !
b0 +
00
b111 ,
1/
01
12
1-
b1111 #
b1111 )
b1111 (
#32000
0>
07
0F
18
0;
0?
0"
06
0@
0C
b10 !
b10 +
0G
0J
b0 ,
0/
0A
0H
02
0-
04
0<
0D
0.
15
b0 #
b0 )
b10 $
b10 *
b10 '
b0 (
#33000
b11 !
b11 +
10
11
1-
b1 #
b1 )
b1 (
#34000
1@
1>
00
b100 !
b100 +
08
b10 ,
17
01
09
1:
0-
14
b10 #
b10 )
b10 (
#35000
b101 !
b101 +
10
11
1-
b11 #
b11 )
b11 (
#36000
0G
0F
0>
0?
00
18
b0 ,
07
b110 !
b110 +
1@
0C
01
19
0:
1A
0-
04
1<
b100 #
b100 )
b100 (
#37000
b111 !
b111 +
10
11
1-
b101 #
b101 )
b101 (
#38000
1G
1F
1?
0@
1C
1>
00
b1000 !
b1000 +
08
b110 ,
17
01
09
1:
0-
14
b110 #
b110 )
b110 (
#39000
b1001 !
b1001 +
10
11
1-
b111 #
b111 )
b111 (
#40000
0F
0>
0?
0"
00
18
b0 ,
07
0@
0C
b1010 !
b1010 +
1G
0J
01
19
0:
0A
1H
0-
04
0<
1D
b1000 #
b1000 )
b1000 (
#41000
b1011 !
b1011 +
10
11
1-
b1001 #
b1001 )
b1001 (
#42000
1@
1>
00
b1100 !
b1100 +
08
b10 ,
17
01
09
1:
0-
14
b1010 #
b1010 )
b1010 (
#43000
b1101 !
b1101 +
10
11
1-
b1011 #
b1011 )
b1011 (
#44000
0"
1G
0J
0F
0>
0?
00
18
b0 ,
07
b1110 !
b1110 +
1@
0C
01
19
0:
1A
0-
04
1<
b1100 #
b1100 )
b1100 (
#45000
b1111 !
b1111 +
10
11
1-
b1101 #
b1101 )
b1101 (
#46000
1"
0G
1J
1F
1?
0@
1C
1>
00
b0 !
b0 +
08
b110 ,
17
01
09
1:
0-
14
b1110 #
b1110 )
b1110 (
#47000
b1 !
b1 +
10
11
1-
b1111 #
b1111 )
b1111 (
#48000
0F
0>
0?
0"
18
b0 ,
07
0@
0C
b11 !
b11 +
0G
0J
19
0:
0A
0H
0-
04
0<
0D
1.
b0 #
b0 )
b11 $
b11 *
b11 '
b0 (
#49000
1@
1>
17
08
1;
16
b100 !
b100 +
00
b11 ,
1/
01
12
1-
b1 #
b1 )
b1 (
#50000
06
10
b10 ,
0/
b101 !
b101 +
08
0;
11
02
09
1:
0-
14
b10 #
b10 )
b10 (
#51000
18
16
b110 !
b110 +
00
b11 ,
1/
01
12
1-
b11 #
b11 )
b11 (
#52000
0G
0F
06
0>
0?
10
0/
18
0;
b0 ,
07
b111 !
b111 +
1@
0C
11
02
19
0:
1A
0-
04
1<
b100 #
b100 )
b100 (
#53000
1G
1F
1?
0@
1C
1>
17
08
1;
16
b1000 !
b1000 +
00
b111 ,
1/
01
12
1-
b101 #
b101 )
b101 (
#54000
06
10
b110 ,
0/
b1001 !
b1001 +
08
0;
11
02
09
1:
0-
14
b110 #
b110 )
b110 (
#55000
18
16
b1010 !
b1010 +
00
b111 ,
1/
01
12
1-
b111 #
b111 )
b111 (
#56000
0F
06
0>
0?
0"
10
0/
18
0;
b0 ,
07
0@
0C
b1011 !
b1011 +
1G
0J
11
02
19
0:
0A
1H
0-
04
0<
1D
b1000 #
b1000 )
b1000 (
#57000
1@
1>
17
08
1;
16
b1100 !
b1100 +
00
b11 ,
1/
01
12
1-
b1001 #
b1001 )
b1001 (
#58000
06
10
b10 ,
0/
b1101 !
b1101 +
08
0;
11
02
09
1:
0-
14
b1010 #
b1010 )
b1010 (
#59000
18
16
b1110 !
b1110 +
00
b11 ,
1/
01
12
1-
b1011 #
b1011 )
b1011 (
#60000
0"
1G
0J
0F
06
0>
0?
10
0/
18
0;
b0 ,
07
b1111 !
b1111 +
1@
0C
11
02
19
0:
1A
0-
04
1<
b1100 #
b1100 )
b1100 (
#61000
1"
0G
1J
1F
1?
0@
1C
1>
17
08
1;
16
b0 !
b0 +
00
b111 ,
1/
01
12
1-
b1101 #
b1101 )
b1101 (
#62000
06
10
b110 ,
0/
b1 !
b1 +
08
0;
11
02
09
1:
0-
14
b1110 #
b1110 )
b1110 (
#63000
18
16
b10 !
b10 +
00
b111 ,
1/
01
12
1-
b1111 #
b1111 )
b1111 (
#64000
0F
0?
08
1@
0C
0"
06
0>
b100 !
b100 +
0G
0J
0/
b0 ,
07
0H
02
0:
0-
04
0<
0D
0.
05
1=
b0 #
b0 )
b100 $
b100 *
b100 '
b0 (
#65000
b101 !
b101 +
10
11
1-
b1 #
b1 )
b1 (
#66000
00
b110 !
b110 +
18
01
19
0-
14
b10 #
b10 )
b10 (
#67000
b111 !
b111 +
10
11
1-
b11 #
b11 )
b11 (
#68000
1G
1F
00
08
b1000 !
b1000 +
0@
b100 ,
1?
01
09
0A
1B
0-
04
1<
b100 #
b100 )
b100 (
#69000
b1001 !
b1001 +
10
11
1-
b101 #
b101 )
b101 (
#70000
00
b1010 !
b1010 +
18
01
19
0-
14
b110 #
b110 )
b110 (
#71000
b1011 !
b1011 +
10
11
1-
b111 #
b111 )
b111 (
#72000
0F
0"
00
08
1@
b0 ,
0?
b1100 !
b1100 +
1G
0J
01
09
1A
0B
1H
0-
04
0<
1D
b1000 #
b1000 )
b1000 (
#73000
b1101 !
b1101 +
10
11
1-
b1001 #
b1001 )
b1001 (
#74000
00
b1110 !
b1110 +
18
01
19
0-
14
b1010 #
b1010 )
b1010 (
#75000
b1111 !
b1111 +
10
11
1-
b1011 #
b1011 )
b1011 (
#76000
1"
0G
1J
1F
00
08
b0 !
b0 +
0@
b100 ,
1?
01
09
0A
1B
0-
04
1<
b1100 #
b1100 )
b1100 (
#77000
b1 !
b1 +
10
11
1-
b1101 #
b1101 )
b1101 (
#78000
00
b10 !
b10 +
18
01
19
0-
14
b1110 #
b1110 )
b1110 (
#79000
b11 !
b11 +
10
11
1-
b1111 #
b1111 )
b1111 (
#80000
0F
0"
08
1@
b0 ,
0?
b101 !
b101 +
0G
0J
09
1A
0B
0H
0-
04
0<
0D
1.
b0 #
b0 )
b101 $
b101 *
b101 '
b0 (
#81000
18
16
b110 !
b110 +
00
b1 ,
1/
01
12
1-
b1 #
b1 )
b1 (
#82000
0G
0F
0?
1@
0C
0>
06
07
10
b0 ,
0/
b111 !
b111 +
18
0;
11
02
19
0-
14
b10 #
b10 )
b10 (
#83000
1G
1F
1?
0@
1C
1>
17
08
1;
16
b1000 !
b1000 +
00
b111 ,
1/
01
12
1-
b11 #
b11 )
b11 (
#84000
0>
06
07
10
b100 ,
0/
08
0;
b1001 !
b1001 +
0@
0C
11
02
09
0A
1B
0-
04
1<
b100 #
b100 )
b100 (
#85000
18
16
b1010 !
b1010 +
00
b101 ,
1/
01
12
1-
b101 #
b101 )
b101 (
#86000
0@
0>
06
07
10
b100 ,
0/
b1011 !
b1011 +
18
0;
11
02
19
0-
14
b110 #
b110 )
b110 (
#87000
1@
1>
17
08
1;
16
b1100 !
b1100 +
00
b111 ,
1/
01
12
1-
b111 #
b111 )
b111 (
#88000
0>
06
07
0F
0"
10
0/
08
0;
1@
0C
b0 ,
0?
b1101 !
b1101 +
1G
0J
11
02
09
1A
0B
1H
0-
04
0<
1D
b1000 #
b1000 )
b1000 (
#89000
18
16
b1110 !
b1110 +
00
b1 ,
1/
01
12
1-
b1001 #
b1001 )
b1001 (
#90000
0"
1G
0J
0F
0?
1@
0C
0>
06
07
10
b0 ,
0/
b1111 !
b1111 +
18
0;
11
02
19
0-
14
b1010 #
b1010 )
b1010 (
#91000
1"
0G
1J
1F
1?
0@
1C
1>
17
08
1;
16
b0 !
b0 +
00
b111 ,
1/
01
12
1-
b1011 #
b1011 )
b1011 (
#92000
0>
06
07
10
b100 ,
0/
08
0;
b1 !
b1 +
0@
0C
11
02
09
0A
1B
0-
04
1<
b1100 #
b1100 )
b1100 (
#93000
18
16
b10 !
b10 +
00
b101 ,
1/
01
12
1-
b1101 #
b1101 )
b1101 (
#94000
0@
0>
06
07
10
b100 ,
0/
b11 !
b11 +
18
0;
11
02
19
0-
14
b1110 #
b1110 )
b1110 (
#95000
1@
1>
17
08
1;
16
b100 !
b100 +
00
b111 ,
1/
01
12
1-
b1111 #
b1111 )
b1111 (
#96000
0>
07
18
0;
0F
0"
06
1@
0C
0?
b110 !
b110 +
0G
0J
b0 ,
0/
1A
0B
0H
02
0-
04
0<
0D
0.
15
b0 #
b0 )
b110 $
b110 *
b110 '
b0 (
#97000
b111 !
b111 +
10
11
1-
b1 #
b1 )
b1 (
#98000
1G
1F
1?
0@
1C
1>
00
b1000 !
b1000 +
08
b110 ,
17
01
09
1:
0-
14
b10 #
b10 )
b10 (
#99000
b1001 !
b1001 +
10
11
1-
b11 #
b11 )
b11 (
#100000
0>
00
18
b100 ,
07
b1010 !
b1010 +
0@
0C
01
19
0:
0A
1B
0-
04
1<
b100 #
b100 )
b100 (
#101000
b1011 !
b1011 +
10
11
1-
b101 #
b101 )
b101 (
#102000
1@
1>
00
b1100 !
b1100 +
08
b110 ,
17
01
09
1:
0-
14
b110 #
b110 )
b110 (
#103000
b1101 !
b1101 +
10
11
1-
b111 #
b111 )
b111 (
#104000
0>
0F
0"
00
18
07
1@
0C
b0 ,
0?
b1110 !
b1110 +
1G
0J
01
19
0:
1A
0B
1H
0-
04
0<
1D
b1000 #
b1000 )
b1000 (
#105000
b1111 !
b1111 +
10
11
1-
b1001 #
b1001 )
b1001 (
#106000
1"
0G
1J
1F
1?
0@
1C
1>
00
b0 !
b0 +
08
b110 ,
17
01
09
1:
0-
14
b1010 #
b1010 )
b1010 (
#107000
b1 !
b1 +
10
11
1-
b1011 #
b1011 )
b1011 (
#108000
0>
00
18
b100 ,
07
b10 !
b10 +
0@
0C
01
19
0:
0A
1B
0-
04
1<
b1100 #
b1100 )
b1100 (
#109000
b11 !
b11 +
10
11
1-
b1101 #
b1101 )
b1101 (
#110000
1@
1>
00
b100 !
b100 +
08
b110 ,
17
01
09
1:
0-
14
b1110 #
b1110 )
b1110 (
#111000
b101 !
b101 +
10
11
1-
b1111 #
b1111 )
b1111 (
#112000
0>
0F
0"
18
07
1@
0C
b0 ,
0?
b111 !
b111 +
0G
0J
19
0:
1A
0B
0H
0-
04
0<
0D
1.
b0 #
b0 )
b111 $
b111 *
b111 '
b0 (
#113000
1G
1F
1?
0@
1C
1>
17
08
1;
16
b1000 !
b1000 +
00
b111 ,
1/
01
12
1-
b1 #
b1 )
b1 (
#114000
06
10
b110 ,
0/
b1001 !
b1001 +
08
0;
11
02
09
1:
0-
14
b10 #
b10 )
b10 (
#115000
18
16
b1010 !
b1010 +
00
b111 ,
1/
01
12
1-
b11 #
b11 )
b11 (
#116000
06
0>
10
0/
18
0;
b100 ,
07
b1011 !
b1011 +
0@
0C
11
02
19
0:
0A
1B
0-
04
1<
b100 #
b100 )
b100 (
#117000
1@
1>
17
08
1;
16
b1100 !
b1100 +
00
b111 ,
1/
01
12
1-
b101 #
b101 )
b101 (
#118000
06
10
b110 ,
0/
b1101 !
b1101 +
08
0;
11
02
09
1:
0-
14
b110 #
b110 )
b110 (
#119000
18
16
b1110 !
b1110 +
00
b111 ,
1/
01
12
1-
b111 #
b111 )
b111 (
#120000
06
0>
0F
0"
10
0/
18
0;
07
1@
0C
b0 ,
0?
b1111 !
b1111 +
1G
0J
11
02
19
0:
1A
0B
1H
0-
04
0<
1D
b1000 #
b1000 )
b1000 (
#121000
1"
0G
1J
1F
1?
0@
1C
1>
17
08
1;
16
b0 !
b0 +
00
b111 ,
1/
01
12
1-
b1001 #
b1001 )
b1001 (
#122000
06
10
b110 ,
0/
b1 !
b1 +
08
0;
11
02
09
1:
0-
14
b1010 #
b1010 )
b1010 (
#123000
18
16
b10 !
b10 +
00
b111 ,
1/
01
12
1-
b1011 #
b1011 )
b1011 (
#124000
06
0>
10
0/
18
0;
b100 ,
07
b11 !
b11 +
0@
0C
11
02
19
0:
0A
1B
0-
04
1<
b1100 #
b1100 )
b1100 (
#125000
1@
1>
17
08
1;
16
b100 !
b100 +
00
b111 ,
1/
01
12
1-
b1101 #
b1101 )
b1101 (
#126000
06
10
b110 ,
0/
b101 !
b101 +
08
0;
11
02
09
1:
0-
14
b1110 #
b1110 )
b1110 (
#127000
18
16
b110 !
b110 +
00
b111 ,
1/
01
12
1-
b1111 #
b1111 )
b1111 (
#128000
0"
08
0@
b1000 !
b1000 +
1G
0J
06
0>
0F
0/
07
b0 ,
0?
02
0:
0B
0-
04
0<
0D
0.
05
0=
1E
b0 #
b0 )
b1000 $
b1000 *
b1000 '
b0 (
#129000
b1001 !
b1001 +
10
11
1-
b1 #
b1 )
b1 (
#130000
00
b1010 !
b1010 +
18
01
19
0-
14
b10 #
b10 )
b10 (
#131000
b1011 !
b1011 +
10
11
1-
b11 #
b11 )
b11 (
#132000
00
08
b1100 !
b1100 +
1@
01
09
1A
0-
04
1<
b100 #
b100 )
b100 (
#133000
b1101 !
b1101 +
10
11
1-
b101 #
b101 )
b101 (
#134000
00
b1110 !
b1110 +
18
01
19
0-
14
b110 #
b110 )
b110 (
#135000
b1111 !
b1111 +
10
11
1-
b111 #
b111 )
b111 (
#136000
00
08
0@
b0 !
b0 +
0G
1"
01
09
0A
0H
1I
0-
04
0<
1D
b1000 #
b1000 )
b1000 (
#137000
b1 !
b1 +
10
11
1-
b1001 #
b1001 )
b1001 (
#138000
00
b10 !
b10 +
18
01
19
0-
14
b1010 #
b1010 )
b1010 (
#139000
b11 !
b11 +
10
11
1-
b1011 #
b1011 )
b1011 (
#140000
00
08
b100 !
b100 +
1@
01
09
1A
0-
04
1<
b1100 #
b1100 )
b1100 (
#141000
b101 !
b101 +
10
11
1-
b1101 #
b1101 )
b1101 (
#142000
00
b110 !
b110 +
18
01
19
0-
14
b1110 #
b1110 )
b1110 (
#143000
b111 !
b111 +
10
11
1-
b1111 #
b1111 )
b1111 (
#144000
08
0@
b1001 !
b1001 +
1G
0"
09
0A
1H
0I
0-
04
0<
0D
1.
b0 #
b0 )
b1001 $
b1001 *
b1001 '
b0 (
#145000
18
16
b1010 !
b1010 +
00
b1 ,
1/
01
12
1-
b1 #
b1 )
b1 (
#146000
0@
0>
06
07
10
b0 ,
0/
b1011 !
b1011 +
18
0;
11
02
19
0-
14
b10 #
b10 )
b10 (
#147000
1@
1>
17
08
1;
16
b1100 !
b1100 +
00
b11 ,
1/
01
12
1-
b11 #
b11 )
b11 (
#148000
0"
1G
0J
0>
0F
06
07
0?
10
b0 ,
0/
08
0;
b1101 !
b1101 +
1@
0C
11
02
09
1A
0-
04
1<
b100 #
b100 )
b100 (
#149000
18
16
b1110 !
b1110 +
00
b1 ,
1/
01
12
1-
b101 #
b101 )
b101 (
#150000
0"
1G
0J
0F
0?
1@
0C
0>
06
07
10
b0 ,
0/
b1111 !
b1111 +
18
0;
11
02
19
0-
14
b110 #
b110 )
b110 (
#151000
1"
0G
1J
1F
1?
0@
1C
1>
17
08
1;
16
b0 !
b0 +
00
b111 ,
1/
01
12
1-
b111 #
b111 )
b111 (
#152000
0>
0F
06
07
0?
10
b0 ,
0/
08
0;
0@
0C
b1 !
b1 +
0G
0J
11
02
09
0A
0H
1I
0-
04
0<
1D
b1000 #
b1000 )
b1000 (
#153000
18
16
b10 !
b10 +
00
b1 ,
1/
01
12
1-
b1001 #
b1001 )
b1001 (
#154000
0@
0>
06
07
10
b0 ,
0/
b11 !
b11 +
18
0;
11
02
19
0-
14
b1010 #
b1010 )
b1010 (
#155000
1@
1>
17
08
1;
16
b100 !
b100 +
00
b11 ,
1/
01
12
1-
b1011 #
b1011 )
b1011 (
#156000
0G
0>
0F
06
07
0?
10
b0 ,
0/
08
0;
b101 !
b101 +
1@
0C
11
02
09
1A
0-
04
1<
b1100 #
b1100 )
b1100 (
#157000
18
16
b110 !
b110 +
00
b1 ,
1/
01
12
1-
b1101 #
b1101 )
b1101 (
#158000
0G
0F
0?
1@
0C
0>
06
07
10
b0 ,
0/
b111 !
b111 +
18
0;
11
02
19
0-
14
b1110 #
b1110 )
b1110 (
#159000
1G
1F
1?
0@
1C
1>
17
08
1;
16
b1000 !
b1000 +
00
b111 ,
1/
01
12
1-
b1111 #
b1111 )
b1111 (
#160000
0>
07
0F
18
0;
0?
06
0@
0C
b1010 !
b1010 +
1G
0J
0"
b0 ,
0/
0A
1H
0I
02
0-
04
0<
0D
0.
15
b0 #
b0 )
b1010 $
b1010 *
b1010 '
b0 (
#161000
b1011 !
b1011 +
10
11
1-
b1 #
b1 )
b1 (
#162000
1@
1>
00
b1100 !
b1100 +
08
b10 ,
17
01
09
1:
0-
14
b10 #
b10 )
b10 (
#163000
b1101 !
b1101 +
10
11
1-
b11 #
b11 )
b11 (
#164000
0"
1G
0J
0F
0>
0?
00
18
b0 ,
07
b1110 !
b1110 +
1@
0C
01
19
0:
1A
0-
04
1<
b100 #
b100 )
b100 (
#165000
b1111 !
b1111 +
10
11
1-
b101 #
b101 )
b101 (
#166000
1"
0G
1J
1F
1?
0@
1C
1>
00
b0 !
b0 +
08
b110 ,
17
01
09
1:
0-
14
b110 #
b110 )
b110 (
#167000
b1 !
b1 +
10
11
1-
b111 #
b111 )
b111 (
#168000
0F
0>
0?
00
18
b0 ,
07
0@
0C
b10 !
b10 +
0G
0J
01
19
0:
0A
0H
1I
0-
04
0<
1D
b1000 #
b1000 )
b1000 (
#169000
b11 !
b11 +
10
11
1-
b1001 #
b1001 )
b1001 (
#170000
1@
1>
00
b100 !
b100 +
08
b10 ,
17
01
09
1:
0-
14
b1010 #
b1010 )
b1010 (
#171000
b101 !
b101 +
10
11
1-
b1011 #
b1011 )
b1011 (
#172000
0G
0F
0>
0?
00
18
b0 ,
07
b110 !
b110 +
1@
0C
01
19
0:
1A
0-
04
1<
b1100 #
b1100 )
b1100 (
#173000
b111 !
b111 +
10
11
1-
b1101 #
b1101 )
b1101 (
#174000
1G
1F
1?
0@
1C
1>
00
b1000 !
b1000 +
08
b110 ,
17
01
09
1:
0-
14
b1110 #
b1110 )
b1110 (
#175000
b1001 !
b1001 +
10
11
1-
b1111 #
b1111 )
b1111 (
#176000
0F
0>
0?
18
b0 ,
07
0@
0C
b1011 !
b1011 +
1G
0J
0"
19
0:
0A
1H
0I
0-
04
0<
0D
1.
b0 #
b0 )
b1011 $
b1011 *
b1011 '
b0 (
#177000
1@
1>
17
08
1;
16
b1100 !
b1100 +
00
b11 ,
1/
01
12
1-
b1 #
b1 )
b1 (
#178000
06
10
b10 ,
0/
b1101 !
b1101 +
08
0;
11
02
09
1:
0-
14
b10 #
b10 )
b10 (
#179000
18
16
b1110 !
b1110 +
00
b11 ,
1/
01
12
1-
b11 #
b11 )
b11 (
#180000
0"
1G
0J
0F
06
0>
0?
10
0/
18
0;
b0 ,
07
b1111 !
b1111 +
1@
0C
11
02
19
0:
1A
0-
04
1<
b100 #
b100 )
b100 (
#181000
1"
0G
1J
1F
1?
0@
1C
1>
17
08
1;
16
b0 !
b0 +
00
b111 ,
1/
01
12
1-
b101 #
b101 )
b101 (
#182000
06
10
b110 ,
0/
b1 !
b1 +
08
0;
11
02
09
1:
0-
14
b110 #
b110 )
b110 (
#183000
18
16
b10 !
b10 +
00
b111 ,
1/
01
12
1-
b111 #
b111 )
b111 (
#184000
0F
06
0>
0?
10
0/
18
0;
b0 ,
07
0@
0C
b11 !
b11 +
0G
0J
11
02
19
0:
0A
0H
1I
0-
04
0<
1D
b1000 #
b1000 )
b1000 (
#185000
1@
1>
17
08
1;
16
b100 !
b100 +
00
b11 ,
1/
01
12
1-
b1001 #
b1001 )
b1001 (
#186000
06
10
b10 ,
0/
b101 !
b101 +
08
0;
11
02
09
1:
0-
14
b1010 #
b1010 )
b1010 (
#187000
18
16
b110 !
b110 +
00
b11 ,
1/
01
12
1-
b1011 #
b1011 )
b1011 (
#188000
0G
0F
06
0>
0?
10
0/
18
0;
b0 ,
07
b111 !
b111 +
1@
0C
11
02
19
0:
1A
0-
04
1<
b1100 #
b1100 )
b1100 (
#189000
1G
1F
1?
0@
1C
1>
17
08
1;
16
b1000 !
b1000 +
00
b111 ,
1/
01
12
1-
b1101 #
b1101 )
b1101 (
#190000
06
10
b110 ,
0/
b1001 !
b1001 +
08
0;
11
02
09
1:
0-
14
b1110 #
b1110 )
b1110 (
#191000
18
16
b1010 !
b1010 +
00
b111 ,
1/
01
12
1-
b1111 #
b1111 )
b1111 (
#192000
0F
0?
08
1@
0C
06
0>
b1100 !
b1100 +
1G
0J
0"
0/
b0 ,
07
1H
0I
02
0:
0-
04
0<
0D
0.
05
1=
b0 #
b0 )
b1100 $
b1100 *
b1100 '
b0 (
#193000
b1101 !
b1101 +
10
11
1-
b1 #
b1 )
b1 (
#194000
00
b1110 !
b1110 +
18
01
19
0-
14
b10 #
b10 )
b10 (
#195000
b1111 !
b1111 +
10
11
1-
b11 #
b11 )
b11 (
#196000
1"
0G
1J
1F
00
08
b0 !
b0 +
0@
b100 ,
1?
01
09
0A
1B
0-
04
1<
b100 #
b100 )
b100 (
#197000
b1 !
b1 +
10
11
1-
b101 #
b101 )
b101 (
#198000
00
b10 !
b10 +
18
01
19
0-
14
b110 #
b110 )
b110 (
#199000
b11 !
b11 +
10
11
1-
b111 #
b111 )
b111 (
#200000
0F
00
08
1@
b0 ,
0?
b100 !
b100 +
0G
0J
01
09
1A
0B
0H
1I
0-
04
0<
1D
b1000 #
b1000 )
b1000 (
#201000
b101 !
b101 +
10
11
1-
b1001 #
b1001 )
b1001 (
#202000
00
b110 !
b110 +
18
01
19
0-
14
b1010 #
b1010 )
b1010 (
#203000
b111 !
b111 +
10
11
1-
b1011 #
b1011 )
b1011 (
#204000
1G
1F
00
08
b1000 !
b1000 +
0@
b100 ,
1?
01
09
0A
1B
0-
04
1<
b1100 #
b1100 )
b1100 (
#205000
b1001 !
b1001 +
10
11
1-
b1101 #
b1101 )
b1101 (
#206000
00
b1010 !
b1010 +
18
01
19
0-
14
b1110 #
b1110 )
b1110 (
#207000
b1011 !
b1011 +
10
11
1-
b1111 #
b1111 )
b1111 (
#208000
0F
08
1@
b0 ,
0?
b1101 !
b1101 +
1G
0J
0"
09
1A
0B
1H
0I
0-
04
0<
0D
1.
b0 #
b0 )
b1101 $
b1101 *
b1101 '
b0 (
#209000
18
16
b1110 !
b1110 +
00
b1 ,
1/
01
12
1-
b1 #
b1 )
b1 (
#210000
0"
1G
0J
0F
0?
1@
0C
0>
06
07
10
b0 ,
0/
b1111 !
b1111 +
18
0;
11
02
19
0-
14
b10 #
b10 )
b10 (
#211000
1"
0G
1J
1F
1?
0@
1C
1>
17
08
1;
16
b0 !
b0 +
00
b111 ,
1/
01
12
1-
b11 #
b11 )
b11 (
