verilog/digital_system_experiment/digitalsystem4/full_adder.v
module full_adder(A,B,cin,sum,cout);

input A,B;
input cin;
output sum,cout;

wire t1,t2,t3;

xor(t1,A,B);
and(t2,A,B);
xor(sum,t1,cin);
and(t3,t1,cin);
or(cout,t3,t2);

endmodule

verilog/digital_system_experiment/digitalsystem4/full_adder_tb.v
`include "full_adder.v"
`timescale 100ps/1ps

module full_adder_tb;

reg A,B;
reg cin;
wire sum,cout;

full_adder fa0 (A,B,cin,sum,cout);

initial begin
    $dumpfile("full_adder_tb.vcd");
    $dumpvars(0,full_adder_tb);
        A<=1'b0; B<= 1'b0; cin <= 1'b0;
    #10 A<=1'b0; B<= 1'b0; cin <= 1'b1;
    #10 A<=1'b0; B<= 1'b1; cin <= 1'b0;
    #10 A<=1'b0; B<= 1'b1; cin <= 1'b1;
    #10 A<=1'b1; B<= 1'b0; cin <= 1'b0;
    #10 A<=1'b1; B<= 1'b0; cin <= 1'b1;
    #10 A<=1'b1; B<= 1'b1; cin <= 1'b0;
    #10 A<=1'b1; B<= 1'b1; cin <= 1'b1;
    $finish;

end

endmodule

verilog/digitalsystem4/full_adder_tb.vcd
$date
	Sat Sep 28 13:22:20 2019
$end
$version
	Icarus Verilog
$end
$timescale
	1ps
$end
$scope module full_adder_tb $end
$var wire 1 ! sum $end
$var wire 1 " cout $end
$var reg 1 # A $end
$var reg 1 $ B $end
$var reg 1 % cin $end
$scope module fa0 $end
$var wire 1 # A $end
$var wire 1 $ B $end
$var wire 1 % cin $end
$var wire 1 " cout $end
$var wire 1 ! sum $end
$var wire 1 & t1 $end
$var wire 1 ' t2 $end
$var wire 1 ( t3 $end
$upscope $end
$upscope $end
$enddefinitions $end
#0
$dumpvars
0(
0'
0&
0%
0$
0#
0"
0!
$end
#1000
1!
1%
#2000
1&
0%
1$
#3000
1"
0!
1(
1%
#4000
0"
1!
0(
0%
0$
1#
#5000
1"
0!
1(
1%
#6000
0(
0&
1'
0%
1$
#7000
1!
1%
