verilog/VLSI_experiment/6w/Practice_06_ref/rflp128x52mx4.v
`timescale 1 ns / 10 ps
module rflp128x52mx4(
    output [52-1:0] DO,
    input [52-1:0] DIN,
    input [5-1:0] RA,
    input [2-1:0] CA,
    input NWRT,
    input NCE,
    input CLK);
   
    reg [52-1:0] array[128-1:0];
    reg [52-1:0] r_din;
    reg [7-1:0] r_addr;
    reg r_nwrt, r_nce;
    
    event write, read;
    integer i;
    
    reg [52-1:0] temp_reg;
    reg [52-1:0] write_data;
    reg [52-1:0] do_reg;
    wire [7-1:0] A;
    
    //assign DO = (1'b1)? do_reg: 44'hz;
    wire [52-1:0] BDO;
    
         buf(BDO[0], do_reg[0]);
         buf(BDO[1], do_reg[1]);
         buf(BDO[2], do_reg[2]);
         buf(BDO[3], do_reg[3]);
         buf(BDO[4], do_reg[4]);
         buf(BDO[5], do_reg[5]);
         buf(BDO[6], do_reg[6]);
         buf(BDO[7], do_reg[7]);
         buf(BDO[8], do_reg[8]);
         buf(BDO[9], do_reg[9]);
         buf(BDO[10], do_reg[10]);
         buf(BDO[11], do_reg[11]);
         buf(BDO[12], do_reg[12]);
         buf(BDO[13], do_reg[13]);
         buf(BDO[14], do_reg[14]);
         buf(BDO[15], do_reg[15]);
         buf(BDO[16], do_reg[16]);
         buf(BDO[17], do_reg[17]);
         buf(BDO[18], do_reg[18]);
         buf(BDO[19], do_reg[19]);
         buf(BDO[20], do_reg[20]);
         buf(BDO[21], do_reg[21]);
         buf(BDO[22], do_reg[22]);
         buf(BDO[23], do_reg[23]);
         buf(BDO[24], do_reg[24]);
         buf(BDO[25], do_reg[25]);
         buf(BDO[26], do_reg[26]);
         buf(BDO[27], do_reg[27]);
         buf(BDO[28], do_reg[28]);
         buf(BDO[29], do_reg[29]);
         buf(BDO[30], do_reg[30]);
         buf(BDO[31], do_reg[31]);
         buf(BDO[32], do_reg[32]);
         buf(BDO[33], do_reg[33]);
         buf(BDO[34], do_reg[34]);
         buf(BDO[35], do_reg[35]);
         buf(BDO[36], do_reg[36]);
         buf(BDO[37], do_reg[37]);
         buf(BDO[38], do_reg[38]);
         buf(BDO[39], do_reg[39]);
		 buf(BDO[40], do_reg[40]);
		 buf(BDO[41], do_reg[41]);
		 buf(BDO[42], do_reg[42]);
		 buf(BDO[43], do_reg[43]);
         buf(BDO[44], do_reg[44]);
         buf(BDO[45], do_reg[45]);
         buf(BDO[46], do_reg[46]);
         buf(BDO[47], do_reg[47]);
		 buf(BDO[48], do_reg[48]);
		 buf(BDO[49], do_reg[49]);
		 buf(BDO[50], do_reg[50]);
		 buf(BDO[51], do_reg[51]);

         bufif1(DO[0], BDO[0], 1'b1);
         bufif1(DO[1], BDO[1], 1'b1);
         bufif1(DO[2], BDO[2], 1'b1);
         bufif1(DO[3], BDO[3], 1'b1);
         bufif1(DO[4], BDO[4], 1'b1);
         bufif1(DO[5], BDO[5], 1'b1);
         bufif1(DO[6], BDO[6], 1'b1);
         bufif1(DO[7], BDO[7], 1'b1);
         bufif1(DO[8], BDO[8], 1'b1);
         bufif1(DO[9], BDO[9], 1'b1);
         bufif1(DO[10], BDO[10], 1'b1);
         bufif1(DO[11], BDO[11], 1'b1);
         bufif1(DO[12], BDO[12], 1'b1);
         bufif1(DO[13], BDO[13], 1'b1);
         bufif1(DO[14], BDO[14], 1'b1);
         bufif1(DO[15], BDO[15], 1'b1);
         bufif1(DO[16], BDO[16], 1'b1);
         bufif1(DO[17], BDO[17], 1'b1);
         bufif1(DO[18], BDO[18], 1'b1);
         bufif1(DO[19], BDO[19], 1'b1);
         bufif1(DO[20], BDO[20], 1'b1);
         bufif1(DO[21], BDO[21], 1'b1);
         bufif1(DO[22], BDO[22], 1'b1);
         bufif1(DO[23], BDO[23], 1'b1);
         bufif1(DO[24], BDO[24], 1'b1);
         bufif1(DO[25], BDO[25], 1'b1);
         bufif1(DO[26], BDO[26], 1'b1);
         bufif1(DO[27], BDO[27], 1'b1);
         bufif1(DO[28], BDO[28], 1'b1);
         bufif1(DO[29], BDO[29], 1'b1);
         bufif1(DO[30], BDO[30], 1'b1);
         bufif1(DO[31], BDO[31], 1'b1);
         bufif1(DO[32], BDO[32], 1'b1);
         bufif1(DO[33], BDO[33], 1'b1);
         bufif1(DO[34], BDO[34], 1'b1);
         bufif1(DO[35], BDO[35], 1'b1);
         bufif1(DO[36], BDO[36], 1'b1);
         bufif1(DO[37], BDO[37], 1'b1);
         bufif1(DO[38], BDO[38], 1'b1);
         bufif1(DO[39], BDO[39], 1'b1);
		 bufif1(DO[40], BDO[40], 1'b1);
		 bufif1(DO[41], BDO[41], 1'b1);
		 bufif1(DO[42], BDO[42], 1'b1);
		 bufif1(DO[43], BDO[43], 1'b1);
         bufif1(DO[44], BDO[44], 1'b1);
         bufif1(DO[45], BDO[45], 1'b1);
         bufif1(DO[46], BDO[46], 1'b1);
         bufif1(DO[47], BDO[47], 1'b1);
		 bufif1(DO[48], BDO[48], 1'b1);
		 bufif1(DO[49], BDO[49], 1'b1);
		 bufif1(DO[50], BDO[50], 1'b1);
		 bufif1(DO[51], BDO[51], 1'b1);
         
         assign A = {RA, CA};
         
         always@(posedge CLK)
                begin
                     r_nwrt <= NWRT;
                     r_nce <= NCE;
                     r_din <= DIN;
                     r_addr <= A;
                     
                #0.1
                      if(!r_nce && !r_nwrt)
                        -> write;
                      if(!r_nce && r_nwrt)
                        -> read;
                        
                    end
                    
         always@(write)
                begin
                      temp_reg = array[r_addr];
                      write_data = r_din;
                array[r_addr] = write_data;
            end
          
            
         always@(read)
                begin
                     #0.1
                     do_reg = array[r_addr];
                 end
                 
         reg FLAG_X;
         initial FLAG_X = 1'b0;
         always@(FLAG_X)
         begin
             for(i=0; i<(128); i=i+1)
              begin
                  //array[i] = {40{1'bx}};
              end
              $display("INSUFFICIENT SETUP/HOLD TIME - POTENTIAL MEMORY DATA CORRUPTION");
              
          end
          
          specify
                  specparam
                            tCLK = 3,              // Clock Cycle Time
                            tCH = 0.4*tCLK,        // Clock High-Level Width
                            tCL = 0.4*tCLK,        // Clock Low-level Width
                            tDH = 0.0,             // Data-in Hold Time
                            tDS = 0.40,            // Data-in Setup Time
                            tAH = 0.0,             // address Hold Time
                            tAS = 0.60,            // address Setup Time
                            tPHL = 0.8,            
                            tPLH = 0.8,        
                            tEH = 0.0, 
                            tES = 0.40;            // control signal Hold Time
                  $width(posedge CLK, tCH);        // control signal Setup Time
                  
                  $width(negedge CLK, tCL); 
                  
                  $period(negedge CLK, tCLK);
                  
                  $period(posedge CLK, tCLK);
                  
                  $setuphold(posedge CLK, posedge NWRT, tES, tEH);
                  $setuphold(posedge CLK, posedge NCE, tES, tEH);
                  
                  $setuphold(posedge CLK, posedge DIN[0], tDS, tDH);
                  $setuphold(posedge CLK, posedge DIN[1], tDS, tDH);
                  $setuphold(posedge CLK, posedge DIN[2], tDS, tDH);
                  $setuphold(posedge CLK, posedge DIN[3], tDS, tDH);
                  $setuphold(posedge CLK, posedge DIN[4], tDS, tDH);
                  $setuphold(posedge CLK, posedge DIN[5], tDS, tDH);
                  $setuphold(posedge CLK, posedge DIN[6], tDS, tDH);
                  $setuphold(posedge CLK, posedge DIN[7], tDS, tDH);
                  $setuphold(posedge CLK, posedge DIN[8], tDS, tDH);
                  $setuphold(posedge CLK, posedge DIN[9], tDS, tDH);
                  $setuphold(posedge CLK, posedge DIN[10], tDS, tDH);
                  $setuphold(posedge CLK, posedge DIN[11], tDS, tDH);
                  $setuphold(posedge CLK, posedge DIN[12], tDS, tDH);
                  $setuphold(posedge CLK, posedge DIN[13], tDS, tDH);
                  $setuphold(posedge CLK, posedge DIN[14], tDS, tDH);
                  $setuphold(posedge CLK, posedge DIN[15], tDS, tDH);
                  $setuphold(posedge CLK, posedge DIN[16], tDS, tDH);
                  $setuphold(posedge CLK, posedge DIN[17], tDS, tDH);
                  $setuphold(posedge CLK, posedge DIN[18], tDS, tDH);
                  $setuphold(posedge CLK, posedge DIN[19], tDS, tDH);
                  $setuphold(posedge CLK, posedge DIN[20], tDS, tDH);
                  $setuphold(posedge CLK, posedge DIN[21], tDS, tDH);
                  $setuphold(posedge CLK, posedge DIN[22], tDS, tDH);
                  $setuphold(posedge CLK, posedge DIN[23], tDS, tDH);
                  $setuphold(posedge CLK, posedge DIN[24], tDS, tDH);
                  $setuphold(posedge CLK, posedge DIN[25], tDS, tDH);
                  $setuphold(posedge CLK, posedge DIN[26], tDS, tDH);
                  $setuphold(posedge CLK, posedge DIN[27], tDS, tDH);
                  $setuphold(posedge CLK, posedge DIN[28], tDS, tDH);
                  $setuphold(posedge CLK, posedge DIN[29], tDS, tDH);
                  $setuphold(posedge CLK, posedge DIN[30], tDS, tDH);
                  $setuphold(posedge CLK, posedge DIN[31], tDS, tDH);
                  $setuphold(posedge CLK, posedge DIN[32], tDS, tDH);
                  $setuphold(posedge CLK, posedge DIN[33], tDS, tDH);
                  $setuphold(posedge CLK, posedge DIN[34], tDS, tDH);
                  $setuphold(posedge CLK, posedge DIN[35], tDS, tDH);
                  $setuphold(posedge CLK, posedge DIN[36], tDS, tDH);
                  $setuphold(posedge CLK, posedge DIN[37], tDS, tDH);
                  $setuphold(posedge CLK, posedge DIN[38], tDS, tDH);
                  $setuphold(posedge CLK, posedge DIN[39], tDS, tDH);
				  $setuphold(posedge CLK, posedge DIN[40], tDS, tDH);
				  $setuphold(posedge CLK, posedge DIN[41], tDS, tDH);
				  $setuphold(posedge CLK, posedge DIN[42], tDS, tDH);
				  $setuphold(posedge CLK, posedge DIN[43], tDS, tDH);
                  $setuphold(posedge CLK, posedge DIN[44], tDS, tDH);
                  $setuphold(posedge CLK, posedge DIN[45], tDS, tDH);
                  $setuphold(posedge CLK, posedge DIN[46], tDS, tDH);
                  $setuphold(posedge CLK, posedge DIN[47], tDS, tDH);
				  $setuphold(posedge CLK, posedge DIN[48], tDS, tDH);
				  $setuphold(posedge CLK, posedge DIN[49], tDS, tDH);
				  $setuphold(posedge CLK, posedge DIN[50], tDS, tDH);
				  $setuphold(posedge CLK, posedge DIN[51], tDS, tDH);

                  
                  
                  (CLK => DO[0]) = (tPLH, tPHL);
                  (CLK => DO[1]) = (tPLH, tPHL);
                  (CLK => DO[2]) = (tPLH, tPHL);
                  (CLK => DO[3]) = (tPLH, tPHL);
                  (CLK => DO[4]) = (tPLH, tPHL);
                  (CLK => DO[5]) = (tPLH, tPHL);
                  (CLK => DO[6]) = (tPLH, tPHL);
                  (CLK => DO[7]) = (tPLH, tPHL);
                  (CLK => DO[8]) = (tPLH, tPHL);
                  (CLK => DO[9]) = (tPLH, tPHL);
                  (CLK => DO[10]) = (tPLH, tPHL);
                  (CLK => DO[11]) = (tPLH, tPHL);
                  (CLK => DO[12]) = (tPLH, tPHL);
                  (CLK => DO[13]) = (tPLH, tPHL);
                  (CLK => DO[14]) = (tPLH, tPHL);
                  (CLK => DO[15]) = (tPLH, tPHL);
                  (CLK => DO[16]) = (tPLH, tPHL);
                  (CLK => DO[17]) = (tPLH, tPHL);
                  (CLK => DO[18]) = (tPLH, tPHL);
                  (CLK => DO[19]) = (tPLH, tPHL);
                  (CLK => DO[20]) = (tPLH, tPHL);
                  (CLK => DO[21]) = (tPLH, tPHL);
                  (CLK => DO[22]) = (tPLH, tPHL);
                  (CLK => DO[23]) = (tPLH, tPHL); 
                  (CLK => DO[24]) = (tPLH, tPHL);
                  (CLK => DO[25]) = (tPLH, tPHL);
                  (CLK => DO[26]) = (tPLH, tPHL);
                  (CLK => DO[27]) = (tPLH, tPHL);
                  (CLK => DO[28]) = (tPLH, tPHL);
                  (CLK => DO[29]) = (tPLH, tPHL);
                  (CLK => DO[30]) = (tPLH, tPHL);
                  (CLK => DO[31]) = (tPLH, tPHL);
                  (CLK => DO[32]) = (tPLH, tPHL);
                  (CLK => DO[33]) = (tPLH, tPHL);
                  (CLK => DO[34]) = (tPLH, tPHL);
                  (CLK => DO[35]) = (tPLH, tPHL);
                  (CLK => DO[36]) = (tPLH, tPHL);
                  (CLK => DO[37]) = (tPLH, tPHL);
                  (CLK => DO[38]) = (tPLH, tPHL);
                  (CLK => DO[39]) = (tPLH, tPHL);
				  (CLK => DO[40]) = (tPLH, tPHL);
				  (CLK => DO[41]) = (tPLH, tPHL);
				  (CLK => DO[42]) = (tPLH, tPHL);
				  (CLK => DO[43]) = (tPLH, tPHL);
                  (CLK => DO[44]) = (tPLH, tPHL);
                  (CLK => DO[45]) = (tPLH, tPHL);
                  (CLK => DO[46]) = (tPLH, tPHL);
                  (CLK => DO[47]) = (tPLH, tPHL);
				  (CLK => DO[48]) = (tPLH, tPHL);
				  (CLK => DO[49]) = (tPLH, tPHL);
				  (CLK => DO[50]) = (tPLH, tPHL);
				  (CLK => DO[51]) = (tPLH, tPHL);
                  
                   $setuphold(posedge CLK, posedge RA[0], tDS, tDH, FLAG_X);
                   $setuphold(posedge CLK, posedge RA[1], tDS, tDH, FLAG_X);
                   $setuphold(posedge CLK, posedge RA[2], tDS, tDH, FLAG_X);
                   $setuphold(posedge CLK, posedge RA[3], tDS, tDH, FLAG_X);
                   $setuphold(posedge CLK, posedge RA[4], tDS, tDH, FLAG_X);
                   
                   
                   $setuphold(posedge CLK, posedge CA[0], tDS, tDH, FLAG_X);
                   $setuphold(posedge CLK, posedge CA[1], tDS, tDH, FLAG_X);
                   
                  $setuphold(posedge CLK, negedge NWRT, tES, tEH);
                  $setuphold(posedge CLK, negedge NCE, tES, tEH);
                          
                
                  $setuphold(posedge CLK, negedge DIN[0], tDS, tDH);
                  $setuphold(posedge CLK, negedge DIN[1], tDS, tDH);
                  $setuphold(posedge CLK, negedge DIN[2], tDS, tDH);
                  $setuphold(posedge CLK, negedge DIN[3], tDS, tDH);
                  $setuphold(posedge CLK, negedge DIN[4], tDS, tDH);
                  $setuphold(posedge CLK, negedge DIN[5], tDS, tDH);
                  $setuphold(posedge CLK, negedge DIN[6], tDS, tDH);
                  $setuphold(posedge CLK, negedge DIN[7], tDS, tDH);
                  $setuphold(posedge CLK, negedge DIN[8], tDS, tDH);
                  $setuphold(posedge CLK, negedge DIN[9], tDS, tDH);
                  $setuphold(posedge CLK, negedge DIN[10], tDS, tDH);
                  $setuphold(posedge CLK, negedge DIN[11], tDS, tDH);
                  $setuphold(posedge CLK, negedge DIN[12], tDS, tDH);
                  $setuphold(posedge CLK, negedge DIN[13], tDS, tDH);
                  $setuphold(posedge CLK, negedge DIN[14], tDS, tDH);
                  $setuphold(posedge CLK, negedge DIN[15], tDS, tDH);
                  $setuphold(posedge CLK, negedge DIN[16], tDS, tDH);
                  $setuphold(posedge CLK, negedge DIN[17], tDS, tDH);
                  $setuphold(posedge CLK, negedge DIN[18], tDS, tDH);
                  $setuphold(posedge CLK, negedge DIN[19], tDS, tDH);
                  $setuphold(posedge CLK, negedge DIN[20], tDS, tDH);
                  $setuphold(posedge CLK, negedge DIN[21], tDS, tDH);
                  $setuphold(posedge CLK, negedge DIN[22], tDS, tDH);
                  $setuphold(posedge CLK, negedge DIN[23], tDS, tDH);
                  $setuphold(posedge CLK, negedge DIN[24], tDS, tDH);
                  $setuphold(posedge CLK, negedge DIN[25], tDS, tDH);
                  $setuphold(posedge CLK, negedge DIN[26], tDS, tDH);
                  $setuphold(posedge CLK, negedge DIN[27], tDS, tDH);
                  $setuphold(posedge CLK, negedge DIN[28], tDS, tDH);
                  $setuphold(posedge CLK, negedge DIN[29], tDS, tDH);
                  $setuphold(posedge CLK, negedge DIN[30], tDS, tDH);
                  $setuphold(posedge CLK, negedge DIN[31], tDS, tDH);
                  $setuphold(posedge CLK, negedge DIN[32], tDS, tDH);
                  $setuphold(posedge CLK, negedge DIN[33], tDS, tDH);
                  $setuphold(posedge CLK, negedge DIN[34], tDS, tDH);
                  $setuphold(posedge CLK, negedge DIN[35], tDS, tDH);
                  $setuphold(posedge CLK, negedge DIN[36], tDS, tDH);
                  $setuphold(posedge CLK, negedge DIN[37], tDS, tDH);
                  $setuphold(posedge CLK, negedge DIN[38], tDS, tDH);
                  $setuphold(posedge CLK, negedge DIN[39], tDS, tDH);
				  $setuphold(posedge CLK, negedge DIN[40], tDS, tDH);
				  $setuphold(posedge CLK, negedge DIN[41], tDS, tDH);
				  $setuphold(posedge CLK, negedge DIN[42], tDS, tDH);
				  $setuphold(posedge CLK, negedge DIN[43], tDS, tDH);
                  $setuphold(posedge CLK, negedge DIN[44], tDS, tDH);
                  $setuphold(posedge CLK, negedge DIN[45], tDS, tDH);
                  $setuphold(posedge CLK, negedge DIN[46], tDS, tDH);
                  $setuphold(posedge CLK, negedge DIN[47], tDS, tDH);
				  $setuphold(posedge CLK, negedge DIN[48], tDS, tDH);
				  $setuphold(posedge CLK, negedge DIN[49], tDS, tDH);
				  $setuphold(posedge CLK, negedge DIN[50], tDS, tDH);
				  $setuphold(posedge CLK, negedge DIN[51], tDS, tDH);
                  
                  $setuphold(posedge CLK, negedge RA[0], tDS, tDH, FLAG_X);
                  $setuphold(posedge CLK, negedge RA[1], tDS, tDH, FLAG_X);
                  $setuphold(posedge CLK, negedge RA[2], tDS, tDH, FLAG_X);
                  $setuphold(posedge CLK, negedge RA[3], tDS, tDH, FLAG_X);
                  $setuphold(posedge CLK, negedge RA[4], tDS, tDH, FLAG_X);                  
                  
                  $setuphold(posedge CLK, negedge CA[0], tDS, tDH, FLAG_X);
                  $setuphold(posedge CLK, negedge CA[1], tDS, tDH, FLAG_X);
              endspecify
              
      endmodule

verilog/VLSI_experiment/6w/Practice_06_ref/Top_MBIST.v
`timescale 1 ns / 10 ps
`include "rflp128x52mx4.v"

module Top_MBIST(DATA_out, MBIST_done, MBIST_start, clk, rstn);
    output [52-1:0] DATA_out;
    output reg MBIST_done;
    input  MBIST_start;
    input  clk;
    input  rstn;

    wire [7-1:0] ADDR;
    wire [3-1:0] State_counter;
    reg [5-1:0] RA;
    reg [2-1:0] CA;
    reg NWRT, NCE;
    reg [52-1:0] Data_IN;
    counter_10b count({State_counter, ADDR}, clk, rstn);

    rflp128x52mx4 sram(DATA_out, Data_IN, RA, CA, NWRT, NCE, clk);

    always@ (posedge clk)
    begin
        if (MBIST_start == 1'b1)
            begin
                NCE <= 1'b0;
            end

        else if(State_counter[0] == 1'b0)
            begin
                NWRT <= 1'b0; // 메모리에 쓰기 시작.
                case (State_counter[2:1])
                    2'b00 : Data_IN <= 52'h0;
                    2'b01 : Data_IN <= 52'hfffffffffffff;
                    2'b10 : Data_IN <= 52'h5555555555555;
                    2'b11 : Data_IN <= 52'haaaaaaaaaaaaa;
                endcase
                {RA, CA} <= ADDR;
            end
        else if (State_counter[0] == 1'b1)
            begin
                NWRT <= 1'b1; // 메모리에서 읽기 시작.
                {RA, CA} <= ADDR;
            end
        if({State_counter, ADDR} == 10'b1111111111)
        begin
            MBIST_done <= 1'b1;
        end

        else
        begin end
    end
endmodule

module counter_10b (cnt, clk, rstn);
    output [10-1:0] cnt;
    input  clk, rstn;
    reg [10-1:0] cnt;

    always@(posedge clk or rstn)
    begin
        if(~rstn)
            begin  
                cnt <= 10'b0;
            end
        else if(cnt == 10'b1111111111)
            begin
                cnt <= 10'b0;
            end
        else
            begin
                cnt <= cnt + 1'b1;
            end
    end
endmodule

verilog/VLSI_experiment/6w/Practice_06_ref/stimulus_Top_MBIST.v
`timescale 1 ns / 10 ps
`include "Top_MBIST.v"
module stimulus_Top_MBIST;

	reg clk;
	reg rstn;
	reg MBIST_start;

	wire [52-1:0] out;
	wire out_done;

	Top_MBIST MBIST_TEST(.DATA_out(out), .MBIST_done(out_done), .MBIST_start(MBIST_start), .clk(clk), .rstn(rstn));

	always #5 clk <= ~clk;

	initial	
	begin
		$dumpfile("stimulus_Top_MBIST.vcd");
    	$dumpvars(0, stimulus_Top_MBIST);
		clk <= 1; rstn <= 0; MBIST_start <= 0;
		#20
		MBIST_start <= 1;
		#10
		MBIST_start <= 0; rstn <= 1; 
		#10300 $stop;
		$finish;
	end

endmodule

verilog/VLSI_experiment/6w/Practice_06_ref/stimulus_Top_MBIST.vcd
$date
	Fri Apr 14 22:03:11 2023
$end
$version
	Icarus Verilog
$end
$timescale
	10ps
$end
$scope module stimulus_Top_MBIST $end
$var wire 1 ! out_done $end
$var wire 52 " out [51:0] $end
$var reg 1 # MBIST_start $end
$var reg 1 $ clk $end
$var reg 1 % rstn $end
$scope module MBIST_TEST $end
$var wire 1 # MBIST_start $end
$var wire 1 $ clk $end
$var wire 1 % rstn $end
$var wire 3 & State_counter [2:0] $end
$var wire 52 ' DATA_out [51:0] $end
$var wire 7 ( ADDR [6:0] $end
$var reg 2 ) CA [1:0] $end
$var reg 52 * Data_IN [51:0] $end
$var reg 1 ! MBIST_done $end
$var reg 1 + NCE $end
$var reg 1 , NWRT $end
$var reg 5 - RA [4:0] $end
$scope module count $end
$var wire 1 $ clk $end
$var wire 1 % rstn $end
$var reg 10 . cnt [9:0] $end
$upscope $end
$scope module sram $end
$var event 1 / write $end
$var event 1 0 read $end
$var wire 2 1 CA [1:0] $end
$var wire 1 $ CLK $end
$var wire 52 2 DIN [51:0] $end
$var wire 1 + NCE $end
$var wire 1 , NWRT $end
$var wire 5 3 RA [4:0] $end
$var wire 52 4 DO [51:0] $end
$var wire 52 5 BDO [51:0] $end
$var wire 7 6 A [6:0] $end
$var reg 1 7 FLAG_X $end
$var reg 52 8 do_reg [51:0] $end
$var reg 7 9 r_addr [6:0] $end
$var reg 52 : r_din [51:0] $end
$var reg 1 ; r_nce $end
$var reg 1 < r_nwrt $end
$var reg 52 = temp_reg [51:0] $end
$var reg 52 > write_data [51:0] $end
$var integer 32 ? i [31:0] $end
$upscope $end
$upscope $end
$upscope $end
$enddefinitions $end
#0
$dumpvars
b10000000 ?
bx >
bx =
x<
x;
bx :
bx 9
bx 8
07
bx 6
bx 5
bx 4
bx 3
bx 2
bx 1
10
1/
b0 .
bx -
x,
x+
bx *
bx )
b0 (
bx '
b0 &
0%
1$
0#
bx "
x!
$end
#500
0$
#1000
b0 -
b0 3
b0 6
b0 )
b0 1
b0 *
b0 2
0,
1$
#1500
0$
#2000
0+
b0 9
b0 :
0<
1$
1#
#2500
0$
#3000
b1 (
0;
b1 .
1$
1%
0#
#3010
b0 >
1/
#3500
0$
#4000
b10 (
b10 .
b1 6
b1 )
b1 1
1$
#4010
b0 =
1/
#4500
0$
#5000
b11 (
b11 .
b10 6
b10 )
b10 1
b1 9
1$
#5010
bx =
1/
#5500
0$
#6000
b100 (
b100 .
b11 6
b11 )
b11 1
b10 9
1$
#6010
1/
#6500
0$
#7000
b101 (
b101 .
b1 -
b1 3
b100 6
b0 )
b0 1
b11 9
1$
#7010
1/
#7500
0$
#8000
b110 (
b110 .
b101 6
b1 )
b1 1
b100 9
1$
#8010
1/
#8500
0$
#9000
b111 (
b111 .
b110 6
b10 )
b10 1
b101 9
1$
#9010
1/
#9500
0$
#10000
b1000 (
b1000 .
b111 6
b11 )
b11 1
b110 9
1$
#10010
1/
#10500
0$
#11000
b1001 (
b1001 .
b10 -
b10 3
b1000 6
b0 )
b0 1
b111 9
1$
#11010
1/
#11500
0$
#12000
b1010 (
b1010 .
b1001 6
b1 )
b1 1
b1000 9
1$
#12010
1/
#12500
0$
#13000
b1011 (
b1011 .
b1010 6
b10 )
b10 1
b1001 9
1$
#13010
1/
#13500
0$
#14000
b1100 (
b1100 .
b1011 6
b11 )
b11 1
b1010 9
1$
#14010
1/
#14500
0$
#15000
b1101 (
b1101 .
b11 -
b11 3
b1100 6
b0 )
b0 1
b1011 9
1$
#15010
1/
#15500
0$
#16000
b1110 (
b1110 .
b1101 6
b1 )
b1 1
b1100 9
1$
#16010
1/
#16500
0$
#17000
b1111 (
b1111 .
b1110 6
b10 )
b10 1
b1101 9
1$
#17010
1/
#17500
0$
#18000
b10000 (
b10000 .
b1111 6
b11 )
b11 1
b1110 9
1$
#18010
1/
#18500
0$
#19000
b10001 (
b10001 .
b100 -
b100 3
b10000 6
b0 )
b0 1
b1111 9
1$
#19010
1/
#19500
0$
#20000
b10010 (
b10010 .
b10001 6
b1 )
b1 1
b10000 9
1$
#20010
1/
#20500
0$
#21000
b10011 (
b10011 .
b10010 6
b10 )
b10 1
b10001 9
1$
#21010
1/
#21500
0$
#22000
b10100 (
b10100 .
b10011 6
b11 )
b11 1
b10010 9
1$
#22010
1/
#22500
0$
#23000
b10101 (
b10101 .
b101 -
b101 3
b10100 6
b0 )
b0 1
b10011 9
1$
#23010
1/
#23500
0$
#24000
b10110 (
b10110 .
b10101 6
b1 )
b1 1
b10100 9
1$
#24010
1/
#24500
0$
#25000
b10111 (
b10111 .
b10110 6
b10 )
b10 1
b10101 9
1$
#25010
1/
#25500
0$
#26000
b11000 (
b11000 .
b10111 6
b11 )
b11 1
b10110 9
1$
#26010
1/
#26500
0$
#27000
b11001 (
b11001 .
b110 -
b110 3
b11000 6
b0 )
b0 1
b10111 9
1$
#27010
1/
#27500
0$
#28000
b11010 (
b11010 .
b11001 6
b1 )
b1 1
b11000 9
1$
#28010
1/
#28500
0$
#29000
b11011 (
b11011 .
b11010 6
b10 )
b10 1
b11001 9
1$
#29010
1/
#29500
0$
#30000
b11100 (
b11100 .
b11011 6
b11 )
b11 1
b11010 9
1$
#30010
1/
#30500
0$
#31000
b11101 (
b11101 .
b111 -
b111 3
b11100 6
b0 )
b0 1
b11011 9
1$
#31010
1/
#31500
0$
#32000
b11110 (
b11110 .
b11101 6
b1 )
b1 1
b11100 9
1$
#32010
1/
#32500
0$
#33000
b11111 (
b11111 .
b11110 6
b10 )
b10 1
b11101 9
1$
#33010
1/
#33500
0$
#34000
b100000 (
b100000 .
b11111 6
b11 )
b11 1
b11110 9
1$
#34010
1/
#34500
0$
#35000
b100001 (
b100001 .
b1000 -
b1000 3
b100000 6
b0 )
b0 1
b11111 9
1$
#35010
1/
#35500
0$
#36000
b100010 (
b100010 .
b100001 6
b1 )
b1 1
b100000 9
1$
#36010
1/
#36500
0$
#37000
b100011 (
b100011 .
b100010 6
b10 )
b10 1
b100001 9
1$
#37010
1/
#37500
0$
#38000
b100100 (
b100100 .
b100011 6
b11 )
b11 1
b100010 9
1$
#38010
1/
#38500
0$
#39000
b100101 (
b100101 .
b1001 -
b1001 3
b100100 6
b0 )
b0 1
b100011 9
1$
#39010
1/
#39500
0$
#40000
b100110 (
b100110 .
b100101 6
b1 )
b1 1
b100100 9
1$
#40010
1/
#40500
0$
#41000
b100111 (
b100111 .
b100110 6
b10 )
b10 1
b100101 9
1$
#41010
1/
#41500
0$
#42000
b101000 (
b101000 .
b100111 6
b11 )
b11 1
b100110 9
1$
#42010
1/
#42500
0$
#43000
b101001 (
b101001 .
b1010 -
b1010 3
b101000 6
b0 )
b0 1
b100111 9
1$
#43010
1/
#43500
0$
#44000
b101010 (
b101010 .
b101001 6
b1 )
b1 1
b101000 9
1$
#44010
1/
#44500
0$
#45000
b101011 (
b101011 .
b101010 6
b10 )
b10 1
b101001 9
1$
#45010
1/
#45500
0$
#46000
b101100 (
b101100 .
b101011 6
b11 )
b11 1
b101010 9
1$
#46010
1/
#46500
0$
#47000
b101101 (
b101101 .
b1011 -
b1011 3
b101100 6
b0 )
b0 1
b101011 9
1$
#47010
1/
#47500
0$
#48000
b101110 (
b101110 .
b101101 6
b1 )
b1 1
b101100 9
1$
#48010
1/
#48500
0$
#49000
b101111 (
b101111 .
b101110 6
b10 )
b10 1
b101101 9
1$
#49010
1/
#49500
0$
#50000
b110000 (
b110000 .
b101111 6
b11 )
b11 1
b101110 9
1$
#50010
1/
#50500
0$
#51000
b110001 (
b110001 .
b1100 -
b1100 3
b110000 6
b0 )
b0 1
b101111 9
1$
#51010
1/
#51500
0$
#52000
b110010 (
b110010 .
b110001 6
b1 )
b1 1
b110000 9
1$
#52010
1/
#52500
0$
#53000
b110011 (
b110011 .
b110010 6
b10 )
b10 1
b110001 9
1$
#53010
1/
#53500
0$
#54000
b110100 (
b110100 .
b110011 6
b11 )
b11 1
b110010 9
1$
#54010
1/
#54500
0$
#55000
b110101 (
b110101 .
b1101 -
b1101 3
b110100 6
b0 )
b0 1
b110011 9
1$
#55010
1/
#55500
0$
#56000
b110110 (
b110110 .
b110101 6
b1 )
b1 1
b110100 9
1$
#56010
1/
#56500
0$
#57000
b110111 (
b110111 .
b110110 6
b10 )
b10 1
b110101 9
1$
#57010
1/
#57500
0$
#58000
b111000 (
b111000 .
b110111 6
b11 )
b11 1
b110110 9
1$
#58010
1/
#58500
0$
#59000
b111001 (
b111001 .
b1110 -
b1110 3
b111000 6
b0 )
b0 1
b110111 9
1$
#59010
1/
#59500
0$
#60000
b111010 (
b111010 .
b111001 6
b1 )
b1 1
b111000 9
1$
#60010
1/
#60500
0$
#61000
b111011 (
b111011 .
b111010 6
b10 )
b10 1
b111001 9
1$
#61010
1/
#61500
0$
#62000
b111100 (
b111100 .
b111011 6
b11 )
b11 1
b111010 9
1$
#62010
1/
#62500
0$
#63000
b111101 (
b111101 .
b1111 -
b1111 3
b111100 6
b0 )
b0 1
b111011 9
1$
#63010
1/
#63500
0$
#64000
b111110 (
b111110 .
b111101 6
b1 )
b1 1
b111100 9
1$
#64010
1/
#64500
0$
#65000
b111111 (
b111111 .
b111110 6
b10 )
b10 1
b111101 9
1$
#65010
1/
#65500
0$
#66000
b1000000 (
b1000000 .
b111111 6
b11 )
b11 1
b111110 9
1$
#66010
1/
#66500
0$
#67000
b1000001 (
b1000001 .
b10000 -
b10000 3
b1000000 6
b0 )
b0 1
b111111 9
1$
#67010
1/
#67500
0$
#68000
b1000010 (
b1000010 .
b1000001 6
b1 )
b1 1
b1000000 9
1$
#68010
1/
#68500
0$
