verilog/VLSI_experiment/2w/full_adder_1bit.v
// full adder 1bit 만들기
// 수업 자료 보고 만들기.

module full_adder_1bit(sum, c_out, a, b, c_in);

    output sum, c_out;
    input a, b, c_in;

    wire s1, s2, c1;

    xor(s1, a, b);
    and(c1, a, b);
    xor(sum, s1, c_in);
    and(s2, s1, c_in);
    xor(c_out, s2, c1);
    
endmodule

verilog/VLSI_experiment/2w/full_adder_16bits/full_adder_16bits.v
// full adder 1bit 이어서 16bits adder 만들기
`include "full_adder_1bit.v"

module full_adder_16bits(sum[16:0], a[15:0], b[15:0], c_in);

    output  [16:0]sum;
    input   [15:0]a, b;
    input   c_in;

    wire [14:0]c;  // carry output

    full_adder_1bit fa0  ( sum[0], c[0],    a[0],  b[0],  c_in);
    full_adder_1bit fa1  ( sum[1], c[1],    a[1],  b[1],  c[0]);
    full_adder_1bit fa2  ( sum[2], c[2],    a[2],  b[2],  c[1]);
    full_adder_1bit fa3  ( sum[3], c[3],    a[3],  b[3],  c[2]);
    full_adder_1bit fa4  ( sum[4], c[4],    a[4],  b[4],  c[3]);
    full_adder_1bit fa5  ( sum[5], c[5],    a[5],  b[5],  c[4]);
    full_adder_1bit fa6  ( sum[6], c[6],    a[6],  b[6],  c[5]);
    full_adder_1bit fa7  ( sum[7], c[7],    a[7],  b[7],  c[6]);
    full_adder_1bit fa8  ( sum[8], c[8],    a[8],  b[8],  c[7]);
    full_adder_1bit fa9  ( sum[9], c[9],    a[9],  b[9],  c[8]);
    full_adder_1bit fa10 (sum[10], c[10],   a[10], b[10], c[9]);
    full_adder_1bit fa11 (sum[11], c[11],   a[11], b[11], c[10]);
    full_adder_1bit fa12 (sum[12], c[12],   a[12], b[12], c[11]);
    full_adder_1bit fa13 (sum[13], c[13],   a[13], b[13], c[12]);
    full_adder_1bit fa14 (sum[14], c[14],   a[14], b[14], c[13]);
    full_adder_1bit fa15 (sum[15], sum[16], a[15], b[15], c[14]);

endmodule

verilog/VLSI_experiment/2w/full_adder_16bits/full_adder_dff_16bits.v
// full adder 1bit 이어서 16bits adder 만들기
`include "full_adder_16bits.v"

module full_adder_dff_16bits(sum[16:0], a[15:0], b[15:0], c_in, clk, reset);

    output  [16:0]sum;
    input   [15:0]a, b;
    input   c_in;
    input   clk, reset;
    reg [16-1:0] a_q, b_q;   // input flip flop
    reg [17-1:0] sum;        // output flip flop
    reg c_in_ff;

    wire [14:0]c;  // carry output
    wire [17-1:0] sum_d;

    full_adder_16bits fa16 (sum_d, a_q, b_q, c_in_ff );

    // full_adder_1bit fa0  (sum_d[0],  c[0],    a_q[0],  b_q[0],  c_in_ff);
    // full_adder_1bit fa1  (sum_d[1],  c[1],    a_q[1],  b_q[1],  c[0]);
    // full_adder_1bit fa2  (sum_d[2],  c[2],    a_q[2],  b_q[2],  c[1]);
    // full_adder_1bit fa3  (sum_d[3],  c[3],    a_q[3],  b_q[3],  c[2]);
    // full_adder_1bit fa4  (sum_d[4],  c[4],    a_q[4],  b_q[4],  c[3]);
    // full_adder_1bit fa5  (sum_d[5],  c[5],    a_q[5],  b_q[5],  c[4]);
    // full_adder_1bit fa6  (sum_d[6],  c[6],    a_q[6],  b_q[6],  c[5]);
    // full_adder_1bit fa7  (sum_d[7],  c[7],    a_q[7],  b_q[7],  c[6]);
    // full_adder_1bit fa8  (sum_d[8],  c[8],    a_q[8],  b_q[8],  c[7]);
    // full_adder_1bit fa9  (sum_d[9],  c[9],    a_q[9],  b_q[9],  c[8]);
    // full_adder_1bit fa10 (sum_d[10], c[10],   a_q[10], b_q[10], c[9]);
    // full_adder_1bit fa11 (sum_d[11], c[11],   a_q[11], b_q[11], c[10]);
    // full_adder_1bit fa12 (sum_d[12], c[12],   a_q[12], b_q[12], c[11]);
    // full_adder_1bit fa13 (sum_d[13], c[13],   a_q[13], b_q[13], c[12]);
    // full_adder_1bit fa14 (sum_d[14], c[14],   a_q[14], b_q[14], c[13]);
    // full_adder_1bit fa15 (sum_d[15], sum_d[16], a_q[15], b_q[15], c[14]);

always @ (negedge clk) 
begin
if(reset) begin
    a_q <= 16'h0000;
    b_q <= 16'h0000;
    sum <= 17'b0; 
    c_in_ff <= 1'b0; end
else begin
    c_in_ff <= c_in;
    a_q <= a;
    b_q <= b;
    sum <= sum_d; end
end

endmodule

verilog/VLSI_experiment/2w/full_adder_16bits/full_adder_dff_16bits_tb.v
// full adder testbench
`include "full_adder_dff_16bits.v"
`timescale 1ns/1ns

module full_adder_dff_16bits_tb;

wire [17-1:0] sum;
reg [16-1:0] a, b;
reg [17-1:0] mat_sum;
reg clk;
reg reset;

reg [16-1:0] mat_a_input [0:99];
reg [16-1:0] mat_b_input [0:99];
reg [17-1:0] mat_sum_output [0:99];

full_adder_dff_16bits gate(sum, a, b, 1'b0, clk, reset);

integer i,j;
integer err;

initial
    begin
    clk = 1'b0;
    reset = 1'b1;
    #7 reset = 1'b0;
    end
initial
    for (j = 0; j < 200; j = j + 1)
    begin
        #5 clk = ~clk;
    end

initial begin
    $dumpfile("full_adder_dff_16bits_tb.vcd");
    $dumpvars(0, full_adder_dff_16bits_tb);


    $readmemh("Practice_02_ref/a_input.txt", mat_a_input);
    $readmemh("Practice_02_ref/b_input.txt", mat_b_input);
    $readmemh("Practice_02_ref/sum_output.txt", mat_sum_output);

    i = 0;
    err = 0;
    #(10);

    for (i = 0; i < 100; i = i + 1)
        begin
            a = mat_a_input[i];
            b = mat_b_input[i];
            mat_sum = mat_sum_output[i-1];
            #(2);
            if(sum != mat_sum)
                err = err + 1;
            #(8);
        end
    #(20)
    $finish;
end

endmodule

verilog/VLSI_experiment/2w/full_adder_16bits/full_adder_dff_16bits_tb.vcd
$date
	Tue Mar 21 22:00:41 2023
$end
$version
	Icarus Verilog
$end
$timescale
	1ns
$end
$scope module full_adder_dff_16bits_tb $end
$var wire 17 ! sum [16:0] $end
$var reg 16 " a [15:0] $end
$var reg 16 # b [15:0] $end
$var reg 1 $ clk $end
$var reg 17 % mat_sum [16:0] $end
$var reg 1 & reset $end
$var integer 32 ' err [31:0] $end
$var integer 32 ( i [31:0] $end
$var integer 32 ) j [31:0] $end
$scope module gate $end
$var wire 16 * a [15:0] $end
$var wire 16 + b [15:0] $end
$var wire 1 , c_in $end
$var wire 1 $ clk $end
$var wire 1 & reset $end
$var wire 17 - sum_d [16:0] $end
$var reg 16 . a_q [15:0] $end
$var reg 16 / b_q [15:0] $end
$var reg 1 0 c_in_ff $end
$var reg 17 1 sum [16:0] $end
$scope module fa16 $end
$var wire 16 2 a [15:0] $end
$var wire 16 3 b [15:0] $end
$var wire 1 0 c_in $end
$var wire 17 4 sum [16:0] $end
$var wire 15 5 c [14:0] $end
$scope module fa0 $end
$var wire 1 6 a $end
$var wire 1 7 b $end
$var wire 1 8 c1 $end
$var wire 1 0 c_in $end
$var wire 1 9 c_out $end
$var wire 1 : s1 $end
$var wire 1 ; s2 $end
$var wire 1 < sum $end
$upscope $end
$scope module fa1 $end
$var wire 1 = a $end
$var wire 1 > b $end
$var wire 1 ? c1 $end
$var wire 1 @ c_in $end
$var wire 1 A c_out $end
$var wire 1 B s1 $end
$var wire 1 C s2 $end
$var wire 1 D sum $end
$upscope $end
$scope module fa10 $end
$var wire 1 E a $end
$var wire 1 F b $end
$var wire 1 G c1 $end
$var wire 1 H c_in $end
$var wire 1 I c_out $end
$var wire 1 J s1 $end
$var wire 1 K s2 $end
$var wire 1 L sum $end
$upscope $end
$scope module fa11 $end
$var wire 1 M a $end
$var wire 1 N b $end
$var wire 1 O c1 $end
$var wire 1 P c_in $end
$var wire 1 Q c_out $end
$var wire 1 R s1 $end
$var wire 1 S s2 $end
$var wire 1 T sum $end
$upscope $end
$scope module fa12 $end
$var wire 1 U a $end
$var wire 1 V b $end
$var wire 1 W c1 $end
$var wire 1 X c_in $end
$var wire 1 Y c_out $end
$var wire 1 Z s1 $end
$var wire 1 [ s2 $end
$var wire 1 \ sum $end
$upscope $end
$scope module fa13 $end
$var wire 1 ] a $end
$var wire 1 ^ b $end
$var wire 1 _ c1 $end
$var wire 1 ` c_in $end
$var wire 1 a c_out $end
$var wire 1 b s1 $end
$var wire 1 c s2 $end
$var wire 1 d sum $end
$upscope $end
$scope module fa14 $end
$var wire 1 e a $end
$var wire 1 f b $end
$var wire 1 g c1 $end
$var wire 1 h c_in $end
$var wire 1 i c_out $end
$var wire 1 j s1 $end
$var wire 1 k s2 $end
$var wire 1 l sum $end
$upscope $end
$scope module fa15 $end
$var wire 1 m a $end
$var wire 1 n b $end
$var wire 1 o c1 $end
$var wire 1 p c_in $end
$var wire 1 q c_out $end
$var wire 1 r s1 $end
$var wire 1 s s2 $end
$var wire 1 t sum $end
$upscope $end
$scope module fa2 $end
$var wire 1 u a $end
$var wire 1 v b $end
$var wire 1 w c1 $end
$var wire 1 x c_in $end
$var wire 1 y c_out $end
$var wire 1 z s1 $end
$var wire 1 { s2 $end
$var wire 1 | sum $end
$upscope $end
$scope module fa3 $end
$var wire 1 } a $end
$var wire 1 ~ b $end
$var wire 1 !" c1 $end
$var wire 1 "" c_in $end
$var wire 1 #" c_out $end
$var wire 1 $" s1 $end
$var wire 1 %" s2 $end
$var wire 1 &" sum $end
$upscope $end
$scope module fa4 $end
$var wire 1 '" a $end
$var wire 1 (" b $end
$var wire 1 )" c1 $end
$var wire 1 *" c_in $end
$var wire 1 +" c_out $end
$var wire 1 ," s1 $end
$var wire 1 -" s2 $end
$var wire 1 ." sum $end
$upscope $end
$scope module fa5 $end
$var wire 1 /" a $end
$var wire 1 0" b $end
$var wire 1 1" c1 $end
$var wire 1 2" c_in $end
$var wire 1 3" c_out $end
$var wire 1 4" s1 $end
$var wire 1 5" s2 $end
$var wire 1 6" sum $end
$upscope $end
$scope module fa6 $end
$var wire 1 7" a $end
$var wire 1 8" b $end
$var wire 1 9" c1 $end
$var wire 1 :" c_in $end
$var wire 1 ;" c_out $end
$var wire 1 <" s1 $end
$var wire 1 =" s2 $end
$var wire 1 >" sum $end
$upscope $end
$scope module fa7 $end
$var wire 1 ?" a $end
$var wire 1 @" b $end
$var wire 1 A" c1 $end
$var wire 1 B" c_in $end
$var wire 1 C" c_out $end
$var wire 1 D" s1 $end
$var wire 1 E" s2 $end
$var wire 1 F" sum $end
$upscope $end
$scope module fa8 $end
$var wire 1 G" a $end
$var wire 1 H" b $end
$var wire 1 I" c1 $end
$var wire 1 J" c_in $end
$var wire 1 K" c_out $end
$var wire 1 L" s1 $end
$var wire 1 M" s2 $end
$var wire 1 N" sum $end
$upscope $end
$scope module fa9 $end
$var wire 1 O" a $end
$var wire 1 P" b $end
$var wire 1 Q" c1 $end
$var wire 1 R" c_in $end
$var wire 1 S" c_out $end
$var wire 1 T" s1 $end
$var wire 1 U" s2 $end
$var wire 1 V" sum $end
$upscope $end
$upscope $end
$upscope $end
$upscope $end
$enddefinitions $end
#0
$dumpvars
0V"
0U"
0T"
0S"
0R"
0Q"
0P"
0O"
0N"
0M"
0L"
0K"
0J"
0I"
0H"
0G"
0F"
0E"
0D"
0C"
0B"
0A"
0@"
0?"
0>"
0="
0<"
0;"
0:"
09"
08"
07"
06"
05"
04"
03"
02"
01"
00"
0/"
0."
0-"
0,"
0+"
0*"
0)"
0("
0'"
0&"
0%"
0$"
0#"
0""
0!"
0~
0}
0|
0{
0z
0y
0x
0w
0v
0u
0t
0s
0r
0q
0p
0o
0n
0m
0l
0k
0j
0i
0h
0g
0f
0e
0d
0c
0b
0a
0`
0_
0^
0]
0\
0[
0Z
0Y
0X
0W
0V
0U
0T
0S
0R
0Q
0P
0O
0N
0M
0L
0K
0J
0I
0H
0G
0F
0E
0D
0C
0B
0A
0@
0?
0>
0=
0<
0;
0:
09
08
07
06
b0 5
b0 4
b0 3
b0 2
b0 1
00
b0 /
b0 .
b0 -
0,
bx +
bx *
b0 )
b0 (
b0 '
1&
bx %
0$
bx #
bx "
b0 !
$end
#5
b1 )
1$
#7
0&
#10
1V"
1R"
1K"
1M"
1J"
1|
0N"
1T
1d
1<
1."
b110000000 5
1C"
1\
1l
b1111101000010101 -
b1111101000010101 4
1t
1z
1L"
1R
1b
1:
1,"
1A"
1Z
1j
1r
1v
1@"
1H"
1N
1^
16
1'"
1?"
1U
1e
1m
b10100110000100 /
b10100110000100 3
b1101000010010001 .
b1101000010010001 2
b10 )
0$
b10100110000100 #
b10100110000100 +
b1101000010010001 "
b1101000010010001 *
#15
b11 )
1$
#20
1X
1Q
0T
1S
1P
1I
1E"
1V"
1K
1J"
1p
1B"
1R"
1H
1D
0F"
1C"
0l
1i
1t
1q
16"
1;"
1N"
0M"
1K"
b100111111000000 5
1S"
0L
b11011001100110111 -
b11011001100110111 4
1\
1B
1D"
0A"
0j
1g
0r
1o
14"
19"
0L"
1I"
1Q"
1J
0Z
1>
1("
18"
0@"
1P"
0^
1f
1n
0'"
1/"
17"
1G"
1O"
1E
0U
1]
b1111101000010101 !
b1111101000010101 1
b1100101101010110 /
b1100101101010110 3
b1110011111100001 .
b1110011111100001 2
b100 )
0$
b1111101000010101 %
b1100101101010110 #
b1100101101010110 +
b1110011111100001 "
b1110011111100001 *
b1 (
#25
b101 )
1$
#30
1\
1X
1Q
0T
1S
1P
1I
0L
1K
0t
1J"
1x
0B"
1R"
1H
0p
1|
1&"
0."
0F"
0E"
1C"
0D
1A
0;"
0N"
1M"
1K"
0V"
1U"
1S"
1l
b111110000010 5
0i
b111000000101101 -
b111000000101101 4
0q
0z
1$"
0,"
0D"
1A"
0B
1?
09"
1L"
0I"
1T"
0Q"
1j
0g
0o
17
0v
1~
0("
10"
08"
1@"
1F
0n
06
1=
0/"
07"
0G"
0O"
0E
0e
0m
b11011001100110111 !
b11011001100110111 1
b100111110101011 /
b100111110101011 3
b10000010000010 .
b10000010000010 2
b110 )
0$
b11011001100110111 %
b100111110101011 #
b100111110101011 +
b10000010000010 "
b10000010000010 *
b10 (
#35
b111 )
1$
#40
1\
1X
1Q
12"
0T
1S
1+"
1P
1-"
1I
1*"
0L
1K
1#"
1H
0&"
1%"
1S"
1""
1C
1E"
0V"
1U"
1x
1y
1J"
1@
1B"
1R"
0D
1A
0|
1{
16"
0F"
1C"
0<
19
0."
1;"
1N"
0M"
b111111011111 5
1K"
b10111000100100000 -
b10111000100100000 4
1q
1B
0?
1z
04"
1D"
0A"
0:
18
1,"
19"
0L"
1I"
1o
0>
1v
00"
18"
0@"
0N
0f
1n
16
1'"
17"
1G"
1M
1e
1m
b111000000101101 !
b111000000101101 1
b1000011101001101 /
b1000011101001101 3
b1110100111010011 .
b1110100111010011 2
b1000 )
0$
b111000000101101 %
b1000011101001101 #
b1000011101001101 +
b1110100111010011 "
b1110100111010011 *
b11 (
#45
b1001 )
1$
#50
0\
0X
1""
1H
0Q
1y
1S"
1T
0S
06"
0|
1{
0*"
0V"
1U"
0P
02"
1>"
1x
0#"
1R"
0I
1h
0@
0+"
1:"
0D
0C
1A
1&"
0%"
0N"
1M"
1K"
1L
0K
0d
1a
1t
0q
1<
09
0."
0-"
b10001111100110 5
13"
b1100110001001001 -
b1100110001001001 4
1l
0B
1?
0$"
1L"
0I"
0J
0b
1_
1r
0o
1:
08
0,"
11"
0j
1>
0~
10"
0H"
0F
1N
1^
0n
06
0'"
1/"
0M
0e
b10111000100100000 !
b10111000100100000 1
b10101001100111 /
b10101001100111 3
b1010000111100010 .
b1010000111100010 2
b1010 )
0$
b10111000100100000 %
b10101001100111 #
b10101001100111 +
b1010000111100010 "
b1010000111100010 *
b100 (
#55
b1011 )
1$
#60
0L
0H
1J"
0S"
0&"
1C"
1V"
0U"
0""
0F"
1E"
1."
15"
0R"
1\
1d
0l
0y
1:"
1B"
0x
1*"
12"
0K"
1X
1`
0h
0|
0{
06"
13"
0>"
1="
1;"
1D
0A
1#"
1+"
1N"
0M"
b1011001100010011 -
b1011001100010011 4
0T
1Q
1Y
b1100011111000 5
0a
0z
14"
01"
1<"
09"
1B
0?
1!"
1)"
0L"
0R
1O
1W
0_
0v
1~
1("
00"
08"
1V
0^
1n
0=
1}
1'"
0G"
1M
1U
0]
0m
b1100110001001001 !
b1100110001001001 1
b1001101000011011 /
b1001101000011011 3
b1100011111000 .
b1100011111000 2
b1100 )
0$
b1100110001001001 %
b1001101000011011 #
b1001101000011011 +
b1100011111000 "
b1100011111000 *
b101 (
#65
b1101 )
1$
#70
1T
1P
0N"
1I
1|
0:"
0J"
1K
0\
0d
0*"
1B"
1x
02"
03"
0C"
1R"
1H
0X
0`
1p
1&"
0#"
0>"
0="
1;"
1t
0D
1A
1."
0-"
0+"
06"
05"
1F"
0E"
1K"
1V"
1S"
b1000101010011101 -
b1000101010011101 4
0L
0Q
0Y
b100011101000010 5
1i
1$"
0!"
0<"
19"
0r
0B
1?
1,"
0)"
04"
0D"
1I"
0T"
1Q"
1J
0O
0W
1g
07
0~
18"
1H"
0N
0V
1f
0n
16
1=
0'"
0/"
0?"
1G"
1O"
1E
0M
0U
1e
b1011001100010011 !
b1011001100010011 1
b100001101010010 /
b100001101010010 3
b100011101001011 .
b100011101001011 2
b1110 )
0$
b1011001100010011 %
b100001101010010 #
b100001101010010 +
b100011101001011 "
b100011101001011 *
b110 (
#75
b1111 )
1$
#80
1\
0|
0F"
1X
0t
1P
0x
0B"
0R"
0H
1Q
0p
16"
0L
0K
1I
1d
0A
0&"
1>"
0;"
1N"
0K"
1V"
0U"
0S"
0T
1S
b110000000000 5
0i
b10011001101110001 -
b10011001101110001 4
1q
14"
0J
1G
1b
0?
0$"
1<"
09"
1L"
0I"
1T"
0Q"
1R
0g
1o
17
0>
10"
1F
1^
0f
1n
06
0=
0}
07"
0G"
0O"
1M
0e
1m
b1000101010011101 !
b1000101010011101 1
b1010011101110001 /
b1010011101110001 3
b1000110000000000 .
b1000110000000000 2
b10000 )
0$
b1000101010011101 %
b1010011101110001 #
b1010011101110001 +
b1000110000000000 "
b1000110000000000 *
b111 (
#85
b10001 )
1$
#90
1F"
1B"
1;"
0>"
1="
1t
1:"
1p
13"
0\
1i
06"
15"
0X
1k
0P
12"
0Q
1`
1h
0V"
1L
0I
1D
1|
1&"
0."
1+"
0T
0S
1Y
1d
b111000001110000 5
1a
b11010010110001111 -
b11010010110001111 4
0l
0T"
1J
0G
1B
1z
1$"
0,"
1)"
0R
1W
0b
1_
1j
07
0H"
0P"
0F
1V
16
1=
1u
1}
1'"
1G"
0M
1U
1]
1e
b10011001101110001 !
b10011001101110001 1
b1011000001110000 /
b1011000001110000 3
b1111010100011111 .
b1111010100011111 2
b10010 )
0$
b10011001101110001 %
b1011000001110000 #
b1011000001110000 +
b1111010100011111 "
b1111010100011111 *
b1000 (
#95
b10011 )
1$
#100
1\
1""
1X
1y
1Q
0|
1{
0:"
0B"
0J"
1V"
1S
1x
03"
0;"
0C"
1R"
1P
02"
1H
0D
1A
06"
05"
0>"
0="
1F"
0E"
0N"
1K"
1L
1I
0T
0<
b11011011010001000 -
b11011011010001000 4
1&"
0+"
b111111100000110 5
1S"
0B
1?
04"
0<"
1D"
0L"
1I"
0J
1G
1R
0:
0$"
0)"
1Q"
1>
1v
0("
00"
08"
1@"
1H"
1P"
1F
1N
06
0u
0}
0'"
1O"
b11010010110001111 !
b11010010110001111 1
b1011111110000110 /
b1011111110000110 3
b1111011100000010 .
b1111011100000010 2
b10100 )
0$
b11010010110001111 %
b1011111110000110 #
b1011111110000110 +
b1111011100000010 "
b1111011100000010 *
b1001 (
#105
b10101 )
1$
#110
0""
0X
0y
0."
0Q
1|
0{
0*"
16"
0L
1T
0S
0d
0x
0#"
12"
1B"
0R"
0H
0P
0`
1F"
1<
1D
0A
1&"
0%"
1+"
1;"
1N"
0K"
1V"
0U"
0S"
0I
1\
0[
b110000001010000 5
0Y
b1001101110101111 -
b1001101110101111 4
0q
0D"
1:
1B
0?
1$"
1)"
19"
1L"
0I"
1T"
0Q"
0G
1Z
0W
0o
1("
18"
0@"
0F
0N
1f
0n
16
0=
1}
1'"
17"
0G"
0O"
0E
1M
0U
0e
0m
b11011011010001000 !
b11011011010001000 1
b111001101010110 /
b111001101010110 3
b10100001011001 .
b10100001011001 2
b10110 )
0$
b11011011010001000 %
b111001101010110 #
b111001101010110 +
b10100001011001 "
b10100001011001 *
b1010 (
#115
b10111 )
1$
#120
1p
1i
0l
1k
1>"
1c
1h
1:"
1`
1q
0D
0V"
1L
0d
1a
13"
0\
b111000001110000 5
1Y
b10000110111101101 -
b10000110111101101 4
0t
1s
0B
0T"
1J
1b
0_
11"
0Z
1W
1r
17
0>
10"
0P"
1F
0^
0f
06
1/"
1U
1e
1m
b1001101110101111 !
b1001101110101111 1
b1010101110101 /
b1010101110101 3
b1111100001111000 .
b1111100001111000 2
b11000 )
0$
b1001101110101111 %
b1010101110101 #
b1010101110101 +
b1111100001111000 "
b1111100001111000 *
b1011 (
#125
b11001 )
1$
#130
0\
0X
0Q
1T
0S
0P
0I
1L
0K
0H
0S"
0U"
1q
0R"
0t
1s
0K"
1p
1N"
0M"
1i
1-"
0J"
0l
1k
16"
0>"
1*"
0C"
1h
12"
0:"
0B"
0<
1D
0&"
1#"
1F"
0E"
1V"
1d
0c
1a
b10010111110100110 -
b10010111110100110 4
0."
1+"
03"
b111000000011000 5
0;"
0:
1B
0$"
1!"
1D"
1T"
0b
1_
1,"
0)"
01"
09"
07
1>
1~
00"
08"
1@"
0H"
1P"
0F
1N
1^
0'"
0/"
07"
1G"
1E
0M
b10000110111101101 !
b10000110111101101 1
b11101010011110 /
b11101010011110 3
b1111010100001000 .
b1111010100001000 2
b11010 )
0$
b10000110111101101 %
b11101010011110 #
b11101010011110 +
b1111010100001000 "
b1111010100001000 *
b1100 (
#135
b11011 )
1$
#140
1R"
1K"
06"
0N"
1M"
02"
1J"
1q
0+"
1C"
1d
0t
1s
1."
0-"
0F"
1E"
1[
1`
1p
0*"
1B"
1X
0D
0|
1V"
0\
1Y
1l
0k
1i
1<
0#"
1;"
b10110011000010001 -
b10110011000010001 4
0T
b111100111000000 5
1Q
0B
0z
0T"
1Z
0W
0j
1g
1:
0!"
19"
0R
1O
0>
0v
0~
18"
1H"
0P"
0V
1f
1n
16
0}
17"
0G"
1M
0m
b10010111110100110 !
b10010111110100110 1
b1110100111010000 /
b1110100111010000 3
b111110001000001 .
b111110001000001 2
b11100 )
0$
b10010111110100110 %
b1110100111010000 #
b1110100111010000 +
b111110001000001 "
b111110001000001 *
b1101 (
#145
b11101 )
1$
#150
16"
12"
1+"
0."
1-"
0R"
1*"
0K"
1#"
1N"
0M"
1%"
0J"
1""
0C"
0q
1y
1F"
0E"
0H
1S
1t
0s
1{
0`
0B"
0S"
1P
1X
0p
1x
0Y
0h
1>"
0;"
1V"
0U"
0L
1I
0T
1Q
1l
0k
0i
1A
0|
0&"
1\
0[
b1111001111100001 -
b1111001111100001 4
1d
0c
b110000011110 5
0a
1<"
09"
1T"
0J
1G
1R
0O
1j
0g
1?
1z
1$"
0Z
1b
0_
1>
0("
08"
0@"
1P"
1F
0N
0f
0n
1=
1u
1}
1'"
1?"
0U
0]
1m
b10110011000010001 !
b10110011000010001 1
b10011100000010 /
b10011100000010 3
b1100110011011111 .
b1100110011011111 2
b11110 )
0$
b10110011000010001 %
b10011100000010 #
b10011100000010 +
b1100110011011111 "
b1100110011011111 *
b1110 (
#155
b11111 )
1$
#160
0q
1t
0s
0p
02"
0i
0+"
1l
0k
1."
0-"
0h
0*"
0a
0#"
1d
0c
1&"
0%"
0:"
0`
0""
0X
0x
03"
1B"
0P
0Y
0y
0Q
1D
0A
16"
05"
0>"
1;"
1L
b1000000 5
0I
1\
0[
0<
0|
0{
1F"
b1111011110111010 -
b1111011110111010 4
0T
0S
1B
0?
14"
0<"
19"
1J
0G
1Z
0:
0z
0D"
0R
0>
1~
10"
18"
0F
1V
0^
1f
1n
06
0u
0}
0?"
0M
1]
0e
0m
b1111001111100001 !
b1111001111100001 1
b1101001101101000 /
b1101001101101000 3
b10010001010010 .
b10010001010010 2
b100000 )
0$
b1111001111100001 %
b1101001101101000 #
b1101001101101000 +
b10010001010010 "
b10010001010010 *
b1111 (
#165
b100001 )
1$
#170
1>"
1:"
1H
13"
1S"
06"
15"
0V"
1U"
12"
1J"
1R"
1X
0."
1+"
1\
0D
1C"
1N"
1K"
b1111010111001000 -
b1111010111001000 4
1L
b101111110000 5
1Q
0,"
1)"
0Z
0B
1A"
0L"
1I"
0J
1O
0~
1("
00"
1@"
0P"
1N
0V
0f
0=
1}
1/"
1?"
1G"
1O"
0E
1M
1e
b1111011110111010 !
b1111011110111010 1
b1000100111010000 /
b1000100111010000 3
b110101111111000 .
b110101111111000 2
b100010 )
0$
b1111011110111010 %
b1000100111010000 #
b1000100111010000 +
b110101111111000 "
b110101111111000 *
b10000 (
#175
b100011 )
1$
#180
0:"
1T
03"
0F"
1P
1`
16"
05"
0B"
1H
1I
1Y
1h
1p
02"
0J"
0R"
1D
1>"
0="
0;"
0V"
0U"
1S"
0L
1K
0\
1[
1d
1a
1l
1i
1<
1|
0+"
0C"
1N"
0M"
b111111000000000 5
0K"
1t
b11110100101101111 -
b11110100101101111 4
1q
1B
1<"
09"
0T"
1Q"
1J
1Z
0b
1_
0j
1g
1:
1z
0)"
0A"
1L"
0I"
0r
1o
1>
0("
08"
0@"
1P"
1F
1V
1^
1f
16
1u
0'"
0?"
0G"
1m
b1111010111001000 !
b1111010111001000 1
b1111111100000010 /
b1111111100000010 3
b1110101001101101 .
b1110101001101101 2
b100100 )
0$
b1111010111001000 %
b1111111100000010 #
b1111111100000010 +
b1110101001101101 "
b1110101001101101 *
b10001 (
#185
b100101 )
1$
#190
1."
1*"
1#"
0d
0&"
1%"
0P
0`
1""
0I
0Y
1y
1L
0K
1\
0[
0|
1{
0H
0X
0p
1x
0h
0N"
1V"
0S"
1T
0S
0Q
1l
0k
0i
1t
0s
0q
0D
1A
06"
b1101111011010001 -
b1101111011010001 4
1F"
b1110 5
0a
0L"
1T"
0Q"
1R
0O
1j
0g
1r
0o
0B
1?
04"
1D"
0_
17
0H"
0P"
0N
0^
0f
0n
06
1=
0/"
1?"
0]
b11110100101101111 !
b11110100101101111 1
b1010000000011 /
b1010000000011 3
b1100101011001110 .
b1100101011001110 2
b100110 )
0$
b11110100101101111 %
b1010000000011 #
b1010000000011 +
b1100101011001110 "
b1100101011001110 *
b10010 (
#195
b100111 )
1$
#200
0N"
0J"
0C"
1F"
0E"
0B"
0;"
1>"
0="
0:"
03"
05"
1q
02"
0t
1s
1C
0""
0*"
1d
0+"
1p
1@
1x
0y
0#"
1R"
1`
1h
1."
0-"
1l
1i
0<
19
0D
1A
1|
0{
0&"
0%"
16"
1K"
1V"
0T
b10110011011110100 -
b10110011011110100 4
0\
1Y
b111000100000011 5
1a
1,"
0j
1g
0:
18
1B
0?
0z
0$"
14"
1I"
0T"
0R
0Z
1W
1_
1("
18"
1H"
0F
1^
1f
16
0=
0u
0}
1/"
07"
1G"
0O"
1E
0M
1U
1]
b1101111011010001 !
b1101111011010001 1
b111000101010011 /
b111000101010011 3
b1111010110100001 .
b1111010110100001 2
b101000 )
0$
b1101111011010001 %
b111000101010011 #
b111000101010011 +
b1111010110100001 "
b1111010110100001 *
b10011 (
#205
b101001 )
1$
#210
1[
1X
1Q
0|
1N"
1S
0x
12"
1J"
1P
0A
1+"
1C"
1I
0q
1l
1D
0C
1&"
0."
1-"
0F"
1E"
0L
1K
1t
0s
1h
0@
1""
1*"
1B"
1H
1`
0p
0T
0d
1c
1a
1<
09
1y
1#"
16"
0>"
1;"
1S"
b1100001100101011 -
b1100001100101011 4
0\
1Y
b11111111011100 5
0i
1R
1b
0_
1:
08
1w
1!"
04"
0<"
19"
1Q"
1Z
0W
0g
0>
1v
1~
0("
1P"
1N
0^
0f
06
1=
1u
1}
1'"
0/"
17"
1O"
0U
0e
b10110011011110100 !
b10110011011110100 1
b1101101001101 /
b1101101001101 3
b1010011111011110 .
b1010011111011110 2
b101010 )
0$
b10110011011110100 %
b1101101001101 #
b1101101001101 +
b1010011111011110 "
b1010011111011110 *
b10100 (
#215
b101011 )
1$
#220
0h
0a
1d
0c
0`
0Y
1\
0[
0X
0Q
16"
1T
0S
0q
12"
0P
1t
0s
1+"
0I
0p
0."
1-"
1>"
0J"
1L
0K
0R"
0i
1*"
1:"
0B"
0C"
0H
0<
1N"
0M"
0K"
1l
0k
0&"
1%"
1#"
13"
0;"
0F"
0E"
b1111111101100010 -
b1111111101100010 4
1V"
0U"
b111100 5
0S"
0:
1L"
0I"
1j
1$"
0!"
11"
09"
0D"
1T"
0Q"
07
1>
1("
10"
08"
0H"
1F
0N
1^
1f
1n
0=
0}
0'"
1/"
07"
0?"
0O"
0E
1M
0]
0m
b1100001100101011 !
b1100001100101011 1
b1111011000111110 /
b1111011000111110 3
b100100100100 .
b100100100100 2
b101100 )
0$
b1100001100101011 %
b1111011000111110 #
b1111011000111110 +
b100100100100 "
b100100100100 *
b10101 (
#225
b101101 )
1$
#230
0*"
06"
0#"
1F"
02"
1&"
0%"
1B"
0+"
1R"
0""
1;"
1<
0."
0-"
0N"
1K"
1V"
0L
0d
1|
b101100000 5
0y
b1101101010001111 -
b1101101010001111 4
0>"
1="
1:
0,"
0L"
1I"
0T"
0J
0b
1z
0w
1<"
17
0("
1H"
0P"
0F
0V
0^
0f
0n
0u
17"
1U
1e
1m
b1111111101100010 !
b1111111101100010 1
b100101111 /
b100101111 3
b1101100101100000 .
b1101100101100000 2
b101110 )
0$
b1111111101100010 %
b100101111 #
b100101111 +
b1101100101100000 "
b1101100101100000 *
b10110 (
#235
b101111 )
1$
