verilog/digitalsystem6/sr.v
module sr_latch(s, r, Q, nQ);
  input s,r;
  output Q, nQ;
  assign Q = ~ (s & nQ);
  assign nQ = ~ (r & Q);
endmodule

verilog/digital_system_experiment/digitalsystem6/d_ff.v
`include "sr.v"
module D_FF(CLK, D, set, Q, nQ);

  input CLK, D, set;
  output Q, nQ;
  wire w1, w2, w3,  w4;  
  
  sr_latch L1(w4|set, CLK&(~set), w1, w2);
  sr_latch L2((CLK&w2)|set, D&(~set), w3,  w4);
  sr_latch L3(w2, w3, Q, nQ);

endmodule

verilog/digitalsystem6/reg.v
`include "d_ff.v"
module register(CLK, SI, SO);
   input SI, CLK;
   output [3:0] SO;
   wire[3:0] SO;
   D_FF F1(.CLK(CLK), .D(SI), .set(1'b0),.Q(SO[0]), .nQ());
   D_FF F2(.CLK(CLK), .D(SO[0]),.set(1'b0), .Q(SO[1]), .nQ());
   D_FF F3(.CLK(CLK), .D(SO[1]),.set(1'b0), .Q(SO[2]), .nQ());
   D_FF F4(.CLK(CLK), .D(SO[2]),.set(1'b0), .Q(SO[3]), .nQ());
endmodule

verilog/digital_system_experiment/digitalsystem6/reg_tb.v
`include "reg.v"
module register_tb;

reg SI,CLK;
wire [3:0]SO;

always #5 CLK <= ~CLK;

register reg1(CLK, SI, SO);

initial begin
    $dumpfile("reg_tb.vcd");
    $dumpvars(0,register_tb);
    CLK <= 1'b0;
    SI <= 1'b0; #50;
    SI <= 1'b1; #50;
    SI <= 1'b0; #50;
    SI <= 1'b1; #50;
    SI <= 1'b0; #50;
    $finish;
end

endmodule

verilog/digitalsystem6/reg_tb.vcd
$date
	Wed Oct 16 23:47:59 2019
$end
$version
	Icarus Verilog
$end
$timescale
	1s
$end
$scope module register_tb $end
$var wire 4 ! SO [3:0] $end
$var reg 1 " CLK $end
$var reg 1 # SI $end
$scope module reg1 $end
$var wire 1 " CLK $end
$var wire 1 # SI $end
$var wire 4 $ SO [3:0] $end
$scope module F1 $end
$var wire 1 " CLK $end
$var wire 1 # D $end
$var wire 1 % set $end
$var wire 1 & w4 $end
$var wire 1 ' w3 $end
$var wire 1 ( w2 $end
$var wire 1 ) w1 $end
$var wire 1 * nQ $end
$var wire 1 + Q $end
$scope module L1 $end
$var wire 1 ) Q $end
$var wire 1 ( nQ $end
$var wire 1 , r $end
$var wire 1 - s $end
$upscope $end
$scope module L2 $end
$var wire 1 ' Q $end
$var wire 1 & nQ $end
$var wire 1 . r $end
$var wire 1 / s $end
$upscope $end
$scope module L3 $end
$var wire 1 + Q $end
$var wire 1 * nQ $end
$var wire 1 ' r $end
$var wire 1 ( s $end
$upscope $end
$upscope $end
$scope module F2 $end
$var wire 1 " CLK $end
$var wire 1 0 D $end
$var wire 1 1 set $end
$var wire 1 2 w4 $end
$var wire 1 3 w3 $end
$var wire 1 4 w2 $end
$var wire 1 5 w1 $end
$var wire 1 6 nQ $end
$var wire 1 7 Q $end
$scope module L1 $end
$var wire 1 5 Q $end
$var wire 1 4 nQ $end
$var wire 1 8 r $end
$var wire 1 9 s $end
$upscope $end
$scope module L2 $end
$var wire 1 3 Q $end
$var wire 1 2 nQ $end
$var wire 1 : r $end
$var wire 1 ; s $end
$upscope $end
$scope module L3 $end
$var wire 1 7 Q $end
$var wire 1 6 nQ $end
$var wire 1 3 r $end
$var wire 1 4 s $end
$upscope $end
$upscope $end
$scope module F3 $end
$var wire 1 " CLK $end
$var wire 1 < D $end
$var wire 1 = set $end
$var wire 1 > w4 $end
$var wire 1 ? w3 $end
$var wire 1 @ w2 $end
$var wire 1 A w1 $end
$var wire 1 B nQ $end
$var wire 1 C Q $end
$scope module L1 $end
$var wire 1 A Q $end
$var wire 1 @ nQ $end
$var wire 1 D r $end
$var wire 1 E s $end
$upscope $end
$scope module L2 $end
$var wire 1 ? Q $end
$var wire 1 > nQ $end
$var wire 1 F r $end
$var wire 1 G s $end
$upscope $end
$scope module L3 $end
$var wire 1 C Q $end
$var wire 1 B nQ $end
$var wire 1 ? r $end
$var wire 1 @ s $end
$upscope $end
$upscope $end
$scope module F4 $end
$var wire 1 " CLK $end
$var wire 1 H D $end
$var wire 1 I set $end
$var wire 1 J w4 $end
$var wire 1 K w3 $end
$var wire 1 L w2 $end
$var wire 1 M w1 $end
$var wire 1 N nQ $end
$var wire 1 O Q $end
$scope module L1 $end
$var wire 1 M Q $end
$var wire 1 L nQ $end
$var wire 1 P r $end
$var wire 1 Q s $end
$upscope $end
$scope module L2 $end
$var wire 1 K Q $end
$var wire 1 J nQ $end
$var wire 1 R r $end
$var wire 1 S s $end
$upscope $end
$scope module L3 $end
$var wire 1 O Q $end
$var wire 1 N nQ $end
$var wire 1 K r $end
$var wire 1 L s $end
$upscope $end
$upscope $end
$upscope $end
$upscope $end
$enddefinitions $end
#0
$dumpvars
0S
xR
xQ
0P
xO
xN
xM
1L
1K
xJ
0I
xH
0G
xF
xE
0D
xC
xB
xA
1@
1?
x>
0=
x<
0;
x:
x9
08
x7
x6
x5
14
13
x2
01
x0
0/
0.
1-
0,
x+
x*
0)
1(
1'
1&
0%
bx $
0#
0"
bx !
$end
#5
19
12
0:
00
bx0 !
bx0 $
0+
1*
0'
x3
x?
xK
x4
x@
xL
1/
x;
xG
xS
1,
18
1D
1P
1"
#10
05
1'
13
1?
1K
14
1@
1L
0/
0;
0G
0S
0,
08
0D
0P
0"
#15
1E
1>
0F
0<
bx00 !
bx00 $
07
16
0'
03
x?
xK
x@
xL
1/
1;
xG
xS
1,
18
1D
1P
1"
#20
0A
1'
13
1?
1K
1@
1L
0/
0;
0G
0S
0,
08
0D
0P
0"
#25
1Q
1J
0R
0H
bx000 !
bx000 $
0C
1B
0'
03
0?
xK
xL
1/
1;
1G
xS
1,
18
1D
1P
1"
#30
0M
1'
13
1?
1K
1L
0/
0;
0G
0S
0,
08
0D
0P
0"
#35
b0 !
b0 $
0O
1N
0'
03
0?
0K
1/
1;
1G
1S
1,
18
1D
1P
1"
#40
1'
13
1?
1K
0/
0;
0G
0S
0,
08
0D
0P
0"
#45
0'
03
0?
0K
1/
1;
1G
1S
1,
18
1D
1P
1"
#50
1)
0-
0&
1'
13
1?
1K
0/
0;
0G
0S
0,
08
0D
0P
1.
0"
1#
#55
0*
1:
10
b1 !
b1 $
1+
03
0?
0K
0(
0/
1;
1G
1S
1,
18
1D
1P
1"
#60
15
09
02
13
1?
1K
1(
0;
0G
0S
0,
08
0D
0P
0"
#65
06
1F
1<
b11 !
b11 $
17
0?
0K
0(
04
0/
0;
1G
1S
1,
18
1D
1P
1"
#70
1A
0E
0>
1?
1K
1(
14
0G
0S
0,
08
0D
0P
0"
#75
0B
1R
1H
b111 !
b111 $
1C
0K
0(
04
0@
0/
0;
0G
1S
1,
18
1D
1P
1"
#80
1M
0Q
0J
1K
1(
14
1@
0S
0,
08
0D
0P
0"
#85
0N
b1111 !
b1111 $
1O
0(
04
0@
0L
0/
0;
0G
0S
1,
18
1D
1P
1"
#90
1(
14
1@
1L
0,
08
0D
0P
0"
#95
0(
04
0@
0L
0/
0;
0G
0S
1,
18
1D
1P
1"
#100
0)
1-
1(
14
1@
1L
1&
0,
08
0D
0P
0.
0"
0#
#105
19
12
0:
00
b1110 !
b1110 $
0+
1*
0'
04
0@
0L
1/
0;
0G
0S
1,
18
1D
1P
1"
#110
05
1'
14
1@
1L
0/
0,
08
0D
0P
0"
#115
1E
1>
0F
0<
b1100 !
b1100 $
07
16
0'
03
0@
0L
1/
1;
0G
0S
1,
18
1D
1P
1"
#120
0A
1'
13
1@
1L
0/
0;
0,
08
0D
0P
0"
#125
1Q
1J
0R
0H
b1000 !
b1000 $
0C
1B
0'
03
0?
0L
1/
1;
1G
0S
1,
18
1D
1P
1"
#130
0M
1'
13
1?
1L
0/
0;
0G
0,
08
0D
0P
0"
#135
b0 !
b0 $
0O
1N
0'
03
0?
0K
1/
1;
1G
1S
1,
18
1D
1P
1"
#140
1'
13
1?
1K
0/
0;
0G
0S
0,
08
0D
0P
0"
#145
0'
03
0?
0K
1/
1;
1G
1S
1,
18
1D
1P
1"
#150
1)
0-
0&
1'
13
1?
1K
0/
0;
0G
0S
0,
08
0D
0P
1.
0"
1#
#155
0*
1:
10
b1 !
b1 $
1+
03
0?
0K
0(
0/
1;
1G
1S
1,
18
1D
1P
1"
#160
15
09
02
13
1?
1K
1(
0;
0G
0S
0,
08
0D
0P
0"
#165
06
1F
1<
b11 !
b11 $
17
0?
0K
0(
04
0/
0;
1G
1S
1,
18
1D
1P
1"
#170
1A
0E
0>
1?
1K
1(
14
0G
0S
0,
08
0D
0P
0"
#175
0B
1R
1H
b111 !
b111 $
1C
0K
0(
04
0@
0/
0;
0G
1S
1,
18
1D
1P
1"
#180
1M
0Q
0J
1K
1(
14
1@
0S
0,
08
0D
0P
0"
#185
0N
b1111 !
b1111 $
1O
0(
04
0@
0L
0/
0;
0G
0S
1,
18
1D
1P
1"
#190
1(
14
1@
1L
0,
08
0D
0P
0"
#195
0(
04
0@
0L
0/
0;
0G
0S
1,
18
1D
1P
1"
#200
0)
1-
1(
14
1@
1L
1&
0,
08
0D
0P
0.
0"
0#
#205
19
12
0:
00
b1110 !
b1110 $
0+
1*
0'
04
0@
0L
1/
0;
0G
0S
1,
18
1D
1P
1"
#210
05
1'
14
1@
1L
0/
0,
08
0D
0P
0"
#215
1E
1>
0F
0<
b1100 !
b1100 $
07
16
0'
03
0@
0L
1/
1;
0G
0S
1,
18
1D
1P
1"
#220
0A
1'
13
1@
1L
0/
0;
0,
08
0D
0P
0"
#225
1Q
1J
0R
0H
b1000 !
b1000 $
0C
1B
0'
03
0?
0L
1/
1;
1G
0S
1,
18
1D
1P
1"
#230
0M
1'
13
1?
1L
0/
0;
0G
0,
08
0D
0P
0"
#235
b0 !
b0 $
0O
1N
0'
03
0?
0K
1/
1;
1G
1S
1,
18
1D
1P
1"
#240
1'
13
1?
1K
0/
0;
0G
0S
0,
08
0D
0P
0"
#245
0'
03
0?
0K
1/
1;
1G
1S
1,
18
1D
1P
1"
#250
1'
13
1?
1K
0/
0;
0G
0S
0,
08
0D
0P
0"
