verilog/VLSI_experiment/2w/full_adder_1bit.v
// full adder 1bit 만들기
// 수업 자료 보고 만들기.

module full_adder_1bit(sum, c_out, a, b, c_in);

    output sum, c_out;
    input a, b, c_in;

    wire s1, s2, c1;

    xor(s1, a, b);
    and(c1, a, b);
    xor(sum, s1, c_in);
    and(s2, s1, c_in);
    xor(c_out, s2, c1);
    
endmodule

verilog/VLSI_experiment/2w/full_adder_16bits/full_adder_16bits.v
// full adder 1bit 이어서 16bits adder 만들기
`include "full_adder_1bit.v"

module full_adder_16bits(sum[16:0], a[15:0], b[15:0], c_in);

    output  [16:0]sum;
    input   [15:0]a, b;
    input   c_in;

    wire [14:0]c;  // carry output

    full_adder_1bit fa0  ( sum[0], c[0],    a[0],  b[0],  c_in);
    full_adder_1bit fa1  ( sum[1], c[1],    a[1],  b[1],  c[0]);
    full_adder_1bit fa2  ( sum[2], c[2],    a[2],  b[2],  c[1]);
    full_adder_1bit fa3  ( sum[3], c[3],    a[3],  b[3],  c[2]);
    full_adder_1bit fa4  ( sum[4], c[4],    a[4],  b[4],  c[3]);
    full_adder_1bit fa5  ( sum[5], c[5],    a[5],  b[5],  c[4]);
    full_adder_1bit fa6  ( sum[6], c[6],    a[6],  b[6],  c[5]);
    full_adder_1bit fa7  ( sum[7], c[7],    a[7],  b[7],  c[6]);
    full_adder_1bit fa8  ( sum[8], c[8],    a[8],  b[8],  c[7]);
    full_adder_1bit fa9  ( sum[9], c[9],    a[9],  b[9],  c[8]);
    full_adder_1bit fa10 (sum[10], c[10],   a[10], b[10], c[9]);
    full_adder_1bit fa11 (sum[11], c[11],   a[11], b[11], c[10]);
    full_adder_1bit fa12 (sum[12], c[12],   a[12], b[12], c[11]);
    full_adder_1bit fa13 (sum[13], c[13],   a[13], b[13], c[12]);
    full_adder_1bit fa14 (sum[14], c[14],   a[14], b[14], c[13]);
    full_adder_1bit fa15 (sum[15], sum[16], a[15], b[15], c[14]);

endmodule

verilog/VLSI_experiment/2w/full_adder_16bits_tb.v
// full adder testbench
`include "full_adder_16bits.v"

module full_adder_16bits_tb;

wire [17-1:0] sum;
reg [16-1:0] a, b;
reg [17-1:0] mat_sum;

reg [16-1:0] mat_a_input [0:99];
reg [16-1:0] mat_b_input [0:99];
reg [17-1:0] mat_sum_output [0:99];

full_adder_16bits gate(sum, a, b, 1'b0);

integer i;
integer err;

initial begin
    $dumpfile("full_adder_16bits_tb.vcd");
    $dumpvars(0, full_adder_16bits_tb);
    $readmemh("Practice_02_ref/a_input.txt", mat_a_input);
    $readmemh("Practice_02_ref/b_input.txt", mat_b_input);
    $readmemh("Practice_02_ref/sum_output.txt", mat_sum_output);

    i = 0;
    err = 0;
    #(10);

    for (i = 0; i < 100; i = i + 1)
        begin
            a = mat_a_input[i];
            b = mat_b_input[i];
            mat_sum = mat_sum_output[i];
            #(1)
            if(sum != mat_sum)
                err = err + 1;
            #(10);
        end
    $finish;
end

endmodule

verilog/VLSI_experiment/2w/full_adder_16bits_tb.vcd
$date
	Fri Mar 17 20:31:25 2023
$end
$version
	Icarus Verilog
$end
$timescale
	1s
$end
$scope module full_adder_16bits_tb $end
$var wire 17 ! sum [16:0] $end
$var reg 16 " a [15:0] $end
$var reg 16 # b [15:0] $end
$var reg 17 $ mat_sum [16:0] $end
$var integer 32 % err [31:0] $end
$var integer 32 & i [31:0] $end
$scope module gate $end
$var wire 16 ' a [15:0] $end
$var wire 16 ( b [15:0] $end
$var wire 1 ) c_in $end
$var wire 17 * sum [16:0] $end
$var wire 15 + c [14:0] $end
$scope module fa0 $end
$var wire 1 , a $end
$var wire 1 - b $end
$var wire 1 . c1 $end
$var wire 1 ) c_in $end
$var wire 1 / c_out $end
$var wire 1 0 s1 $end
$var wire 1 1 s2 $end
$var wire 1 2 sum $end
$upscope $end
$scope module fa1 $end
$var wire 1 3 a $end
$var wire 1 4 b $end
$var wire 1 5 c1 $end
$var wire 1 6 c_in $end
$var wire 1 7 c_out $end
$var wire 1 8 s1 $end
$var wire 1 9 s2 $end
$var wire 1 : sum $end
$upscope $end
$scope module fa10 $end
$var wire 1 ; a $end
$var wire 1 < b $end
$var wire 1 = c1 $end
$var wire 1 > c_in $end
$var wire 1 ? c_out $end
$var wire 1 @ s1 $end
$var wire 1 A s2 $end
$var wire 1 B sum $end
$upscope $end
$scope module fa11 $end
$var wire 1 C a $end
$var wire 1 D b $end
$var wire 1 E c1 $end
$var wire 1 F c_in $end
$var wire 1 G c_out $end
$var wire 1 H s1 $end
$var wire 1 I s2 $end
$var wire 1 J sum $end
$upscope $end
$scope module fa12 $end
$var wire 1 K a $end
$var wire 1 L b $end
$var wire 1 M c1 $end
$var wire 1 N c_in $end
$var wire 1 O c_out $end
$var wire 1 P s1 $end
$var wire 1 Q s2 $end
$var wire 1 R sum $end
$upscope $end
$scope module fa13 $end
$var wire 1 S a $end
$var wire 1 T b $end
$var wire 1 U c1 $end
$var wire 1 V c_in $end
$var wire 1 W c_out $end
$var wire 1 X s1 $end
$var wire 1 Y s2 $end
$var wire 1 Z sum $end
$upscope $end
$scope module fa14 $end
$var wire 1 [ a $end
$var wire 1 \ b $end
$var wire 1 ] c1 $end
$var wire 1 ^ c_in $end
$var wire 1 _ c_out $end
$var wire 1 ` s1 $end
$var wire 1 a s2 $end
$var wire 1 b sum $end
$upscope $end
$scope module fa15 $end
$var wire 1 c a $end
$var wire 1 d b $end
$var wire 1 e c1 $end
$var wire 1 f c_in $end
$var wire 1 g c_out $end
$var wire 1 h s1 $end
$var wire 1 i s2 $end
$var wire 1 j sum $end
$upscope $end
$scope module fa2 $end
$var wire 1 k a $end
$var wire 1 l b $end
$var wire 1 m c1 $end
$var wire 1 n c_in $end
$var wire 1 o c_out $end
$var wire 1 p s1 $end
$var wire 1 q s2 $end
$var wire 1 r sum $end
$upscope $end
$scope module fa3 $end
$var wire 1 s a $end
$var wire 1 t b $end
$var wire 1 u c1 $end
$var wire 1 v c_in $end
$var wire 1 w c_out $end
$var wire 1 x s1 $end
$var wire 1 y s2 $end
$var wire 1 z sum $end
$upscope $end
$scope module fa4 $end
$var wire 1 { a $end
$var wire 1 | b $end
$var wire 1 } c1 $end
$var wire 1 ~ c_in $end
$var wire 1 !" c_out $end
$var wire 1 "" s1 $end
$var wire 1 #" s2 $end
$var wire 1 $" sum $end
$upscope $end
$scope module fa5 $end
$var wire 1 %" a $end
$var wire 1 &" b $end
$var wire 1 '" c1 $end
$var wire 1 (" c_in $end
$var wire 1 )" c_out $end
$var wire 1 *" s1 $end
$var wire 1 +" s2 $end
$var wire 1 ," sum $end
$upscope $end
$scope module fa6 $end
$var wire 1 -" a $end
$var wire 1 ." b $end
$var wire 1 /" c1 $end
$var wire 1 0" c_in $end
$var wire 1 1" c_out $end
$var wire 1 2" s1 $end
$var wire 1 3" s2 $end
$var wire 1 4" sum $end
$upscope $end
$scope module fa7 $end
$var wire 1 5" a $end
$var wire 1 6" b $end
$var wire 1 7" c1 $end
$var wire 1 8" c_in $end
$var wire 1 9" c_out $end
$var wire 1 :" s1 $end
$var wire 1 ;" s2 $end
$var wire 1 <" sum $end
$upscope $end
$scope module fa8 $end
$var wire 1 =" a $end
$var wire 1 >" b $end
$var wire 1 ?" c1 $end
$var wire 1 @" c_in $end
$var wire 1 A" c_out $end
$var wire 1 B" s1 $end
$var wire 1 C" s2 $end
$var wire 1 D" sum $end
$upscope $end
$scope module fa9 $end
$var wire 1 E" a $end
$var wire 1 F" b $end
$var wire 1 G" c1 $end
$var wire 1 H" c_in $end
$var wire 1 I" c_out $end
$var wire 1 J" s1 $end
$var wire 1 K" s2 $end
$var wire 1 L" sum $end
$upscope $end
$upscope $end
$upscope $end
$enddefinitions $end
#0
$dumpvars
xL"
xK"
xJ"
xI"
xH"
xG"
xF"
xE"
xD"
xC"
xB"
xA"
x@"
x?"
x>"
x="
x<"
x;"
x:"
x9"
x8"
x7"
x6"
x5"
x4"
x3"
x2"
x1"
x0"
x/"
x."
x-"
x,"
x+"
x*"
x)"
x("
x'"
x&"
x%"
x$"
x#"
x""
x!"
x~
x}
x|
x{
xz
xy
xx
xw
xv
xu
xt
xs
xr
xq
xp
xo
xn
xm
xl
xk
xj
xi
xh
xg
xf
xe
xd
xc
xb
xa
x`
x_
x^
x]
x\
x[
xZ
xY
xX
xW
xV
xU
xT
xS
xR
xQ
xP
xO
xN
xM
xL
xK
xJ
xI
xH
xG
xF
xE
xD
xC
xB
xA
x@
x?
x>
x=
x<
x;
x:
x9
x8
x7
x6
x5
x4
x3
x2
01
x0
x/
x.
x-
x,
bx +
bx *
0)
bx (
bx '
b0 &
b0 %
bx $
bx #
bx "
bx !
$end
#10
0g
1j
0i
0f
0_
1b
0a
0^
0W
1Z
0Y
0V
0O
0z
0,"
1L"
1R
0Q
0v
0("
1H"
0N
0o
0!"
1A"
0G
1r
0q
1$"
0#"
04"
0<"
0D"
1C"
0B
1J
0I
0:
0n
0~
00"
08"
1@"
0>
0F
06
07
0w
0)"
01"
19"
0I"
0?
b1111101000010101 !
b1111101000010101 *
12
b110000000 +
0/
09
0y
0+"
03"
0;"
0K"
0A
10
0.
08
05
1p
0m
0x
0u
1""
0}
0*"
0'"
02"
0/"
0:"
17"
1B"
0?"
0J"
0G"
0@
0=
1H
0E
1P
0M
1X
0U
1`
0]
1h
0e
0-
04
1l
0t
0|
0&"
0."
16"
1>"
0F"
0<
1D
0L
1T
0\
0d
1,
03
0k
0s
1{
0%"
0-"
15"
0="
0E"
0;
0C
1K
0S
1[
1c
b1111101000010101 $
b10100110000100 #
b10100110000100 (
b1101000010010001 "
b1101000010010001 '
#21
1N
1G
0J
1I
1F
1?
1;"
1L"
1A
1@"
1f
18"
1H"
1>
1:
0<"
19"
0b
1_
1j
1g
1,"
11"
1D"
0C"
1A"
b100111111000000 +
1I"
0B
b11011001100110111 !
b11011001100110111 *
1R
18
1:"
07"
0`
1]
0h
1e
1*"
1/"
0B"
1?"
1G"
1@
0P
14
1|
1."
06"
1F"
0T
1\
1d
0{
1%"
1-"
1="
1E"
1;
0K
1S
b11011001100110111 $
b1100101101010110 #
b1100101101010110 (
b1110011111100001 "
b1110011111100001 '
b1 &
#32
1R
1N
1G
0J
1I
1F
1?
0B
1A
0j
1@"
1n
08"
1H"
1>
0f
1r
1z
0$"
0<"
0;"
19"
0:
17
01"
0D"
1C"
1A"
0L"
1K"
1I"
1b
b111110000010 +
0_
b111000000101101 !
b111000000101101 *
0g
0p
1x
0""
0:"
17"
08
15
0/"
1B"
0?"
1J"
0G"
1`
0]
0e
1-
0l
1t
0|
1&"
0."
16"
1<
0d
0,
13
0%"
0-"
0="
0E"
0;
0[
0c
b111000000101101 $
b100111110101011 #
b100111110101011 (
b10000010000010 "
b10000010000010 '
b10 &
#43
1R
1N
1G
1("
0J
1I
1!"
1F
1#"
1?
1~
0B
1A
1w
1>
0z
1y
1I"
1v
19
1;"
0L"
1K"
1n
1o
1@"
16
18"
1H"
0:
17
0r
1q
1,"
0<"
19"
02
1/
0$"
11"
1D"
0C"
b111111011111 +
1A"
b10111000100100000 !
b10111000100100000 *
1g
18
05
1p
0*"
1:"
07"
00
1.
1""
1/"
0B"
1?"
1e
04
1l
0&"
1."
06"
0D
0\
1d
1,
1{
1-"
1="
1C
1[
1c
b10111000100100000 $
b1000011101001101 #
b1000011101001101 (
b1110100111010011 "
b1110100111010011 '
b11 &
#54
0R
0N
1v
1>
0G
1o
1I"
1J
0I
0,"
0r
1q
0~
0L"
1K"
0F
0("
14"
1n
0w
1H"
0?
1^
06
0!"
10"
0:
09
17
1z
0y
0D"
1C"
1A"
1B
0A
0Z
1W
1j
0g
12
0/
0$"
0#"
b10001111100110 +
1)"
b1100110001001001 !
b1100110001001001 *
1b
08
15
0x
1B"
0?"
0@
0X
1U
1h
0e
10
0.
0""
1'"
0`
14
0t
1&"
0>"
0<
1D
1T
0d
0,
0{
1%"
0C
0[
b1100110001001001 $
b10101001100111 #
b10101001100111 (
b1010000111100010 "
b1010000111100010 '
b100 &
#65
0B
0>
1@"
0I"
0z
19"
1L"
0K"
0v
0<"
1;"
1$"
1+"
0H"
1R
1Z
0b
0o
10"
18"
0n
1~
1("
0A"
1N
1V
0^
0r
0q
0,"
1)"
04"
13"
11"
1:
07
1w
1!"
1D"
0C"
b1011001100010011 !
b1011001100010011 *
0J
1G
1O
b1100011111000 +
0W
0p
1*"
0'"
12"
0/"
18
05
1u
1}
0B"
0H
1E
1M
0U
0l
1t
1|
0&"
0."
1L
0T
1d
03
1s
1{
0="
1C
1K
0S
0c
b1011001100010011 $
b1001101000011011 #
b1001101000011011 (
b1100011111000 "
b1100011111000 '
b101 &
#76
1J
1F
0D"
1?
1r
00"
0@"
1A
0R
0Z
0~
18"
1n
0("
0)"
09"
1H"
1>
0N
0V
1f
1z
0w
04"
03"
11"
1j
0:
17
1$"
0#"
0!"
0,"
0+"
1<"
0;"
1A"
1L"
1I"
b1000101010011101 !
b1000101010011101 *
0B
0G
0O
b100011101000010 +
1_
1x
0u
02"
1/"
0h
08
15
1""
0}
0*"
0:"
1?"
0J"
1G"
1@
0E
0M
1]
0-
0t
1."
1>"
0D
0L
1\
0d
1,
13
0{
0%"
05"
1="
1E"
1;
0C
0K
1[
b1000101010011101 $
b100001101010010 #
b100001101010010 (
b100011101001011 "
b100011101001011 '
b110 &
#87
1R
0r
0<"
1N
0j
1F
0n
08"
0H"
0>
1G
0f
1,"
0B
0A
1?
1Z
07
0z
14"
01"
1D"
0A"
1L"
0K"
0I"
0J
1I
b110000000000 +
0_
b10011001101110001 !
b10011001101110001 *
1g
1*"
0@
1=
1X
05
0x
12"
0/"
1B"
0?"
1J"
0G"
1H
0]
1e
1-
04
1&"
1<
1T
0\
1d
0,
03
0s
0-"
0="
0E"
1C
0[
1c
b10011001101110001 $
b1010011101110001 #
b1010011101110001 (
b1000110000000000 "
b1000110000000000 '
b111 &
#98
1<"
18"
11"
04"
13"
1j
10"
1f
1)"
0R
1_
0,"
1+"
0N
1a
0F
1("
0G
1V
1^
0L"
1B
0?
1:
1r
1z
0$"
1!"
0J
0I
1O
1Z
b111000001110000 +
1W
b11010010110001111 !
b11010010110001111 *
0b
0J"
1@
0=
18
1p
1x
0""
1}
0H
1M
0X
1U
1`
0-
0>"
0F"
0<
1L
1,
13
1k
1s
1{
1="
0C
1K
1S
1[
b11010010110001111 $
b1011000001110000 #
b1011000001110000 (
b1111010100011111 "
b1111010100011111 '
b1000 &
#109
1R
1v
1N
1o
1G
0r
1q
00"
08"
0@"
1L"
1I
1n
0)"
01"
09"
1H"
1F
0("
1>
0:
17
0,"
0+"
04"
03"
1<"
0;"
0D"
1A"
1B
1?
0J
02
b11011011010001000 !
b11011011010001000 *
1z
0!"
b111111100000110 +
1I"
08
15
0*"
02"
1:"
0B"
1?"
0@
1=
1H
00
0x
0}
1G"
14
1l
0|
0&"
0."
16"
1>"
1F"
1<
1D
0,
0k
0s
0{
1E"
b11011011010001000 $
b1011111110000110 #
b1011111110000110 (
b1111011100000010 "
b1111011100000010 '
b1001 &
#120
0v
0N
0o
0$"
0G
1r
0q
0~
1,"
0B
1J
0I
0Z
0n
0w
1("
18"
0H"
0>
0F
0V
1<"
12
1:
07
1z
0y
1!"
11"
1D"
0A"
1L"
0K"
0I"
0?
1R
0Q
b110000001010000 +
0O
b1001101110101111 !
b1001101110101111 *
0g
0:"
10
18
05
1x
1}
1/"
1B"
0?"
1J"
0G"
0=
1P
0M
0e
1|
1."
06"
0<
0D
1\
0d
1,
03
1s
1{
1-"
0="
0E"
0;
1C
0K
0[
0c
b1001101110101111 $
b111001101010110 #
b111001101010110 (
b10100001011001 "
b10100001011001 '
b1010 &
#131
1f
1_
0b
1a
14"
1Y
1^
10"
1V
1g
0:
0L"
1B
0Z
1W
1)"
0R
b111000001110000 +
1O
b10000110111101101 !
b10000110111101101 *
0j
1i
08
0J"
1@
1X
0U
1'"
0P
1M
1h
1-
04
1&"
0F"
1<
0T
0\
0,
1%"
1K
1[
1c
b10000110111101101 $
b1010101110101 #
b1010101110101 (
b1111100001111000 "
b1111100001111000 '
b1011 &
#142
0R
0N
0G
1J
0I
0F
0?
1B
0A
0>
0I"
0K"
1g
0H"
0j
1i
0A"
1f
1D"
0C"
1_
1#"
0@"
0b
1a
1,"
04"
1~
09"
1^
1("
00"
08"
02
1:
0z
1w
1<"
0;"
1L"
1Z
0Y
1W
b10010111110100110 !
b10010111110100110 *
0$"
1!"
0)"
b111000000011000 +
01"
00
18
0x
1u
1:"
1J"
0X
1U
1""
0}
0'"
0/"
0-
14
1t
0&"
0."
16"
0>"
1F"
0<
1D
1T
0{
0%"
0-"
1="
1;
0C
b10010111110100110 $
b11101010011110 #
b11101010011110 (
b1111010100001000 "
b1111010100001000 '
b1100 &
#153
1H"
1A"
0,"
0D"
1C"
0("
1@"
1g
0!"
19"
1Z
0j
1i
1$"
0#"
0<"
1;"
1Q
1V
1f
0~
18"
1N
0:
0r
1L"
0R
1O
1b
0a
1_
12
0w
11"
b10110011000010001 !
b10110011000010001 *
0J
b111100111000000 +
1G
08
0p
0J"
1P
0M
0`
1]
10
0u
1/"
0H
1E
04
0l
0t
1."
1>"
0F"
0L
1\
1d
1,
0s
1-"
0="
1C
0c
b10110011000010001 $
b1110100111010000 #
b1110100111010000 (
b111110001000001 "
b111110001000001 '
b1101 &
#164
1,"
1("
1!"
0$"
1#"
0H"
1~
0A"
1w
1D"
0C"
1y
0@"
1v
09"
0g
1o
1<"
0;"
0>
1I
1j
0i
1q
0V
08"
0I"
1F
1N
0f
1n
0O
0^
14"
01"
1L"
0K"
0B
1?
0J
1G
1b
0a
0_
17
0r
0z
1R
0Q
b1111001111100001 !
b1111001111100001 *
1Z
0Y
b110000011110 +
0W
12"
0/"
1J"
0@
1=
1H
0E
1`
0]
15
1p
1x
0P
1X
0U
14
0|
0."
06"
1F"
1<
0D
0\
0d
13
1k
1s
1{
15"
0K
0S
1c
b1111001111100001 $
b10011100000010 #
b10011100000010 (
b1100110011011111 "
b1100110011011111 '
b1110 &
#175
0g
1j
0i
0f
0("
0_
0!"
1b
0a
1$"
0#"
0^
0~
0W
0w
1Z
0Y
1z
0y
00"
0V
0v
0N
0n
0)"
18"
0F
0O
0o
0G
1:
07
1,"
0+"
04"
11"
1B
b1000000 +
0?
1R
0Q
02
0r
0q
1<"
b1111011110111010 !
b1111011110111010 *
0J
0I
18
05
1*"
02"
1/"
1@
0=
1P
00
0p
0:"
0H
04
1t
1&"
1."
0<
1L
0T
1\
1d
0,
0k
0s
05"
0C
1S
0[
0c
b1111011110111010 $
b1101001101101000 #
b1101001101101000 (
b10010001010010 "
b10010001010010 '
b1111 &
#186
14"
10"
1>
1)"
1I"
0,"
1+"
0L"
1K"
1("
1@"
1H"
1N
0$"
1!"
1R
0:
19"
1D"
1A"
b1111010111001000 !
b1111010111001000 *
1B
b101111110000 +
1G
0""
1}
0P
08
17"
0B"
1?"
0@
1E
0t
1|
0&"
16"
0F"
1D
0L
0\
03
1s
1%"
15"
1="
1E"
0;
1C
1[
b1111010111001000 $
b1000100111010000 #
b1000100111010000 (
b110101111111000 "
b110101111111000 '
b10000 &
#197
00"
1J
0)"
0<"
1F
1V
1,"
0+"
08"
1>
1?
1O
1^
1f
0("
0@"
0H"
1:
14"
03"
01"
0L"
0K"
1I"
0B
1A
0R
1Q
1Z
1W
1b
1_
12
1r
0!"
09"
1D"
0C"
b111111000000000 +
0A"
1j
b11110100101101111 !
b11110100101101111 *
1g
18
12"
0/"
0J"
1G"
1@
1P
0X
1U
0`
1]
10
1p
0}
07"
1B"
0?"
0h
1e
14
0|
0."
06"
1F"
1<
1L
1T
1\
1,
1k
0{
05"
0="
1c
b11110100101101111 $
b1111111100000010 #
b1111111100000010 (
b1110101001101101 "
b1110101001101101 '
b10001 &
#208
1$"
1~
1w
0Z
0z
1y
0F
0V
1v
0?
0O
1o
1B
0A
1R
0Q
0r
1q
0>
0N
0f
1n
0^
0D"
1L"
0I"
1J
0I
0G
1b
0a
0_
1j
0i
0g
0:
17
0,"
b1101111011010001 !
b1101111011010001 *
1<"
b1110 +
0W
0B"
1J"
0G"
1H
0E
1`
0]
1h
0e
08
15
0*"
1:"
0U
1-
0>"
0F"
0D
0T
0\
0d
0,
13
0%"
15"
0S
b1101111011010001 $
b1010000000011 #
b1010000000011 (
b1100101011001110 "
b1100101011001110 '
b10010 &
#219
0D"
0@"
09"
1<"
0;"
08"
01"
14"
03"
00"
0)"
0+"
1g
0("
0j
1i
19
0v
0~
1Z
0!"
1f
16
1n
0o
0w
1H"
1V
1^
1$"
0#"
1b
1_
02
1/
0:
17
1r
0q
0z
0y
1,"
1A"
1L"
0J
b10110011011110100 !
b10110011011110100 *
0R
1O
b111000100000011 +
1W
1""
0`
1]
00
1.
18
05
0p
0x
1*"
1?"
0J"
0H
0P
1M
1U
1|
1."
1>"
0<
1T
1\
1,
03
0k
0s
1%"
0-"
1="
0E"
1;
0C
1K
1S
b10110011011110100 $
b111000101010011 #
b111000101010011 (
b1111010110100001 "
b1111010110100001 '
b10011 &
#230
1Q
1N
1G
0r
1D"
1I
0n
1("
1@"
1F
07
1!"
19"
1?
0g
1b
1:
09
1z
0$"
1#"
0<"
1;"
0B
1A
1j
0i
1^
06
1v
1~
18"
1>
1V
0f
0J
0Z
1Y
1W
12
0/
1o
1w
1,"
04"
11"
1I"
b1100001100101011 !
b1100001100101011 *
0R
1O
b11111111011100 +
0_
1H
1X
0U
10
0.
1m
1u
0*"
02"
1/"
1G"
1P
0M
0]
04
1l
1t
0|
1F"
1D
0T
0\
0,
13
1k
1s
1{
0%"
1-"
1E"
0K
0[
b1100001100101011 $
b1101101001101 #
b1101101001101 (
b1010011111011110 "
b1010011111011110 '
b10100 &
#241
0^
0W
1Z
0Y
0V
0O
1R
0Q
0N
0G
1,"
1J
0I
0g
1("
0F
1j
0i
1!"
0?
0f
0$"
1#"
14"
0@"
1B
0A
0H"
0_
1~
10"
08"
09"
0>
02
1D"
0C"
0A"
1b
0a
0z
1y
1w
1)"
01"
0<"
0;"
b1111111101100010 !
b1111111101100010 *
1L"
0K"
b111100 +
0I"
00
1B"
0?"
1`
1x
0u
1'"
0/"
0:"
1J"
0G"
0-
14
1|
1&"
0."
0>"
1<
0D
1T
1\
1d
03
0s
0{
1%"
0-"
05"
0E"
0;
1C
0S
0c
b1111111101100010 $
b1111011000111110 #
b1111011000111110 (
b100100100100 "
b100100100100 '
b10101 &
#252
0~
0,"
0w
1<"
0("
1z
0y
18"
0!"
1H"
0v
11"
12
0$"
0#"
0D"
1A"
1L"
0B
0Z
1r
b101100000 +
0o
b1101101010001111 !
b1101101010001111 *
04"
13"
10
0""
0B"
1?"
0J"
0@
0X
1p
0m
12"
1-
0|
1>"
0F"
0<
0L
0T
0\
0d
0k
1-"
1K
1[
1c
b1101101010001111 $
b100101111 #
b100101111 (
b1101100101100000 "
b1101100101100000 '
b10110 &
#263
0<"
08"
1N
01"
1G
0L"
14"
03"
1B
0J
1I
0H"
1f
00"
1>
1F
02
0r
1D"
0A"
0b
1_
1j
1g
1$"
1,"
0)"
1I"
b100111000000000 +
1?
1R
b11011010101111010 !
b11011010101111010 *
1Z
00
0p
1B"
0?"
0`
1]
0h
1e
1""
1*"
0'"
1G"
1=
0P
1X
0-
04
0l
0t
1."
0>"
1F"
1<
1\
1d
13
1s
1{
0%"
0-"
1E"
1;
0K
1S
b11011010101111010 $
b1100011001100000 #
b1100011001100000 (
b1110111100011010 "
b1110111100011010 '
b10111 &
#274
0a
0^
0N
0W
0G
1Z
0Y
1L"
1J
0I
0V
0j
1H"
0F
0O
0>
0f
0D"
1A"
1B
0A
0?
1R
0Q
12
1<"
0I"
b10111111011111011 !
b10111111011111011 *
1b
b100000000 +
0_
0B"
1?"
1@
0=
1P
10
1:"
0G"
1`
0]
14
1t
1|
0."
1>"
0F"
0<
1L
1,
03
0s
0{
1-"
15"
0E"
0[
b10111111011111011 $
b1101000100111010 #
b1101000100111010 (
b1010110111000001 "
b1010110111000001 '
b11000 &
#285
1V
1O
0R
1Q
1N
1G
0J
1I
1C"
1F
1@"
1?
19"
0B
1A
0<"
1;"
1>
1r
1j
18"
1H"
1I"
1n
10"
1f
14"
11"
0D"
1A"
0L"
1K"
0:
17
0,"
1)"
1Z
b11010000001011101 !
b11010000001011101 *
0b
b101111111100010 +
1_
02"
1/"
1B"
0?"
1J"
08
15
0*"
1'"
0X
0`
1]
0t
0|
1."
0>"
1F"
1<
1D
13
1s
1{
1%"
0;
0C
0S
1[
b11010000001011101 $
b1101111001100010 #
b1101111001100010 (
b1100000111111011 "
b1100000111111011 '
b11001 &
#296
0>
0I"
1L"
0K"
0H"
0A"
1D"
0C"
0@"
1N
09"
1G
1b
1:
1+"
14"
0r
1<"
0;"
0J
1I
1^
16
1~
1("
10"
0n
1v
08"
1F
1V
1W
0f
02
1/
1z
1w
1$"
1!"
0,"
1)"
1j
0i
0g
07
1o
01"
0B
0A
1?
1R
0Q
1O
b1101001111011010 !
b1101001111011010 *
0Z
1Y
b11110000111101 +
0_
00
1.
0x
1u
0""
1}
1*"
0'"
1h
0e
05
1m
0/"
0@
1=
0P
1M
1X
0]
1-
04
1l
1t
1|
0&"
0."
16"
1>"
0F"
0D
0\
0d
03
1k
0-"
05"
0="
1E"
1;
1C
1K
1S
0[
b1101001111011010 $
b1010110011101 #
b1010110011101 (
b1011111000111101 "
b1011111000111101 '
b11010 &
#307
14"
10"
1)"
0R
1b
0:
0z
0,"
1+"
0N
1^
06
0v
1("
18"
0G
0V
1f
1<"
0D"
0Z
0Y
1W
0/
0o
0$"
1#"
1!"
11"
1J
0I
0O
b110010001111000 +
1_
b1100101011000000 !
b1100101011000000 *
1j
0:"
0B"
0X
1U
0.
0m
1""
0}
1/"
0H
0M
1]
0h
0-
0l
1."
06"
0>"
1F"
0L
1T
1\
0,
0k
0{
1-"
0E"
0C
0K
1[
0c
b1100101011000000 $
b110011001011000 #
b110011001011000 (
b110010001101000 "
b110010001101000 '
b11011 &
#318
1H"
1A"
0("
0<"
1J
1y
00"
1C"
1A
1~
0!"
08"
1F
0^
1v
0)"
1@"
1>
0f
0g
1:
0z
1w
1$"
0#"
14"
03"
01"
0B
1?
1Z
0W
12
1o
0,"
0+"
19"
0D"
1L"
1I"
1b
0a
b11110001100 +
0_
b1110101001010011 !
b1110101001010011 *
1j
0i
18
1x
0u
0""
12"
0/"
1@
0=
1X
0U
10
1m
0*"
17"
1B"
0J"
1G"
1`
0]
1h
14
1l
0t
0|
0."
16"
0<
0T
1,
1k
0%"
15"
1="
1E"
0[
1c
b1110101001010011 $
b100001010000110 #
b100001010000110 (
b1010011111001101 "
b1010011111001101 '
b11100 &
#329
1J
1F
1?
0$"
1<"
0B
1A
0~
1,"
1R
18"
1>
0v
0w
1("
1N
04"
11"
0L"
1K"
1I"
0o
b1111100010100011 !
b1111100010100011 *
0z
0y
1!"
b111111010000 +
1G
02"
1/"
1J"
0G"
0m
0x
1}
1E
1-
04
0l
1|
1."
0F"
1<
1D
1d
0,
13
0k
0s
1{
0;
1C
0c
b1111100010100011 $
b1100110011010001 #
b1100110011010001 (
b10101111010010 "
b10101111010010 '
b11101 &
#340
1$"
1~
1w
1y
1v
1g
1o
0j
1i
1q
0>
1f
1n
0I"
1_
17
1L"
0K"
0b
1a
0:
19
13"
0H"
1V
1@"
1^
16
10"
18"
0A"
1F
1N
1O
0<"
1;"
19"
1Z
1W
02
1/
0r
0z
1)"
04"
11"
1D"
0C"
0B
0A
1?
0J
1I
b111110011111111 +
1G
b10010001100110000 !
b10010001100110000 *
0R
1Q
1:"
07"
0X
1U
00
1.
1p
1x
1'"
12"
0/"
0B"
0@
1=
1H
0E
1P
1&"
06"
1F"
1T
0d
1,
1k
1s
1%"
0-"
0="
0E"
1;
0C
1K
1c
b10010001100110000 $
b110111001110001 #
b110111001110001 (
b1011010010111111 "
b1011010010111111 '
b11110 &
#351
0v
0o
0g
1r
0q
1j
0i
0n
0f
07
0$"
0_
08"
0H"
1:
09
0~
0,"
0@"
0V
1b
0a
01"
0A"
06
0w
0("
09"
0F
1N
0O
0^
14"
03"
1D"
0C"
0L"
0/
0z
0y
0!"
0<"
0;"
0?
0J
0I
1G
1R
0Q
b1111000101000110 !
b1111000101000110 *
1Z
0Y
b100000100000 +
0W
02"
1B"
0J"
0.
0x
0}
0:"
0=
0H
1E
0P
1X
0U
0-
0|
0."
1>"
0F"
0<
1d
0,
0s
0{
05"
0;
1C
0K
0S
0c
b1111000101000110 $
b1110100100100000 #
b1110100100100000 (
b100000100110 "
b100000100110 '
b11111 &
#362
1$"
1~
1w
0<"
1y
08"
1B
1I
1R
1v
00"
01"
1@"
1>
1F
1N
12
0r
1o
0z
1,"
0)"
1D"
0j
0:
14"
03"
19"
1I"
1?
b111010101110001 !
b111010101110001 *
0J
b111010001100 +
1G
10
0p
1m
1x
1*"
0'"
0B"
0h
08
12"
17"
1G"
1=
1H
0E
1-
1l
1t
0&"
16"
0>"
1F"
1<
0\
0d
03
1-"
15"
1E"
1;
0C
1[
b111010101110001 $
b10111010001101 #
b10111010001101 (
b100011011100100 "
b100011011100100 '
b100000 &
#373
0R
0~
0N
0w
0G
1z
0y
0("
1L"
1J
0I
0v
0!"
1H"
0F
0Z
0o
1$"
0#"
b100111101011001 !
b100111101011001 *
0,"
1A"
b1110000000 +
0?
0X
0m
1""
0*"
1?"
0=
0-
0l
1>"
0<
0D
0T
1\
1,
0k
1{
0%"
1="
0;
1C
0[
b100111101011001 $
b100001110001000 #
b100001110001000 (
b101111010001 "
b101111010001 '
b100001 &
