verilog/digitalsystem4/Mux.v
module Mux (In,Sel,Out);

input [1:0] In;
output reg Out;
input Sel;

always @(In,Sel)
begin
    case (Sel)
        2'b00: Out = In[0];
        2'b01: Out = In[1];
    endcase
end
endmodule

verilog/digital_system_experiment/digitalsystem4/full_adder.v
module full_adder(A,B,cin,sum,cout);

input A,B;
input cin;
output sum,cout;

wire t1,t2,t3;

xor(t1,A,B);
and(t2,A,B);
xor(sum,t1,cin);
and(t3,t1,cin);
or(cout,t3,t2);

endmodule

verilog/digital_system_experiment/digitalsystem4/4bit_add_sub.v
`include "full_adder.v"

module add_sub_4bit (A,B,cin,cout,sum);

input [3:0]A,B;
input cin;
output [3:0]sum;
output cout;
wire [3:0]a;  // xor과 full adder 연결
wire [2:0]c;  // full adder 내부 연결

xor(a[0],A[0],cin);
xor(a[1],A[1],cin);
xor(a[2],A[2],cin);
xor(a[3],A[3],cin);

full_adder fa0 (B[0],a[0], cin,sum[0],c[0]);
full_adder fa1 (B[1],a[1],c[0],sum[1],c[1]);
full_adder fa2 (B[2],a[2],c[1],sum[2],c[2]);
full_adder fa3 (B[3],a[3],c[2],sum[3],cout);

endmodule

verilog/digital_system_experiment/digitalsystem4/4bit_div.v
`include "Mux.v"
`include "4bit_add_sub.v"

module div_4bit(A,B,Q,R,cin);

input cin;
input [3:0]A,B;
output [3:0]Q,R;
wire [3:0]q;
wire [3:0]sub0,sub1,sub2,sub3;
wire [2:0]m0,m1,m2;

assign Q[3:0] = ~q[3:0];

//add_sub_4bit (A,B,cin,cout,sum);
//Mux (In,Sel,Out)
add_sub_4bit as4_0 ({3'b000,A[3]}, B, cin, q[3], sub0 );
Mux mux00 ({sub0[2],1'b0},q[3],m0[2]);
Mux mux01 ({sub0[1],1'b0},q[3],m0[1]);
Mux mux02 ({sub0[0],1'b0},q[3],m0[0]);

add_sub_4bit as4_1 ({m0[2],m0[1],m0[0],A[2]},B, cin, q[2], sub1 );
Mux mux10 ({sub1[2],m0[1]},q[2],m1[2]);
Mux mux11 ({sub1[1],m0[0]},q[2],m1[1]);
Mux mux12 ({sub1[0], A[2]},q[2],m1[0]);

add_sub_4bit as4_2 ({m1[2],m1[1],m1[0],A[1]},B, cin, q[1], sub2 );
Mux mux20 ({sub2[2],m1[1]},q[1],m2[2]);
Mux mux21 ({sub2[1],m1[0]},q[1],m2[1]);
Mux mux22 ({sub2[0], A[1]},q[1],m2[0]);

add_sub_4bit as4_3 ({m2[2],m2[1],m2[0],A[0]},B, cin, q[0], sub3 );
Mux mux30 ({sub3[3],m2[2]},q[0],R[3]);
Mux mux31 ({sub3[2],m2[1]},q[0],R[2]);
Mux mux32 ({sub3[1],m2[0]},q[0],R[1]);
Mux mux33 ({sub3[0], A[0]},q[0],R[0]);


endmodule

verilog/digitalsystem4/4bit_div_tb.v
`include "4bit_div.v"
`timescale 100ps/1ps

module div_4bit_tb;

reg [3:0] A,B;
reg cin;
wire [3:0] Q,R;
integer i,j;

div_4bit div0(A,B,Q,R,cin);

initial begin
    $dumpfile("4bit_div_tb.vcd");
    $dumpvars(0,div_4bit_tb); // 여기에는 모듈 이름 써야됨. 파일 제목 x
    cin <= 1'b1;
    for(i=4'b0000; i<= 4'b1111; i++) begin
        B <= i;
        for(j=4'b0000; j<= 4'b1111; j++) begin
            A <= j; #10;
        end
    end
    $finish;
end

endmodule

verilog/digital_system_experiment/digitalsystem4/4bit_div_tb.vcd
$date
	Tue Oct  1 02:17:31 2019
$end
$version
	Icarus Verilog
$end
$timescale
	1ps
$end
$scope module div_4bit_tb $end
$var wire 4 ! R [3:0] $end
$var wire 4 " Q [3:0] $end
$var reg 4 # A [3:0] $end
$var reg 4 $ B [3:0] $end
$var reg 1 % cin $end
$var integer 32 & i [31:0] $end
$var integer 32 ' j [31:0] $end
$scope module div0 $end
$var wire 4 ( A [3:0] $end
$var wire 4 ) B [3:0] $end
$var wire 4 * Q [3:0] $end
$var wire 1 % cin $end
$var wire 4 + sub3 [3:0] $end
$var wire 4 , sub2 [3:0] $end
$var wire 4 - sub1 [3:0] $end
$var wire 4 . sub0 [3:0] $end
$var wire 4 / q [3:0] $end
$var wire 3 0 m2 [2:0] $end
$var wire 3 1 m1 [2:0] $end
$var wire 3 2 m0 [2:0] $end
$var wire 4 3 R [3:0] $end
$scope module as4_0 $end
$var wire 4 4 A [3:0] $end
$var wire 4 5 B [3:0] $end
$var wire 1 % cin $end
$var wire 4 6 sum [3:0] $end
$var wire 1 7 cout $end
$var wire 3 8 c [2:0] $end
$var wire 4 9 a [3:0] $end
$scope module fa0 $end
$var wire 1 : A $end
$var wire 1 ; B $end
$var wire 1 % cin $end
$var wire 1 < cout $end
$var wire 1 = sum $end
$var wire 1 > t1 $end
$var wire 1 ? t2 $end
$var wire 1 @ t3 $end
$upscope $end
$scope module fa1 $end
$var wire 1 A A $end
$var wire 1 B B $end
$var wire 1 C cin $end
$var wire 1 D cout $end
$var wire 1 E sum $end
$var wire 1 F t1 $end
$var wire 1 G t2 $end
$var wire 1 H t3 $end
$upscope $end
$scope module fa2 $end
$var wire 1 I A $end
$var wire 1 J B $end
$var wire 1 K cin $end
$var wire 1 L cout $end
$var wire 1 M sum $end
$var wire 1 N t1 $end
$var wire 1 O t2 $end
$var wire 1 P t3 $end
$upscope $end
$scope module fa3 $end
$var wire 1 Q A $end
$var wire 1 R B $end
$var wire 1 S cin $end
$var wire 1 7 cout $end
$var wire 1 T sum $end
$var wire 1 U t1 $end
$var wire 1 V t2 $end
$var wire 1 W t3 $end
$upscope $end
$upscope $end
$scope module as4_1 $end
$var wire 4 X A [3:0] $end
$var wire 4 Y B [3:0] $end
$var wire 1 % cin $end
$var wire 4 Z sum [3:0] $end
$var wire 1 [ cout $end
$var wire 3 \ c [2:0] $end
$var wire 4 ] a [3:0] $end
$scope module fa0 $end
$var wire 1 ^ A $end
$var wire 1 _ B $end
$var wire 1 % cin $end
$var wire 1 ` cout $end
$var wire 1 a sum $end
$var wire 1 b t1 $end
$var wire 1 c t2 $end
$var wire 1 d t3 $end
$upscope $end
$scope module fa1 $end
$var wire 1 e A $end
$var wire 1 f B $end
$var wire 1 g cin $end
$var wire 1 h cout $end
$var wire 1 i sum $end
$var wire 1 j t1 $end
$var wire 1 k t2 $end
$var wire 1 l t3 $end
$upscope $end
$scope module fa2 $end
$var wire 1 m A $end
$var wire 1 n B $end
$var wire 1 o cin $end
$var wire 1 p cout $end
$var wire 1 q sum $end
$var wire 1 r t1 $end
$var wire 1 s t2 $end
$var wire 1 t t3 $end
$upscope $end
$scope module fa3 $end
$var wire 1 u A $end
$var wire 1 v B $end
$var wire 1 w cin $end
$var wire 1 [ cout $end
$var wire 1 x sum $end
$var wire 1 y t1 $end
$var wire 1 z t2 $end
$var wire 1 { t3 $end
$upscope $end
$upscope $end
$scope module as4_2 $end
$var wire 4 | A [3:0] $end
$var wire 4 } B [3:0] $end
$var wire 1 % cin $end
$var wire 4 ~ sum [3:0] $end
$var wire 1 !" cout $end
$var wire 3 "" c [2:0] $end
$var wire 4 #" a [3:0] $end
$scope module fa0 $end
$var wire 1 $" A $end
$var wire 1 %" B $end
$var wire 1 % cin $end
$var wire 1 &" cout $end
$var wire 1 '" sum $end
$var wire 1 (" t1 $end
$var wire 1 )" t2 $end
$var wire 1 *" t3 $end
$upscope $end
$scope module fa1 $end
$var wire 1 +" A $end
$var wire 1 ," B $end
$var wire 1 -" cin $end
$var wire 1 ." cout $end
$var wire 1 /" sum $end
$var wire 1 0" t1 $end
$var wire 1 1" t2 $end
$var wire 1 2" t3 $end
$upscope $end
$scope module fa2 $end
$var wire 1 3" A $end
$var wire 1 4" B $end
$var wire 1 5" cin $end
$var wire 1 6" cout $end
$var wire 1 7" sum $end
$var wire 1 8" t1 $end
$var wire 1 9" t2 $end
$var wire 1 :" t3 $end
$upscope $end
$scope module fa3 $end
$var wire 1 ;" A $end
$var wire 1 <" B $end
$var wire 1 =" cin $end
$var wire 1 !" cout $end
$var wire 1 >" sum $end
$var wire 1 ?" t1 $end
$var wire 1 @" t2 $end
$var wire 1 A" t3 $end
$upscope $end
$upscope $end
$scope module as4_3 $end
$var wire 4 B" A [3:0] $end
$var wire 4 C" B [3:0] $end
$var wire 1 % cin $end
$var wire 4 D" sum [3:0] $end
$var wire 1 E" cout $end
$var wire 3 F" c [2:0] $end
$var wire 4 G" a [3:0] $end
$scope module fa0 $end
$var wire 1 H" A $end
$var wire 1 I" B $end
$var wire 1 % cin $end
$var wire 1 J" cout $end
$var wire 1 K" sum $end
$var wire 1 L" t1 $end
$var wire 1 M" t2 $end
$var wire 1 N" t3 $end
$upscope $end
$scope module fa1 $end
$var wire 1 O" A $end
$var wire 1 P" B $end
$var wire 1 Q" cin $end
$var wire 1 R" cout $end
$var wire 1 S" sum $end
$var wire 1 T" t1 $end
$var wire 1 U" t2 $end
$var wire 1 V" t3 $end
$upscope $end
$scope module fa2 $end
$var wire 1 W" A $end
$var wire 1 X" B $end
$var wire 1 Y" cin $end
$var wire 1 Z" cout $end
$var wire 1 [" sum $end
$var wire 1 \" t1 $end
$var wire 1 ]" t2 $end
$var wire 1 ^" t3 $end
$upscope $end
$scope module fa3 $end
$var wire 1 _" A $end
$var wire 1 `" B $end
$var wire 1 a" cin $end
$var wire 1 E" cout $end
$var wire 1 b" sum $end
$var wire 1 c" t1 $end
$var wire 1 d" t2 $end
$var wire 1 e" t3 $end
$upscope $end
$upscope $end
$scope module mux00 $end
$var wire 2 f" In [1:0] $end
$var wire 1 g" Sel $end
$var reg 1 h" Out $end
$upscope $end
$scope module mux01 $end
$var wire 2 i" In [1:0] $end
$var wire 1 j" Sel $end
$var reg 1 k" Out $end
$upscope $end
$scope module mux02 $end
$var wire 2 l" In [1:0] $end
$var wire 1 m" Sel $end
$var reg 1 n" Out $end
$upscope $end
$scope module mux10 $end
$var wire 2 o" In [1:0] $end
$var wire 1 p" Sel $end
$var reg 1 q" Out $end
$upscope $end
$scope module mux11 $end
$var wire 2 r" In [1:0] $end
$var wire 1 s" Sel $end
$var reg 1 t" Out $end
$upscope $end
$scope module mux12 $end
$var wire 2 u" In [1:0] $end
$var wire 1 v" Sel $end
$var reg 1 w" Out $end
$upscope $end
$scope module mux20 $end
$var wire 2 x" In [1:0] $end
$var wire 1 y" Sel $end
$var reg 1 z" Out $end
$upscope $end
$scope module mux21 $end
$var wire 2 {" In [1:0] $end
$var wire 1 |" Sel $end
$var reg 1 }" Out $end
$upscope $end
$scope module mux22 $end
$var wire 2 ~" In [1:0] $end
$var wire 1 !# Sel $end
$var reg 1 "# Out $end
$upscope $end
$scope module mux30 $end
$var wire 2 ## In [1:0] $end
$var wire 1 $# Sel $end
$var reg 1 %# Out $end
$upscope $end
$scope module mux31 $end
$var wire 2 &# In [1:0] $end
$var wire 1 '# Sel $end
$var reg 1 (# Out $end
$upscope $end
$scope module mux32 $end
$var wire 2 )# In [1:0] $end
$var wire 1 *# Sel $end
$var reg 1 +# Out $end
$upscope $end
$scope module mux33 $end
$var wire 2 ,# In [1:0] $end
$var wire 1 -# Sel $end
$var reg 1 .# Out $end
$upscope $end
$upscope $end
$upscope $end
$enddefinitions $end
#0
$dumpvars
0.#
1-#
b0 ,#
0+#
1*#
b0 )#
0(#
1'#
b0 &#
0%#
1$#
b0 ##
0"#
1!#
b0 ~"
0}"
1|"
b0 {"
0z"
1y"
b0 x"
0w"
1v"
b0 u"
0t"
1s"
b0 r"
0q"
1p"
b0 o"
0n"
1m"
b0 l"
0k"
1j"
b0 i"
0h"
1g"
b0 f"
1e"
0d"
1c"
0b"
1a"
1`"
0_"
1^"
0]"
1\"
0["
1Z"
1Y"
1X"
0W"
1V"
0U"
1T"
0S"
1R"
1Q"
1P"
0O"
1N"
0M"
1L"
0K"
1J"
1I"
0H"
b1111 G"
b111 F"
1E"
b0 D"
b0 C"
b0 B"
1A"
0@"
1?"
0>"
1="
1<"
0;"
1:"
09"
18"
07"
16"
15"
14"
03"
12"
01"
10"
0/"
1."
1-"
1,"
0+"
1*"
0)"
1("
0'"
1&"
1%"
0$"
b1111 #"
b111 ""
1!"
b0 ~
b0 }
b0 |
1{
0z
1y
0x
1w
1v
0u
1t
0s
1r
0q
1p
1o
1n
0m
1l
0k
1j
0i
1h
1g
1f
0e
1d
0c
1b
0a
1`
1_
0^
b1111 ]
b111 \
1[
b0 Z
b0 Y
b0 X
1W
0V
1U
0T
1S
1R
0Q
1P
0O
1N
0M
1L
1K
1J
0I
1H
0G
1F
0E
1D
1C
1B
0A
1@
0?
1>
0=
1<
1;
0:
b1111 9
b111 8
17
b0 6
b0 5
b0 4
b0 3
b0 2
b0 1
b0 0
b1111 /
b0 .
b0 -
b0 ,
b0 +
b0 *
b0 )
b0 (
b0 '
b0 &
1%
b0 $
b0 #
b0 "
b0 !
$end
#1000
0$#
0'#
0*#
0-#
b1 "
b1 *
b10 ##
b1110 /
0E"
1b"
0e"
0(#
0a"
b10 &#
0Z"
1["
0^"
0+#
0Y"
b10 )#
0R"
1S"
0V"
b1 !
b1 3
1.#
0Q"
b0 F"
0J"
b1111 +
b1111 D"
1K"
0N"
0L"
0I"
b1110 G"
b1 B"
b11 ,#
b1 #
b1 (
b1 '
#2000
1c"
1`"
0!#
0|"
0y"
0$#
0'#
0*#
0-#
b11 "
b11 *
1\"
0%#
0!"
b1100 /
0E"
1X"
b10 ##
1>"
0A"
1b"
0e"
0z"
0="
0a"
0T"
0(#
b10 x"
06"
0Z"
0P"
b10 &#
17"
0:"
1["
0^"
0}"
05"
0Y"
1+#
b10 {"
0."
0R"
b11 )#
1/"
02"
1S"
0V"
b1 0
1"#
0-"
1Q"
b0 ""
0&"
b1 F"
1J"
b1111 ,
b1111 ~
1'"
0*"
b1110 +
b1110 D"
0K"
1N"
0("
1L"
0%"
1I"
b1110 #"
b1101 G"
b10 !
b10 3
0.#
b1 |
b11 ~"
b10 B"
b0 ,#
b10 #
b10 (
b10 '
#3000
b1 )#
0S"
0Q"
b0 F"
0J"
b1101 +
b1101 D"
1K"
0N"
0L"
0I"
b1100 G"
b11 !
b11 3
1.#
b11 B"
b11 ,#
b11 #
b11 (
b11 '
#4000
1?"
1c"
1<"
1`"
0v"
0s"
0p"
0!#
0|"
0y"
18"
0[
0!"
0$#
0'#
0*#
0-#
b111 "
b111 *
0\"
14"
0%#
1x
0{
1>"
0A"
b1000 /
0E"
0X"
b10 ##
0q"
0w
0="
1b"
0e"
00"
0z"
b10 o"
0p
06"
0a"
0,"
1(#
b10 x"
1q
0t
17"
0:"
0Z"
b11 &#
0t"
0o
05"
1["
0^"
1}"
b10 r"
0h
0."
1Y"
b11 {"
1i
0l
1/"
02"
1R"
b1 1
1w"
0g
1-"
1V"
1Q"
b0 \
0`
b1 ""
1&"
1T"
b11 F"
1J"
b1111 -
b1111 Z
1a
0d
b1110 ,
b1110 ~
0'"
1*"
1P"
b1100 +
b1100 D"
0K"
1N"
0b
1("
1L"
0_
1%"
0+#
1I"
b1110 ]
b1101 #"
b0 )#
b1011 G"
b10 0
0"#
b100 !
b100 3
0.#
b1 X
b11 u"
b10 |
b0 ~"
b100 B"
b0 ,#
b100 #
b100 (
b100 '
#5000
b1 &#
0["
0Y"
b10 )#
0R"
1S"
0V"
0Q"
b0 F"
0J"
b1011 +
b1011 D"
1K"
0N"
0L"
0I"
b1010 G"
b101 !
b101 3
1.#
b101 B"
b11 ,#
b101 #
b101 (
b101 '
#6000
b1 {"
0/"
0-"
1Q"
b0 ""
0&"
0T"
b1 F"
1J"
b1101 ,
b1101 ~
1'"
0*"
0P"
b1010 +
b1010 D"
0K"
1N"
0("
1L"
0%"
1+#
1I"
b1100 #"
b11 )#
b1001 G"
b11 0
1"#
b110 !
b110 3
0.#
b11 |
b11 ~"
b110 B"
b0 ,#
b110 #
b110 (
b110 '
#7000
b1 )#
0S"
0Q"
b0 F"
0J"
b1001 +
b1001 D"
1K"
0N"
0L"
0I"
b1000 G"
b111 !
b111 3
1.#
b111 B"
b11 ,#
b111 #
b111 (
b111 '
#8000
1y
1?"
1v
1c"
1<"
0m"
0j"
0g"
1v"
1s"
1p"
1`"
1r
07
1[
1!#
1|"
1y"
18"
1n
1T
0W
0x
1{
1!"
1$#
1'#
1*#
1-#
b1000 "
b1000 *
14"
0%#
0h"
0S
1w
0>"
1A"
b111 /
1E"
1j
b0 ##
0q"
b10 f"
0L
1p
1="
0b"
1e"
1f
0z"
b0 o"
1M
0P
0q
1t
16"
1a"
b0 x"
0k"
0K
1o
07"
1:"
1Z"
0t"
b10 i"
0D
1h
15"
1^"
1Y"
b0 r"
1E
0H
0i
1l
1."
1\"
1R"
b0 2
0n"
0C
1g
12"
1X"
1-"
1V"
1Q"
b10 l"
b0 8
0<
b111 \
1`
10"
b111 ""
1&"
1T"
b111 F"
1J"
b1111 .
b1111 6
1=
0@
b0 -
b0 Z
0a
1d
1,"
0(#
b0 ,
b0 ~
0'"
1*"
1P"
b0 +
b0 D"
0K"
1N"
0>
1b
b0 &#
1("
1L"
0;
1_
0}"
1%"
0+#
1I"
b1110 9
b1111 ]
b0 {"
b1111 #"
b0 )#
b1111 G"
b0 1
0w"
b0 0
0"#
b0 !
b0 3
0.#
b1 4
b0 X
b0 u"
b0 |
b0 ~"
b0 B"
b0 ,#
b1000 #
b1000 (
b1000 '
#9000
0$#
0'#
0*#
0-#
b1001 "
b1001 *
b10 ##
b110 /
0E"
1b"
0e"
0(#
0a"
b10 &#
0Z"
1["
0^"
0+#
0Y"
b10 )#
0R"
1S"
0V"
b1 !
b1 3
1.#
0Q"
b0 F"
0J"
b1111 +
b1111 D"
1K"
0N"
0L"
0I"
b1110 G"
b1 B"
b11 ,#
b1001 #
b1001 (
b1001 '
#10000
1c"
1`"
0!#
0|"
0y"
0$#
0'#
0*#
0-#
b1011 "
b1011 *
1\"
0%#
0!"
b100 /
0E"
1X"
b10 ##
1>"
0A"
1b"
0e"
0z"
0="
0a"
0T"
0(#
b10 x"
06"
0Z"
0P"
b10 &#
17"
0:"
1["
0^"
0}"
05"
0Y"
1+#
b10 {"
0."
0R"
b11 )#
1/"
02"
1S"
0V"
b1 0
1"#
0-"
1Q"
b0 ""
0&"
b1 F"
1J"
b1111 ,
b1111 ~
1'"
0*"
b1110 +
b1110 D"
0K"
1N"
0("
1L"
0%"
1I"
b1110 #"
b1101 G"
b10 !
b10 3
0.#
b1 |
b11 ~"
b10 B"
b0 ,#
b1010 #
b1010 (
b1010 '
#11000
b1 )#
0S"
0Q"
b0 F"
0J"
b1101 +
b1101 D"
1K"
0N"
0L"
0I"
b1100 G"
b11 !
b11 3
1.#
b11 B"
b11 ,#
b1011 #
b1011 (
b1011 '
#12000
1?"
1c"
1<"
1`"
0v"
0s"
0p"
0!#
0|"
0y"
18"
0[
0!"
0$#
0'#
0*#
0-#
b1111 "
b1111 *
0\"
14"
0%#
1x
0{
1>"
0A"
b0 /
0E"
0X"
b10 ##
0q"
0w
0="
1b"
0e"
00"
0z"
b10 o"
0p
06"
0a"
0,"
1(#
b10 x"
1q
0t
17"
0:"
0Z"
b11 &#
0t"
0o
05"
1["
0^"
1}"
b10 r"
0h
0."
1Y"
b11 {"
1i
0l
1/"
02"
1R"
b1 1
1w"
0g
1-"
1V"
1Q"
b0 \
0`
b1 ""
1&"
1T"
b11 F"
1J"
b1111 -
b1111 Z
1a
0d
b1110 ,
b1110 ~
0'"
1*"
1P"
b1100 +
b1100 D"
0K"
1N"
0b
1("
1L"
0_
1%"
0+#
1I"
b1110 ]
b1101 #"
b0 )#
b1011 G"
b10 0
0"#
b100 !
b100 3
0.#
b1 X
b11 u"
b10 |
b0 ~"
b100 B"
b0 ,#
b1100 #
b1100 (
b1100 '
#13000
b1 &#
0["
0Y"
b10 )#
0R"
1S"
0V"
0Q"
b0 F"
0J"
b1011 +
b1011 D"
1K"
0N"
0L"
0I"
b1010 G"
b101 !
b101 3
1.#
b101 B"
b11 ,#
b1101 #
b1101 (
b1101 '
#14000
b1 {"
0/"
0-"
1Q"
b0 ""
0&"
0T"
b1 F"
1J"
b1101 ,
b1101 ~
1'"
0*"
0P"
b1010 +
b1010 D"
0K"
1N"
0("
1L"
0%"
1+#
1I"
b1100 #"
b11 )#
b1001 G"
b11 0
1"#
b110 !
b110 3
0.#
b11 |
b11 ~"
b110 B"
b0 ,#
b1110 #
b1110 (
b1110 '
#15000
b1 )#
0S"
0Q"
b0 F"
0J"
b1001 +
b1001 D"
1K"
0N"
0L"
0I"
b1000 G"
b111 !
b111 3
1.#
b111 B"
b11 ,#
b1111 #
b1111 (
b1111 '
#16000
1%#
1?"
0c"
1<"
0`"
08"
04"
0["
0q"
1z"
1t"
0j
0f
0!#
0|"
0y"
0!"
0$#
0'#
0*#
0-#
b1 2
1n"
1>"
0A"
b11 ##
0E"
1m"
1j"
1g"
0v"
0s"
0p"
b111 "
b111 *
0="
1b"
0e"
17
b1000 /
0[
b11 x"
06"
1a"
0T
1W
1x
0{
17"
0:"
1Z"
1S
0w
15"
1^"
1Y"
b0 f"
1L
b10 o"
0p
1."
1\"
1R"
0M
1P
1q
0t
12"
1X"
1V"
1K
0o
10"
1T"
b0 i"
1D
b11 r"
0h
1,"
0(#
1P"
0E
1H
1i
0l
0/"
0S"
1?
1c
b0 &#
1)"
1M"
1C
1g
1-"
1Q"
1;
1_
0}"
1%"
0+#
1I"
b10 l"
b111 8
1<
b1 \
1`
b11 ""
1&"
b111 F"
1J"
b1111 9
b1101 ]
b0 {"
b1011 #"
b0 )#
b111 G"
b1 .
b1 6
1=
0@
b1111 -
b1111 Z
1a
0d
b1101 ,
b1101 ~
1'"
0*"
b1001 +
b1001 D"
1K"
0N"
b10 1
0w"
b100 0
0"#
b1000 !
b1000 3
0.#
0>
0b
0("
0L"
b0 4
b10 X
b10 u"
b100 |
b10 ~"
b1000 B"
b10 ,#
1:
1^
1$"
1H"
b0 #
b0 (
b1 $
b1 )
b1 5
b1 Y
b1 }
b1 C"
b1 &
b0 '
#17000
b11 ##
1b"
1a"
b0 &#
1Z"
0["
1^"
1Y"
b0 )#
1R"
0S"
1V"
1Q"
b1000 +
b1000 D"
0K"
1N"
b111 F"
1J"
1L"
0M"
0I"
b110 G"
b1001 !
b1001 3
1.#
b1001 B"
b1 ,#
b1 #
b1 (
b1 '
#18000
b1 ##
0b"
0a"
b11 x"
b10 &#
0Z"
17"
1["
0^"
15"
0Y"
b0 {"
1."
b1 F"
0R"
0/"
12"
1S"
0V"
1-"
0T"
b1100 ,
b1100 ~
0'"
1*"
b11 ""
1&"
0P"
b111 +
b111 D"
1K"
0N"
1("
0)"
0L"
1M"
0%"
1+#
1I"
b1010 #"
b11 )#
b101 G"
b101 0
1"#
b1010 !
b1010 3
0.#
b101 |
b1 ~"
b1010 B"
b10 ,#
b10 #
b10 (
b10 '
#19000
b11 )#
1S"
1Q"
b110 +
b110 D"
0K"
1N"
b1 F"
1J"
1L"
0M"
0I"
b100 G"
b1011 !
b1011 3
1.#
b1011 B"
b1 ,#
b11 #
b11 (
b11 '
#20000
b1 x"
07"
05"
1Y"
b11 r"
b1 ""
0."
0\"
b11 F"
1R"
1i
1/"
02"
0X"
0S"
1V"
1g
00"
1T"
b1110 -
b1110 Z
0a
1d
b1 \
1`
0,"
1(#
b1011 ,
b1011 ~
1'"
0*"
1P"
b101 +
b101 D"
1K"
0N"
1b
0c
b11 &#
0("
1)"
0L"
1M"
0_
1}"
1%"
0+#
1I"
b1100 ]
b11 {"
b1001 #"
b0 )#
b11 G"
b11 1
1w"
b110 0
0"#
b1100 !
b1100 3
0.#
b11 X
b1 u"
b110 |
b10 ~"
b1100 B"
b10 ,#
b100 #
b100 (
b100 '
#21000
b11 &#
1["
1Y"
b0 )#
1R"
0S"
1V"
1Q"
b100 +
b100 D"
0K"
1N"
b11 F"
1J"
1L"
0M"
0I"
b10 G"
b1101 !
b1101 3
1.#
b1101 B"
b1 ,#
b101 #
b101 (
b101 '
#22000
b1 &#
0["
0Y"
b11 {"
b1 F"
0R"
1/"
1S"
0V"
1-"
0T"
b1010 ,
b1010 ~
0'"
1*"
b1 ""
1&"
0P"
b11 +
b11 D"
1K"
0N"
1("
0)"
0L"
1M"
0%"
1+#
1I"
b1000 #"
b11 )#
b1 G"
b111 0
1"#
b1110 !
b1110 3
0.#
b111 |
b1 ~"
b1110 B"
b10 ,#
b110 #
b110 (
b110 '
#23000
b11 )#
1S"
1Q"
b10 +
b10 D"
0K"
1N"
b1 F"
1J"
1L"
0M"
0I"
b0 G"
b1111 !
b1111 3
1.#
b1111 B"
b1 ,#
b111 #
b111 (
b111 '
#24000
1["
1v"
1s"
1p"
0!#
0|"
0y"
1[
0$#
0'#
0*#
0-#
0!"
1{
0E"
1w
0A"
0x
0="
0e"
1p
1>"
1y
06"
1c"
1t
1?"
1v
1o
0:"
1`"
0q
1<"
1m"
1j"
1g"
b11 "
b11 *
b111 \
1h
18"
1r
b1100 /
17
0i
1l
14"
0%#
1n
0T
1W
1j
b10 ##
0h"
1S
1b"
1f
0z"
0q"
b0 f"
1L
0a"
b10 x"
b0 o"
0M
1P
17"
0Z"
0t"
0k"
1K
05"
0^"
1Y"
b0 r"
b0 i"
1D
b1 ""
0."
0\"
b11 F"
1R"
b0 2
0n"
0E
1H
1/"
02"
0X"
0S"
1V"
b0 l"
1C
00"
1T"
b0 .
b0 6
0=
1@
b111 8
1<
b1 -
b1 Z
1a
0d
0,"
1(#
b1111 ,
b1111 ~
1'"
0*"
1P"
b1101 +
b1101 D"
1K"
0N"
1>
0?
0b
1c
b11 &#
0("
1)"
0L"
1M"
0;
1_
1}"
1%"
0+#
1I"
b1110 9
b1111 ]
b11 {"
b1101 #"
b0 )#
b1011 G"
b1 1
1w"
b10 0
0"#
b100 !
b100 3
0.#
b1 4
b0 X
b10 u"
b10 |
b10 ~"
b100 B"
b10 ,#
b1000 #
b1000 (
b1000 '
#25000
b11 &#
1["
1Y"
b0 )#
1R"
0S"
1V"
1Q"
b1100 +
b1100 D"
0K"
1N"
b11 F"
1J"
1L"
0M"
0I"
b1010 G"
b101 !
b101 3
1.#
b101 B"
b1 ,#
b1001 #
b1001 (
b1001 '
#26000
b1 &#
0["
0Y"
b11 {"
b1 F"
0R"
1/"
1S"
0V"
1-"
0T"
b1110 ,
b1110 ~
0'"
1*"
b1 ""
1&"
0P"
b1011 +
b1011 D"
1K"
0N"
1("
0)"
0L"
1M"
0%"
1+#
1I"
b1100 #"
b11 )#
b1001 G"
b11 0
1"#
b110 !
b110 3
0.#
b11 |
b1 ~"
b110 B"
b10 ,#
b1010 #
b1010 (
b1010 '
#27000
b11 )#
1S"
1Q"
b1010 +
b1010 D"
0K"
1N"
b1 F"
1J"
1L"
0M"
0I"
b1000 G"
b111 !
b111 3
1.#
b111 B"
b1 ,#
b1011 #
b1011 (
b1011 '
#28000
1!#
1|"
1y"
0$#
0'#
0*#
0-#
1!"
0E"
1A"
1="
0e"
0>"
0a"
16"
1b"
1?"
0Z"
1:"
1c"
1<"
15"
0^"
07"
1`"
1v"
1s"
1p"
b1 "
b1 *
b111 ""
1."
1\"
18"
b1110 /
1[
0/"
12"
1X"
14"
0%#
0x
1{
10"
b10 ##
0q"
1w
1,"
0(#
0z"
b0 o"
1p
b10 &#
b0 x"
0q
1t
1["
0}"
0t"
1o
0Y"
b0 {"
b0 r"
1h
b1 F"
0R"
b0 1
0w"
0i
1l
1S"
0V"
1g
0T"
b0 -
b0 Z
0a
1d
b111 \
1`
b1 ,
b1 ~
1'"
0*"
0P"
b1111 +
b1111 D"
1K"
0N"
1b
0c
0("
1)"
0L"
1M"
0_
1%"
1+#
1I"
b1110 ]
b1111 #"
b11 )#
b1101 G"
b1 0
1"#
b10 !
b10 3
0.#
b1 X
b1 u"
b0 |
b10 ~"
b10 B"
b10 ,#
b1100 #
b1100 (
b1100 '
#29000
b11 )#
1S"
1Q"
b1110 +
b1110 D"
0K"
1N"
b1 F"
1J"
1L"
0M"
0I"
b1100 G"
b11 !
b11 3
1.#
b11 B"
b1 ,#
b1101 #
b1101 (
b1101 '
#30000
1$#
1'#
1*#
1-#
1E"
1e"
1a"
0b"
1Z"
1c"
1^"
1`"
1Y"
0["
1!#
1|"
1y"
b0 "
b0 *
b111 F"
1R"
1\"
0%#
b1111 /
1!"
0S"
1V"
1X"
b0 ##
0>"
1A"
1T"
0z"
1="
1P"
0(#
b0 x"
16"
b0 &#
07"
1:"
0+#
0}"
15"
b0 )#
b0 {"
1."
b0 0
0"#
0/"
12"
1-"
b0 ,
b0 ~
0'"
1*"
b111 ""
1&"
b1 +
b1 D"
1K"
0N"
1("
0)"
0L"
1M"
0%"
1I"
b1110 #"
b1111 G"
b1 !
b1 3
1.#
b1 |
b1 ~"
b0 B"
b10 ,#
b1110 #
b1110 (
b1110 '
#31000
1$#
1'#
1*#
1-#
b0 "
b0 *
b0 ##
b1111 /
1E"
0b"
1e"
0(#
1a"
b0 &#
1Z"
0["
1^"
0+#
1Y"
b0 )#
1R"
b0 !
b0 3
0.#
0S"
1V"
1Q"
b0 +
b0 D"
0K"
1N"
b111 F"
1J"
1L"
0M"
0I"
b1110 G"
b1 B"
b1 ,#
b1111 #
b1111 (
b1111 '
