verilog/VLSI_experiment/2w/MUX/MUX_8to1_behav.v
// 8 to 1 MUX behavior

module MUX_8to1_behav (out, a[7:0], s[2:0]);

    output reg out;
    input [7:0]a;
    input [2:0]s;

    always@(a[7:0], s[2:0]) begin
        case(s[2:0])
            3'b000 : out = a[0];
            3'b001 : out = a[1];
            3'b010 : out = a[2];
            3'b011 : out = a[3];
            3'b100 : out = a[4];
            3'b101 : out = a[5];
            3'b110 : out = a[6];
            3'b111 : out = a[7];
            default: out = 3'b000;
        endcase

    end


endmodule

verilog/VLSI_experiment/2w/MUX/MUX_2to1.v
// 2 to 1 mux

module MUX_2to1 (out, i1, i2, s);

    output out;     // output zz
    input i1, i2;   // input 8bits
    input s;   // select 3bits

    wire andout[1:0];  // and gate output

    and a0(andout[0], ~s, i1);
    and a1(andout[1],  s, i2);

    or or1(out, andout[0], andout[1]);

endmodule

verilog/VLSI_experiment/2w/MUX/MUX_4to1.v
// 4 to 1 mux

module MUX_4to1 (out, a[3:0], s[1:0]);

    output out;     // output zz
    input [3:0]a;   // input 8bits
    input [1:0]s;   // select 3bits

    wire andout[3:0];  // and gate output

    and a0(andout[0], ~s[1], ~s[0], a[0]);
    and a1(andout[1], ~s[1],  s[0], a[1]);
    and a2(andout[2],  s[1], ~s[0], a[2]);
    and a3(andout[3],  s[1],  s[0], a[3]);

    or or1(out, andout[0], andout[1], andout[2], andout[3]);

endmodule

verilog/VLSI_experiment/2w/MUX/MUX_8to1_gate.v
// 8 to 1 mux

`include "MUX_2to1.v"
`include "MUX_4to1.v"

module MUX_8to1_gate (out, a[7:0], s[2:0]);

    output out;     // output 
    input [7:0]a;   // input 8bits
    input [2:0]s;   // select 3bits

    wire mux_out[1:0];  // and gate output

    MUX_4to1 mux4_1(mux_out[0], a[3:0], s[1:0]);
    MUX_4to1 mux4_2(mux_out[1], a[7:4], s[1:0]);
    MUX_2to1 mux2_1(out, mux_out[0], mux_out[1], s[2]);

endmodule

verilog/VLSI_experiment/2w/MUX/MUX_tb.v
`include "MUX_8to1_gate.v"
`include "MUX_8to1_behav.v"
`timescale 1ns/10ps

module MUX_tb;
    
    reg [7:0]in;
    reg [2:0]s;
    wire gate_out, behav_out;
    integer i = 0;

    MUX_8to1_gate mux_gate (gate_out, in, s[2:0]);
    MUX_8to1_behav mux_behav(behav_out, in, s[2:0]);

    initial begin
        $dumpfile("MUX_tb.vcd");
        $dumpvars(0,MUX_tb);
        in = 8'b10101010;
        s = 3'b000;
        #10;
        for(i = 0; i<7; i++) begin
            s = s + 3'b001;
            #10;
        end

        for(i = 8; i>1; i--) begin
            s = s - 3'b001;
            #10;
        end

        $finish;
        
    end
    
endmodule

verilog/VLSI_experiment/2w/MUX/MUX_tb.vcd
$date
	Fri Mar 17 19:35:48 2023
$end
$version
	Icarus Verilog
$end
$timescale
	10ps
$end
$scope module MUX_tb $end
$var wire 1 ! gate_out $end
$var wire 1 " behav_out $end
$var reg 8 # in [7:0] $end
$var reg 3 $ s [2:0] $end
$var integer 32 % i [31:0] $end
$scope module mux_behav $end
$var wire 8 & a [7:0] $end
$var wire 3 ' s [2:0] $end
$var reg 1 " out $end
$upscope $end
$scope module mux_gate $end
$var wire 8 ( a [7:0] $end
$var wire 3 ) s [2:0] $end
$var wire 1 ! out $end
$scope module mux2_1 $end
$var wire 1 ! out $end
$var wire 1 * s $end
$var wire 1 + i2 $end
$var wire 1 , i1 $end
$upscope $end
$scope module mux4_1 $end
$var wire 4 - a [3:0] $end
$var wire 1 , out $end
$var wire 2 . s [1:0] $end
$upscope $end
$scope module mux4_2 $end
$var wire 4 / a [3:0] $end
$var wire 1 + out $end
$var wire 2 0 s [1:0] $end
$upscope $end
$upscope $end
$upscope $end
$enddefinitions $end
#0
$dumpvars
b0 0
b1010 /
b0 .
b1010 -
0,
0+
0*
b0 )
b10101010 (
b0 '
b10101010 &
b0 %
b0 $
b10101010 #
0"
0!
$end
#1000
1!
1,
1+
1"
b1 .
b1 0
b1 $
b1 '
b1 )
#2000
0!
0,
0+
0"
b10 .
b10 0
b10 $
b10 '
b10 )
b1 %
#3000
1!
1,
1+
1"
b11 .
b11 0
b11 $
b11 '
b11 )
b10 %
#4000
0!
0,
0+
0"
b0 .
b0 0
1*
b100 $
b100 '
b100 )
b11 %
#5000
1!
1,
1+
1"
b1 .
b1 0
b101 $
b101 '
b101 )
b100 %
#6000
0!
0,
0+
0"
b10 .
b10 0
b110 $
b110 '
b110 )
b101 %
#7000
1!
1,
1+
1"
b11 .
b11 0
b111 $
b111 '
b111 )
b110 %
#8000
0!
0,
0+
0"
b10 .
b10 0
b110 $
b110 '
b110 )
b1000 %
#9000
1!
1,
1+
1"
b1 .
b1 0
b101 $
b101 '
b101 )
b111 %
#10000
0!
0,
0+
0"
b0 .
b0 0
b100 $
b100 '
b100 )
b110 %
#11000
1!
1,
1+
1"
b11 .
b11 0
0*
b11 $
b11 '
b11 )
b101 %
#12000
0!
0,
0+
0"
b10 .
b10 0
b10 $
b10 '
b10 )
b100 %
#13000
1!
1,
1+
1"
b1 .
b1 0
b1 $
b1 '
b1 )
b11 %
#14000
0!
0,
0+
0"
b0 .
b0 0
b0 $
b0 '
b0 )
b10 %
#15000
b1 %
