verilog/VLSI_experiment/counter/D_FF.v
module D_FF(q, d, clk, reset);

output q;
input d, clk, reset;

reg q;

always @ (negedge clk)  // negative edge일 때 아래 실행
begin 
    if (reset) // rest이 1이면 q에 0을 넣는다.
        q <= 1'b0;
    else 
        q <= d;
end

endmodule

verilog/VLSI_experiment/1w/T_FF.v
`include "D_FF.v"

module T_FF (q, clk, reset);

output q;
input clk, reset;

wire d;

D_FF dff0 (q, d, clk, reset);
not n1(d, q);

endmodule

verilog/VLSI_experiment/counter/ripple_carry_counter_5bits.v
// 문제점 : 클락이 동기화가 되어 있지 않아서 모든 플립플랍의 결과가 밀려서 출력되는 경우가 있다. 항상 동시에 변화하지 않을 수도 있다. 
// 동기화된 클락을 사용하지 않아서 발생하는 문제.

`include "T_FF.v"

module ripple_carry_counter_5bits (q, clk, reset);

output [4:0] q;
input clk, reset;
T_FF tff0 (q[0], clk, reset);
T_FF tff1 (q[1], q[0], reset);
T_FF tff2 (q[2], q[1], reset);
T_FF tff3 (q[3], q[2], reset);
T_FF tff4 (q[4], q[3], reset);

endmodule

verilog/VLSI_experiment/counter/r_counter_tb.v
`include "ripple_carry_counter_5bits.v"
`timescale 100ns/1ns

module a_counter_tb;

reg clk;
reg reset;
wire [4:0] q;


// instatiate the desian block 
ripple_carry_counter_5bits r1 (.clk(clk), .reset(reset), .q(q));

// Control the clk signal that drives the design block.
// cycle time = 10

initial
    clk = 1'b0; // set clk to 0
always
    #5 clk = ~clk; // toggle clk every 5 time units

// Control the reset signal that drives the design block.
// reset is asserted from 0 to 20 and from 200 to 220.
initial
begin
$dumpfile("a_counter_tb.vcd");
$dumpvars(0,a_counter_tb);

             reset = 1'b1;
    #15;     reset = 1'b0;
    #180;    reset = 1'b1;
    #10;     reset = 1'b0;
    #20;     $finish;  // terminate the simulation

end

// Monitor the outputs initial
//initial
//$monitor ($time, " Output q = %d", q);
endmodule

verilog/VLSI_experiment/1w/a_counter_tb.vcd
$date
	Sat Mar 11 17:09:53 2023
$end
$version
	Icarus Verilog
$end
$timescale
	10ps
$end
$scope module a_counter_tb $end
$var wire 5 ! q [4:0] $end
$var reg 1 " clk $end
$var reg 1 # reset $end
$scope module r1 $end
$var wire 1 " clk $end
$var wire 1 # reset $end
$var reg 5 $ q [4:0] $end
$upscope $end
$upscope $end
$enddefinitions $end
#0
$dumpvars
b0 $
1#
0"
b0 !
$end
#500
1"
#1000
0"
#1500
1"
0#
#2000
b1 !
b1 $
0"
#2500
1"
#3000
b10 !
b10 $
0"
#3500
1"
#4000
b11 !
b11 $
0"
#4500
1"
#5000
b100 !
b100 $
0"
#5500
1"
#6000
b101 !
b101 $
0"
#6500
1"
#7000
b110 !
b110 $
0"
#7500
1"
#8000
b111 !
b111 $
0"
#8500
1"
#9000
b1000 !
b1000 $
0"
#9500
1"
#10000
b1001 !
b1001 $
0"
#10500
1"
#11000
b1010 !
b1010 $
0"
#11500
1"
#12000
b1011 !
b1011 $
0"
#12500
1"
#13000
b1100 !
b1100 $
0"
#13500
1"
#14000
b1101 !
b1101 $
0"
#14500
1"
#15000
b1110 !
b1110 $
0"
#15500
1"
#16000
b1111 !
b1111 $
0"
#16500
1"
#17000
b10000 !
b10000 $
0"
#17500
1"
#18000
b10001 !
b10001 $
0"
#18500
1"
#19000
b10010 !
b10010 $
0"
#19500
1"
1#
#20000
b0 !
b0 $
0"
#20500
1"
0#
#21000
b1 !
b1 $
0"
#21500
1"
#22000
b10 !
b10 $
0"
