verilog/digitalsystem6/sr.v
module sr_latch(s, r, Q, nQ);
  input s,r;
  output Q, nQ;
  assign Q = ~ (s & nQ);
  assign nQ = ~ (r & Q);
endmodule

verilog/digital_system_experiment/digitalsystem6/d_ff.v
`include "sr.v"
module D_FF(CLK, D, set, Q, nQ);

  input CLK, D, set;
  output Q, nQ;
  wire w1, w2, w3,  w4;  
  
  sr_latch L1(w4|set, CLK&(~set), w1, w2);
  sr_latch L2((CLK&w2)|set, D&(~set), w3,  w4);
  sr_latch L3(w2, w3, Q, nQ);

endmodule

verilog/digital_system_experiment/digitalsystem6/d_ff_tb.v
`include "d_ff.v"
`timescale 100ps/1ps
module d_ff_tb;

reg clk, D, set;
wire Q, nQ;

always #2.5 clk <= ~clk;

D_FF d_ff(clk,D,set,Q,nQ);

initial begin
    $dumpfile("d_ff_tb.vcd");
    $dumpvars(0,d_ff_tb);
    clk <= 1; set <= 0;
    D <= 0; #10;
    D <= 0; #10;
    D <= 1; #10;
    D <= 1; #10;
    $finish;
    end


endmodule

verilog/digital_system_experiment/digitalsystem6/d_ff_tb.vcd
$date
	Tue Oct 15 16:17:27 2019
$end
$version
	Icarus Verilog
$end
$timescale
	1ps
$end
$scope module d_ff_tb $end
$var wire 1 ! nQ $end
$var wire 1 " Q $end
$var reg 1 # D $end
$var reg 1 $ clk $end
$var reg 1 % set $end
$scope module d_ff $end
$var wire 1 $ CLK $end
$var wire 1 # D $end
$var wire 1 % set $end
$var wire 1 & w4 $end
$var wire 1 ' w3 $end
$var wire 1 ( w2 $end
$var wire 1 ) w1 $end
$var wire 1 ! nQ $end
$var wire 1 " Q $end
$scope module L1 $end
$var wire 1 ) Q $end
$var wire 1 ( nQ $end
$var wire 1 * r $end
$var wire 1 + s $end
$upscope $end
$scope module L2 $end
$var wire 1 ' Q $end
$var wire 1 & nQ $end
$var wire 1 , r $end
$var wire 1 - s $end
$upscope $end
$scope module L3 $end
$var wire 1 " Q $end
$var wire 1 ! nQ $end
$var wire 1 ' r $end
$var wire 1 ( s $end
$upscope $end
$upscope $end
$upscope $end
$enddefinitions $end
#0
$dumpvars
x-
0,
1+
1*
x)
x(
x'
1&
0%
1$
0#
x"
x!
$end
#250
0)
1'
1(
0-
0*
0$
#500
0"
1!
0'
1-
1*
1$
#750
1'
0-
0*
0$
#1000
0'
1-
1*
1$
#1250
1'
0-
0*
0$
#1500
0'
1-
1*
1$
#1750
1'
0-
0*
0$
#2000
0!
1"
0(
1)
0+
0&
0-
1*
1,
1$
1#
#2250
1(
0*
0$
#2500
0(
0-
1*
1$
#2750
1(
0*
0$
#3000
0(
0-
1*
1$
#3250
1(
0*
0$
#3500
0(
0-
1*
1$
#3750
1(
0*
0$
#4000
0(
0-
1*
1$
