verilog/digitalsystem6/sr.v
module sr_latch(s, r, Q, nQ);
  input s,r;
  output Q, nQ;
  assign Q = ~ (s & nQ);
  assign nQ = ~ (r & Q);
endmodule

verilog/digital_system_experiment/digitalsystem6/d_ff.v
`include "sr.v"
module D_FF(CLK, D, set, Q, nQ);

  input CLK, D, set;
  output Q, nQ;
  wire w1, w2, w3,  w4;  
  
  sr_latch L1(w4|set, CLK&(~set), w1, w2);
  sr_latch L2((CLK&w2)|set, D&(~set), w3,  w4);
  sr_latch L3(w2, w3, Q, nQ);

endmodule

verilog/digitalsystem6/jk.v
`include "d_ff.v"

module JK_FF(CLK, set, J, K, Q, nQ);
  input CLK, J, K, set;
  output Q,  nQ;
  wire w1;
  assign w1 = (J & nQ) | (~K & Q);
  D_FF F1(~CLK, w1, set, Q, nQ);
endmodule

verilog/digitalsystem6/jk_tb.v
`include "jk.v"
`timescale 100ps/1ps
module jk_tb;

reg clk, set, j, k;
wire Q, nQ;


always #2.5 clk <= ~clk;

 JK_FF jk_ff(clk,set,j,k,Q,nQ);

initial begin
    $dumpfile("jk_tb.vcd");
    $dumpvars(0,jk_tb);
    clk <= 1; set <= 0;
    j<= 0; k<= 0; #10;
    j<= 0; k<= 1; #10;
    j<= 1; k<= 0; #10;
    j<= 1; k<= 1; #10;
    j<= 0; k<= 0; #10;
    j<= 0; k<= 1; #10;
    j<= 1; k<= 0; #10;
    j<= 1; k<= 1; #10;
    $finish;
    end


endmodule

verilog/digital_system_experiment/digitalsystem6/jk_tb.vcd
$date
	Tue Oct 15 16:23:08 2019
$end
$version
	Icarus Verilog
$end
$timescale
	1ps
$end
$scope module jk_tb $end
$var wire 1 ! nQ $end
$var wire 1 " Q $end
$var reg 1 # clk $end
$var reg 1 $ j $end
$var reg 1 % k $end
$var reg 1 & set $end
$scope module jk_ff $end
$var wire 1 # CLK $end
$var wire 1 $ J $end
$var wire 1 % K $end
$var wire 1 & set $end
$var wire 1 ' w1 $end
$var wire 1 ! nQ $end
$var wire 1 " Q $end
$scope module F1 $end
$var wire 1 ( CLK $end
$var wire 1 ' D $end
$var wire 1 & set $end
$var wire 1 ) w4 $end
$var wire 1 * w3 $end
$var wire 1 + w2 $end
$var wire 1 , w1 $end
$var wire 1 ! nQ $end
$var wire 1 " Q $end
$scope module L1 $end
$var wire 1 , Q $end
$var wire 1 + nQ $end
$var wire 1 - r $end
$var wire 1 . s $end
$upscope $end
$scope module L2 $end
$var wire 1 * Q $end
$var wire 1 ) nQ $end
$var wire 1 / r $end
$var wire 1 0 s $end
$upscope $end
$scope module L3 $end
$var wire 1 " Q $end
$var wire 1 ! nQ $end
$var wire 1 * r $end
$var wire 1 + s $end
$upscope $end
$upscope $end
$upscope $end
$upscope $end
$enddefinitions $end
#0
$dumpvars
00
x/
x.
0-
x,
1+
1*
x)
0(
x'
0&
0%
0$
1#
x"
x!
$end
#250
x*
x+
x0
1-
1(
0#
#500
1*
1+
00
0-
0(
1#
#750
x*
x+
x0
1-
1(
0#
#1000
0,
1.
1)
1*
1+
0/
00
0'
0-
0(
1#
1%
#1250
0"
1!
0*
10
1-
1(
0#
#1500
1*
00
0-
0(
1#
#1750
0*
10
1-
1(
0#
#2000
1,
0.
0)
1*
00
1/
0-
1'
0(
1#
0%
1$
#2250
0!
1"
0+
00
1-
1(
0#
#2500
1+
0-
0(
1#
#2750
0+
00
1-
1(
0#
#3000
0,
1.
1)
1+
0/
0'
0-
0(
1#
1%
#3250
1/
0"
1'
1!
0*
10
1-
1(
0#
#3500
1,
0.
0)
1*
00
0-
0(
1#
#3750
1.
1)
0/
0'
0!
1"
0+
00
1-
1(
0#
#4000
0.
1,
0)
1+
1/
1'
0-
0(
1#
0%
0$
#4250
0+
00
1-
1(
0#
#4500
1+
0-
0(
1#
#4750
0+
00
1-
1(
0#
#5000
0,
1.
1)
1+
0/
0'
0-
0(
1#
1%
#5250
0"
1!
0*
10
1-
1(
0#
#5500
1*
00
0-
0(
1#
#5750
0*
10
1-
1(
0#
#6000
1,
0.
0)
1*
00
1/
0-
1'
0(
1#
0%
1$
#6250
0!
1"
0+
00
1-
1(
0#
#6500
1+
0-
0(
1#
#6750
0+
00
1-
1(
0#
#7000
0,
1.
1)
1+
0/
0'
0-
0(
1#
1%
#7250
1/
0"
1'
1!
0*
10
1-
1(
0#
#7500
1,
0.
0)
1*
00
0-
0(
1#
#7750
1.
1)
0/
0'
0!
1"
0+
00
1-
1(
0#
#8000
0,
1+
0-
0(
1#
