verilog/digital_system_experiment/digitalsystem5/line_decoder.v
module line_decoder(A,S);

input [3:0] A;
output reg[3:0] S;
reg dummy;

always@(A)
    case(A)
    4'b0000 : S <= 4'b0000;
    4'b0001 : S <= 4'b0001;
    4'b0010 : S <= 4'b0010;
    4'b0011 : S <= 4'b0011;
    4'b0100 : S <= 4'b0100;
    4'b0101 : S <= 4'b1000;
    4'b0110 : S <= 4'b1001;
    4'b0111 : S <= 4'b1010;
    4'b1000 : S <= 4'b1011;
    4'b1001 : S <= 4'b1100;
    default : S <= {dummy};
    endcase
endmodule

verilog/digital_system_experiment/digitalsystem5/line_decoder_tb.v
`include "line_decoder.v"
module line_decoder_tb;

reg [3:0]A;
wire [3:0]B;
integer i;

line_decoder ld(A,B);
initial begin
    $dumpfile("line_decoder_tb.vcd");
    $dumpvars(0,line_decoder_tb); // 여기에는 모듈 이름 써야됨. 파일 제목 x
    for (i = 4'b0000; i <= 4'b1111; i = i+1)
    begin
        A <= i;
        #10;
    end
    $finish;
end

endmodule

verilog/digitalsystem5/line_decoder_tb.vcd
$date
	Mon Oct  7 21:06:53 2019
$end
$version
	Icarus Verilog
$end
$timescale
	1s
$end
$scope module line_decoder_tb $end
$var wire 4 ! B [3:0] $end
$var reg 4 " A [3:0] $end
$var integer 32 # i [31:0] $end
$scope module ld $end
$var wire 4 $ A [3:0] $end
$var reg 4 % S [3:0] $end
$var reg 1 & dummy $end
$upscope $end
$upscope $end
$enddefinitions $end
#0
$dumpvars
x&
b0 %
b0 $
b0 #
b0 "
b0 !
$end
#10
b1 !
b1 %
b1 "
b1 $
b1 #
#20
b10 !
b10 %
b10 "
b10 $
b10 #
#30
b11 !
b11 %
b11 "
b11 $
b11 #
#40
b100 !
b100 %
b100 "
b100 $
b100 #
#50
b1000 !
b1000 %
b101 "
b101 $
b101 #
#60
b1001 !
b1001 %
b110 "
b110 $
b110 #
#70
b1010 !
b1010 %
b111 "
b111 $
b111 #
#80
b1011 !
b1011 %
b1000 "
b1000 $
b1000 #
#90
b1100 !
b1100 %
b1001 "
b1001 $
b1001 #
#100
b0x !
b0x %
b1010 "
b1010 $
b1010 #
#110
b1011 "
b1011 $
b1011 #
#120
b1100 "
b1100 $
b1100 #
#130
b1101 "
b1101 $
b1101 #
#140
b1110 "
b1110 $
b1110 #
#150
b1111 "
b1111 $
b1111 #
#160
b10000 #
